Workbook

Sheet Amortization Table
B2: Acquisition Loan | H2: Refinance / Supplemental Loan
B4: Month | C4: Beg Bal | D4: Interest | E4: Principal | F4: End Bal | H4: Month | I4: Beg Bal | J4: Interest | K4: Principal | L4: End Bal
B5: 1 | C5: ='Executive Summary'!C24 -> 5200000 | D5: ='Debt Financing'!$D$3/12*C5 -> 21016.667 | E5: =IF(B5<='Debt Financing'!$D$4,0,'Debt Financing'!$D$7/12-D5) -> 0 | F5: =C5-E5 -> 5200000 | H5: 1 | I5: ='Executive Summary'!$L$18 -> 0 | J5: ='Debt Financing'!$D$27/12*I5 -> 0 | K5: =IF('Executive Summary'!$L$18=0,0,'Debt Financing'!$D$30/12-J5) -> 0 | L5: =I5-K5 -> 0
B6: =+B5+1 -> 2 | C6: =F5 -> 5200000 | D6: ='Debt Financing'!$D$3/12*C6 -> 21016.667 | E6: =IF(B6<='Debt Financing'!$D$4,0,'Debt Financing'!$D$7/12-D6) -> 0 | F6: =C6-E6 -> 5200000 | H6: =+H5+1 -> 2 | I6: =L5 -> 0 | J6: ='Debt Financing'!$D$27/12*I6 -> 0 | K6: =IF('Executive Summary'!$L$18=0,0,'Debt Financing'!$D$30/12-J6) -> 0 | L6: =I6-K6 -> 0
B7: =+B6+1 -> 3 | C7: =F6 -> 5200000 | D7: ='Debt Financing'!$D$3/12*C7 -> 21016.667 | E7: =IF(B7<='Debt Financing'!$D$4,0,'Debt Financing'!$D$7/12-D7) -> 0 | F7: =C7-E7 -> 5200000 | H7: =+H6+1 -> 3 | I7: =L6 -> 0 | J7: ='Debt Financing'!$D$27/12*I7 -> 0 | K7: =IF('Executive Summary'!$L$18=0,0,'Debt Financing'!$D$30/12-J7) -> 0 | L7: =I7-K7 -> 0
B8: =+B7+1 -> 4 | C8: =F7 -> 5200000 | D8: ='Debt Financing'!$D$3/12*C8 -> 21016.667 | E8: =IF(B8<='Debt Financing'!$D$4,0,'Debt Financing'!$D$7/12-D8) -> 0 | F8: =C8-E8 -> 5200000 | H8: =+H7+1 -> 4 | I8: =L7 -> 0 | J8: ='Debt Financing'!$D$27/12*I8 -> 0 | K8: =IF('Executive Summary'!$L$18=0,0,'Debt Financing'!$D$30/12-J8) -> 0 | L8: =I8-K8 -> 0
B9: =+B8+1 -> 5 | C9: =F8 -> 5200000 | D9: ='Debt Financing'!$D$3/12*C9 -> 21016.667 | E9: =IF(B9<='Debt Financing'!$D$4,0,'Debt Financing'!$D$7/12-D9) -> 0 | F9: =C9-E9 -> 5200000 | H9: =+H8+1 -> 5 | I9: =L8 -> 0 | J9: ='Debt Financing'!$D$27/12*I9 -> 0 | K9: =IF('Executive Summary'!$L$18=0,0,'Debt Financing'!$D$30/12-J9) -> 0 | L9: =I9-K9 -> 0
B10: =+B9+1 -> 6 | C10: =F9 -> 5200000 | D10: ='Debt Financing'!$D$3/12*C10 -> 21016.667 | E10: =IF(B10<='Debt Financing'!$D$4,0,'Debt Financing'!$D$7/12-D10) -> 0 | F10: =C10-E10 -> 5200000 | H10: =+H9+1 -> 6 | I10: =L9 -> 0 | J10: ='Debt Financing'!$D$27/12*I10 -> 0 | K10: =IF('Executive Summary'!$L$18=0,0,'Debt Financing'!$D$30/12-J10) -> 0 | L10: =I10-K10 -> 0
B11: =+B10+1 -> 7 | C11: =F10 -> 5200000 | D11: ='Debt Financing'!$D$3/12*C11 -> 21016.667 | E11: =IF(B11<='Debt Financing'!$D$4,0,'Debt Financing'!$D$7/12-D11) -> 0 | F11: =C11-E11 -> 5200000 | H11: =+H10+1 -> 7 | I11: =L10 -> 0 | J11: ='Debt Financing'!$D$27/12*I11 -> 0 | K11: =IF('Executive Summary'!$L$18=0,0,'Debt Financing'!$D$30/12-J11) -> 0 | L11: =I11-K11 -> 0
B12: =+B11+1 -> 8 | C12: =F11 -> 5200000 | D12: ='Debt Financing'!$D$3/12*C12 -> 21016.667 | E12: =IF(B12<='Debt Financing'!$D$4,0,'Debt Financing'!$D$7/12-D12) -> 0 | F12: =C12-E12 -> 5200000 | H12: =+H11+1 -> 8 | I12: =L11 -> 0 | J12: ='Debt Financing'!$D$27/12*I12 -> 0 | K12: =IF('Executive Summary'!$L$18=0,0,'Debt Financing'!$D$30/12-J12) -> 0 | L12: =I12-K12 -> 0
B13: =+B12+1 -> 9 | C13: =F12 -> 5200000 | D13: ='Debt Financing'!$D$3/12*C13 -> 21016.667 | E13: =IF(B13<='Debt Financing'!$D$4,0,'Debt Financing'!$D$7/12-D13) -> 0 | F13: =C13-E13 -> 5200000 | H13: =+H12+1 -> 9 | I13: =L12 -> 0 | J13: ='Debt Financing'!$D$27/12*I13 -> 0 | K13: =IF('Executive Summary'!$L$18=0,0,'Debt Financing'!$D$30/12-J13) -> 0 | L13: =I13-K13 -> 0
B14: =+B13+1 -> 10 | C14: =F13 -> 5200000 | D14: ='Debt Financing'!$D$3/12*C14 -> 21016.667 | E14: =IF(B14<='Debt Financing'!$D$4,0,'Debt Financing'!$D$7/12-D14) -> 0 | F14: =C14-E14 -> 5200000 | H14: =+H13+1 -> 10 | I14: =L13 -> 0 | J14: ='Debt Financing'!$D$27/12*I14 -> 0 | K14: =IF('Executive Summary'!$L$18=0,0,'Debt Financing'!$D$30/12-J14) -> 0 | L14: =I14-K14 -> 0
B15: =+B14+1 -> 11 | C15: =F14 -> 5200000 | D15: ='Debt Financing'!$D$3/12*C15 -> 21016.667 | E15: =IF(B15<='Debt Financing'!$D$4,0,'Debt Financing'!$D$7/12-D15) -> 0 | F15: =C15-E15 -> 5200000 | H15: =+H14+1 -> 11 | I15: =L14 -> 0 | J15: ='Debt Financing'!$D$27/12*I15 -> 0 | K15: =IF('Executive Summary'!$L$18=0,0,'Debt Financing'!$D$30/12-J15) -> 0 | L15: =I15-K15 -> 0
B16: =+B15+1 -> 12 | C16: =F15 -> 5200000 | D16: ='Debt Financing'!$D$3/12*C16 -> 21016.667 | E16: =IF(B16<='Debt Financing'!$D$4,0,'Debt Financing'!$D$7/12-D16) -> 0 | F16: =C16-E16 -> 5200000 | H16: =+H15+1 -> 12 | I16: =L15 -> 0 | J16: ='Debt Financing'!$D$27/12*I16 -> 0 | K16: =IF('Executive Summary'!$L$18=0,0,'Debt Financing'!$D$30/12-J16) -> 0 | L16: =I16-K16 -> 0
B17: =+B16+1 -> 13 | C17: =F16 -> 5200000 | D17: ='Debt Financing'!$D$3/12*C17 -> 21016.667 | E17: =IF(B17<='Debt Financing'!$D$4,0,'Debt Financing'!$D$7/12-D17) -> 0 | F17: =C17-E17 -> 5200000 | H17: =+H16+1 -> 13 | I17: =L16 -> 0 | J17: ='Debt Financing'!$D$27/12*I17 -> 0 | K17: =IF('Executive Summary'!$L$18=0,0,'Debt Financing'!$D$30/12-J17) -> 0 | L17: =I17-K17 -> 0
... B124: =+B123+1 -> 120 | C124: =F123 -> 4481492.5 | D124: ='Debt Financing'!$D$3/12*C124 -> 18112.699 | E124: =IF(B124<='Debt Financing'!$D$4,0,'Debt Financing'!$D$7/12-D124) -> 10207.049 | F124: =C124-E124 -> 4471285.4 | H124: =+H123+1 -> 120 | I124: =L123 -> 0 | J124: ='Debt Financing'!$D$27/12*I124 -> 0 | K124: =IF('Executive Summary'!$L$18=0,0,'Debt Financing'!$D$30/12-J124) -> 0 | L124: =I124-K124 -> 0

Sheet Drop-down List(s)
B2: Closing | D2: Max CF | F2: Yes
B3: Construction | D3: Max IRR | F3: No
B4: Lease-Up
B5: Stabilized
B6: Refinance
B7: Sale

Sheet Executive Summary
B2: Riverhill TH
B4: Property Details: | H4: Growth Assumptions: | K4: Debt Financing Assumptions: | N4: Equity Contributions: | O4: % | P4: Amount
B5: Property Name | C5: Riverhill TH | H5: Rent Growth (Year 1) | I5: ='Cignal Market Read'!$C$43 -> 0.0066 | K5: Acquisition Loan Proceeds | L5: ='Debt Financing'!D17 -> 5200000 | N5: LP Equity | O5: =1-O6 -> 0.9 | P5: =O5*$P$7 -> 1873961.1
B6: Address | C6: 3017 Limestone Drive | H6: Rent Growth (Year 2) | I6: ='Cignal Market Read'!$C$44 -> 0.0326 | K6: Loan-to-Purchase Price | L6: =IFERROR(L5/C30,0) -> 0.78490566 | N6: GP Equity | O6: 0.1 | P6: =O6*$P$7 -> 208217.9
B7: City, State | C7: Louisville, TN | H7: Rent Growth (Subsequent) | I7: ='Cignal Market Read'!$C$45 -> 0.03 | K7: Loan-to-Total Cost | L7: =L5/I23 -> 0.74198266 | N7: Total Equity | O7: =SUM(O5:O6) -> 1 | P7: =C33-C24 -> 2082179
B8: MSA | C8: Knoxville | H8: Other Growth (Year 1) | I8: 0.02 | K8: Interest Rate | L8: 0.0485
B9: Year Built / Renovated | C9: 1982 | H9: Other Growth (Year 2) | I9: 0.02 | K9: Loan Term | L9: 10 | N9: GP Fees:
B10: Construction Type | C10: Frame | H10: Other Growth (Subsequent) | I10: 0.02 | K10: Initial I/O Period | L10: 36 | N10: Acquisition Fee | O10: =C37 -> 0.02 | P10: =D37 -> 132500
B11: # Buildings | C11: 10 | K11: Amortization (after Initial I/O period) | L11: 28 | N11: Equity Placement Fee | O11: =C38 -> 0.02 | P11: =D38 -> 37479.222
B12: # Units | C12: 80 | H12: Exit Assumptions: | K12: Analysis Starting Month | L12: 1 | N12: Asset Management Fee | O12: 0.01 | P12: ='Cash Flow - Monthly'!E149 -> 43342.355
B13: Rentable Square Footage (SF) | C13: 80640 | H13: Hold Period | I13: 60 | K13: Loan Closing Costs | L13: 0 | N13: Disposition Fee | O13: 0 | P13: =O13*I16 -> 0
H14: Exit NOI | I14: ='Cash Flow - Monthly'!E59 -> 606550.05 | K14: Mortgage Insurance Premium | L14: 0
B15: Unit Mix: | H15: Exit Cap Rate | I15: ='Cignal Market Read'!$C$47 -> 0.06770634 | N15: Carried Interest | O15: 0
B16: Type | C16: Count | D16: Avg SF | E16: Market Rent | F16: $ PSF | H16: Gross Sale Proceeds | I16: ='Cash Flow - Monthly'!E120 -> 8958541.5 | K16: Refinance | L16: No
B17: Studio | C17: ='Unit Mix & Comparables'!J51 -> 0 | D17: ='Unit Mix & Comparables'!K51 -> 0 | E17: ='Unit Mix & Comparables'!Q51 -> 0 | F17: =IFERROR(IF(C17, E17/D17, 0),0) -> 0 | H17: Sale Costs | I17: 0.02 | K17: Refinance Month | L17: 0 | N17: Waterfall Assumptions:
B18: 1-BR | C18: ='Unit Mix & Comparables'!J52 -> 0 | D18: ='Unit Mix & Comparables'!K52 -> 0 | E18: ='Unit Mix & Comparables'!Q52 -> 0 | F18: =IFERROR(IF(C18, E18/D18, 0),0) -> 0 | K18: Refinance Proceeds | L18: =IF(L16="No",0,'Debt Financing'!D38) -> 0 | S18: Distribution as %
B19: 2-BR | C19: ='Unit Mix & Comparables'!J53 -> 80 | D19: ='Unit Mix & Comparables'!K53 -> 1008 | E19: ='Unit Mix & Comparables'!Q53 -> 827.225 | F19: =IFERROR(IF(C19, E19/D19, 0),0) -> 0.82065972 | H19: Other Metrics: | K19: LTV | L19: =IF($L$16="No","N/A",IF($K$17="Refinance Month",$L$18/(4*SUM(OFFSET('Cash Flow - Monthly'!$G$55,0,$L$17-1,1,-3))/$I$15),($L$18+'Cash Flow - Monthly'!E98)/C30)) -> N/A | N19: Promote Structure | O19: > __% IRR | P19: Up to __% IRR | Q19: Promote | S19: GP % | T19: LP %
B20: 3-BR + | C20: ='Unit Mix & Comparables'!J54 -> 0 | D20: ='Unit Mix & Comparables'!K54 -> 0 | E20: ='Unit Mix & Comparables'!Q54 -> 0 | F20: =IFERROR(IF(C20, E20/D20, 0),0) -> 0 | H20: Pro Forma Expenses/Unit | I20: ='Operating Inputs'!J36 -> 4311.682 | K20: LTC on Total Cost Basis to Date | L20: =IF($L$16="No","N/A",IF($K$17="Refinance Month",$L$18/(C30+$D$36+$D$43+SUM(OFFSET('Cash Flow - Monthly'!$G$61,0,0,4,$L$17))),($L$18+$L$5)/(C30+$D$36+$D$43+SUM(OFFSET('Cash Flow - Monthly'!$G$61,0,0,4,$L$17))))) -> N/A | N20: Hurdle 1 (Preferred Return) | P20: =O21 -> 0.08 | Q20: GP | R20: LP | S20: =O6 -> 0.1 | T20: =1-S20 -> 0.9
B21: Total/Avg | C21: ='Unit Mix & Comparables'!J55 -> 80 | D21: ='Unit Mix & Comparables'!K55 -> 1008 | E21: =SUMPRODUCT(C17:C20, E17:E20)/SUM(C17:C20) -> 827.225 | F21: =IFERROR(IF(C21, E21/D21, 0),0) -> 0.82065972 | H21: Estimated Replacement Cost | I21: =I30 -> 11808200 | K21: Interest Rate | L21: 0 | N21: Hurdle 2 | O21: 0.08 | P21: =O22 -> 0.1 | Q21: 0.25 | R21: =1-Q21 -> 0.75 | S21: =1-(O5*R21) -> 0.325 | T21: =1-S21 -> 0.675
H22: Total Cost/Replacement Cost | I22: =IFERROR(C33/I21,0) -> 0.61670526 | K22: Loan Term | L22: 0 | N22: Hurdle 3 | O22: 0.1 | P22: =O23 -> 0.12 | Q22: 0.3 | R22: =1-Q22 -> 0.7 | S22: =1-(O5*R22) -> 0.37 | T22: =1-S22 -> 0.63
B23: Sources | C23: $ | D23: $ Per Unit | E23: $ PSF | F23: % | H23: Total Cost | I23: =C30+D39+'Renovation Plan'!O21+'Renovation Plan'!O18+'Renovation Plan'!I35+'Renovation Plan'!J35 -> 7008250 | K23: Initial I/O Period | L23: 0 | N23: Hurdle 4 | O23: 0.12 | Q23: 0.35 | R23: =1-Q23 -> 0.65 | S23: =1-(O5*R23) -> 0.415 | T23: =1-S23 -> 0.585
B24: Senior Debt | C24: ='Debt Financing'!D17 -> 5200000 | D24: =C24/$C$12 -> 65000 | E24: =C24/$C$13 -> 64.484127 | F24: =C24/C$33 -> 0.71407198 | K24: Amortization (after Initial I/O period) | L24: 30
B25: LP Equity (90%) | C25: =P5 -> 1873961.1 | D25: =C25/$C$12 -> 23424.514 | E25: =C25/$C$13 -> 23.238605 | F25: =C25/C$27 -> 0.25733522 | H25: Replacement Cost Estimate: | K25: Refinancing Closing Costs | L25: 0.015 | N25: Investment Performance: | O25: IRR | P25: Equity Multiple | Q25: Peak Capital | R25: Profit | S25: ROI
B26: GP Equity (10%) | C26: =P6 -> 208217.9 | D26: =C26/$C$12 -> 2602.7238 | E26: =C26/$C$13 -> 2.5820672 | F26: =C26/C$27 -> 0.028592802 | H26: Estimated Insurance Cost PSF | I26: 70 | N26: Deal-Level | O26: ='Equity Waterfall - Monthly'!D8 -> 0.20356645 | P26: =1+R26/Q26 -> 2.2452101 | Q26: =-'Cash Flow - Monthly'!G152 -> 2083229.2 | R26: ='Equity Waterfall - Annual'!D7 -> 2594058 | S26: =R26/Q26 -> 1.2452101
B27: Total Sources | C27: =SUM(C24:C26) -> 7282179 | D27: =C27/$C$12 -> 91027.238 | E27: =C27/$C$13 -> 90.304799 | F27: =SUM(F24:F26) -> 1 | H27: Estimated Market Cost PSF | I27: 130 | K27: DSCR: | N27: LP | O27: ='Equity Waterfall - Monthly'!D15 -> #VALUE! | P27: =1+R27/Q27 -> #VALUE! | Q27: =O5*$Q$26 -> 1874906.3 | R27: ='Equity Waterfall - Annual'!D27 -> #VALUE! | S27: =R27/Q27 -> #VALUE!
H28: Estimated Land Value | I28: 1325000 | K28: Trailing-3 Months | L28: ='Debt Financing'!C18 -> 1.2350334 | N28: GP | O28: ='Equity Waterfall - Monthly'!D26 -> #VALUE! | P28: =1+R28/Q28 -> #VALUE! | Q28: =O6*$Q$26 -> 208322.92 | R28: ='Equity Waterfall - Annual'!D22 -> #VALUE! | S28: =R28/Q28 -> #VALUE!
B29: Uses | C29: $ | D29: $ Per Unit | E29: $ PSF | F29: % | H29: Insurance Replacement Cost | I29: =C13*I26 -> 5644800 | K29: Year 1 Pro Forma | L29: =('Operating Inputs'!I38-'Executive Summary'!L36*'Executive Summary'!C12)/-PMT(L8,L11,L5) -> 1.2442006 | N29: Unlevered Returns | O29: =(1+IRR('Cash Flow - Monthly'!G159:EI159,0.1/12))^12-1 -> 0.10165469 | P29: =1+R29/Q29 -> 1.534326 | Q29: =-'Cash Flow - Monthly'!E160 -> 7282179 | R29: ='Cash Flow - Monthly'!E159 -> 3891057.3 | S29: =R29/Q29 -> 0.53432596
B30: Purchase Price | C30: 6625000 | D30: =C30/$C$12 -> 82812.5 | E30: =C30/$C$13 -> 82.155258 | F30: =C30/C$33 -> 0.90975517 | H30: Market Replacement Cost | I30: =C13*I27+I28 -> 11808200 | K30: Stabilized Pro Forma | L30: =('Operating Inputs'!K38-'Executive Summary'!L36*'Executive Summary'!C12)/-PMT(L8,L11,L5) -> 1.3651034
B31: Capital Expenditures | C31: ='Renovation Plan'!I19 -> 383250 | D31: =C31/$C$12 -> 4790.625 | E31: =C31/$C$13 -> 4.7526042 | F31: =C31/C$33 -> 0.052628478 | N31: Cash-on-Cash Return: | O31: Year 1 | P31: Year 2 | Q31: Year 3 | R31: Hold Period
B32: Closing Costs | C32: 273929 | D32: =C32/$C$12 -> 3424.1125 | E32: =C32/$C$13 -> 3.396937 | F32: =C32/C$33 -> 0.037616351 | H32: Property Taxes: | K32: Financing Constraints: | N32: Average | O32: ='Cash Flow - Monthly'!EK157 -> 0.08394162 | P32: ='Cash Flow - Monthly'!EL157 -> 0.10014328 | Q32: ='Cash Flow - Monthly'!EM157 -> 0.11157693 | R32: ='Cash Flow - Monthly'!E157 -> 0.091979767
B33: Total Uses | C33: =SUM(C30:C32) -> 7282179 | D33: =C33/$C$12 -> 91027.238 | E33: =C33/$C$13 -> 90.304799 | F33: =SUM(F30:F32) -> 1 | H33: Appraisal to Purchase Price Ratio | I33: 0.4 | K33: DSCR Constraint
H34: Tax Rate | I34: 0.0247 | K34: NOI (Trailing-12 Months) | L34: ='Operating Inputs'!C38 -> 446567
B35: Closing Costs: | H35: Non-Ad Valorem Taxes and Fees (%) | I35: 0 | K35: DSCR | L35: 1.25
B36: Origination Fee | C36: 0.0075 | D36: =C36*C24 -> 39000 | H36: Non-Ad Valorem Taxes and Fees ($) | I36: =I35*'Operating Inputs'!M20 -> 0 | K36: Reserves/unit | L36: 275
B37: Acquisition Fee | C37: 0.02 | D37: =C37*'Executive Summary'!C30 -> 132500 | H37: Estimated Property Taxes | I37: =C30*I33*I34+I36 -> 65455 | K37: Interest Rate | L37: 0.0485
B38: Equity Placement Fee | C38: 0.02 | D38: =C38*'Executive Summary'!P5 -> 37479.222 | H38: Estimated Year 1 Taxes | I38: =AVERAGE(I37,'Operating Inputs'!C32) -> 60150.5 | K38: Maximum Annual Payment | L38: =(L34-L36*$C$12)/L35 -> 339653.6
B39: Debt Placement Fee | C39: 0 | D39: =C39*'Executive Summary'!C24 -> 0 | K39: Maximum Proceeds | L39: =-PV(L37/12,L11*12,L38/12) -> 5197194.2
B40: Third Party Reports | D40: 20000 | H40: Insurance:
B41: Legal | D41: 20000 | H41: Estimate
B42: Title Costs | D42: 10000 | H42: Rental Income | I42: ='Operating Inputs'!I14 -> 700161.93
B43: Other Reserves | D43: 16000 | H43: Insurance Rate Estimate | I43: 0.45
B44: Total - Closing Costs | D44: =SUM(D35:D43) -> 274979.22 | H44: General Liability Rate/Unit Estimate | I44: 200
H45: Property Insurance Estimate | I45: =(I29+I42)/100*I43 -> 28552.329
B46: Acquisition Metrics: | H46: Estimated General Liability | I46: =I44*C12 -> 16000
B47: Going-in Cap Rate | C47: ='Operating Inputs'!C40 -> 0.06740634 | H47: Flood Insurance Estimate | I47: 0
B48: Year 2 Pro Forma Cap Rate | C48: ='Operating Inputs'!K40 -> 0.07407295 | H48: Estimated Other | I48: 0
H49: Total Insurance Estimate | I49: =SUM(I45:I48) -> 44552.329
B50: Capital Assumptions: | H50: Pending Quote
B51: Property Renovation Budget | C51: ='Cash Flow - Monthly'!E62+'Cash Flow - Monthly'!E63+'Cash Flow - Monthly'!E64 -> 383250 | H51: Property Insurance | I51: 16000
B52: Average Unit Upgrade Cost | C52: ='Renovation Plan'!D24 -> 0 | H52: General Liability | I52: 0
B53: Reserve Application | C53: Max IRR | H53: Flood | I53: 0
B54: Recurring Reserves/Unit (Years 1-5) | C54: 275 | H54: Umbrella/Other | I54: 0
B55: Recurring Reserves/Unit (Years 6-10) | C55: 275 | H55: Total Insurance Quote | I55: =SUM(I51:I54) -> 16000

Sheet Cignal Market Read
B2: CIGNAL · MARKET READ
B3: Forward pro forma assumptions derived from local market performance - not a flat straight-line
B5: Market (MSA) | C5: Knoxville, TN (Knox MSA)
B6: As of | C6: Q2 2026 - illustrative seed; auto-populates from Cignal warehouse in production
B7: Scenario | C7: Base | D7: <- Bear / Base / Bull
B8: Cycle phase (read) | C8: =C48 -> Late Hypersupply -> Recovery (turning up)
B10: A. MARKET INPUTS (from Cignal / editable)
B11: Long-run trend rent growth | C11: 0.03
B12: Employment growth YoY (metro) | C12: 0.012 | E12: Yardi Matrix Apr-2026: +1.2% (2x US 0.6%)
B13: US employment growth (benchmark) | C13: 0.006
B14: Employment / demographic signal (-1..+1) | C14: 0.6 | E14: Emp 2x US; unemployment 2.9%; #1 US in-migration 2026
B15: Rent-momentum signal (-1..+1) | C15: 0.2 | E15: Q2-26 +1.9% - first positive quarter after 3 declines
B16: Absorption / demand signal (-1..+1) | C16: 0.5 | E16: Absorption 592u in Q2, ~3x Q1, 2-yr high
B17: Supply-pressure signal, near-term (-1..+1) | C17: 0.8 | E17: Largest wave in 15y; vacancy 10-yr high; 2,827u under constr.
B18: Supply easing by Year 2 (decay 0..1) | C18: 0.5 | E18: Starts -73%; completions -18% YoY
B19: Current market vacancy | C19: 0.06 | E19: Broad soft; stabilized ~5-6%
B20: Structural (stabilized) vacancy | C20: 0.05
B21: Current 10Y Treasury | C21: 0.043 | E21: FRED DGS10 ~4.3-4.7%
B22: Projected 10Y at exit | C22: 0.043 | E22: Editable rate view
B23: Going-in cap (from deal) | C23: ='Executive Summary'!$C$47 -> 0.06740634 | E23: Linked from Executive Summary
B25: B. ENGINE COEFFICIENTS (MSA-panel calibrated, v2026.08-msapanel-v2 - see Calibration tab)
B26: Rent sensitivity to momentum (k_rent) | C26: 0.065 | E26: Panel elasticities: vacancy -1.7, employment +0.53 (metro FE, R2 0.53)
B27: Vacancy sensitivity to supply (k_vac) | C27: 0.01 | E27: MSA-panel estimate: +0.21 vacancy per 1% of stock permitted (low R2)
B28: Exit-cap rate beta | C28: 0.5 | E28: Literature-anchored; cap~10Y link is loose/regime-dependent
B29: Exit-cap phase sensitivity | C29: 0.01 | E29: Judgmental
B30: Exit-cap conservatism buffer | C30: 0.0035 | E30: Judgmental underwriting buffer
B31: Demand weights: emp / rent-mom / absorption | C31: 0.45 | D31: 0.35 | E31: 0.2
E32: Employment UP-weighted: a strong local rent driver in the panel
B33: C. DERIVATION
B34: Demand Index | C34: =C31*C14+D31*C15+E31*C16 -> 0.44
B35: Supply pressure - Year 1 | C35: =C17 -> 0.8
B36: Supply pressure - Year 2 | C36: =C17*(1-C18) -> 0.4
B37: Momentum - Year 1 | C37: =C34-C35 -> -0.36
B38: Momentum - Year 2 | C38: =C34-C36 -> 0.04
B39: Momentum - at exit | C39: =C34-C17*0.15 -> 0.32
B40: Scenario deltas: rent / vac / cap | C40: =IF(C7="Bear",-0.015,IF(C7="Bull",0.015,0)) -> 0 | D40: =IF(C7="Bear",0.01,IF(C7="Bull",-0.0075,0)) -> 0 | E40: =IF(C7="Bear",0.0035,IF(C7="Bull",-0.0035,0)) -> 0
B42: D. FORWARD ASSUMPTIONS -> feeding the model
B43: Rent Growth - Year 1 | C43: =C11+C37*C26+C40 -> 0.0066
B44: Rent Growth - Year 2 | C44: =C11+C38*C26+C40 -> 0.0326
B45: Rent Growth - Subsequent | C45: =C11+C40 -> 0.03
B46: Stabilized Vacancy | C46: =C20+((C35+C36)/2)*C27+D40 -> 0.056
B47: Exit Cap Rate | C47: =C23+(C22-C21)*C28-C39*C29+C30+E40 -> 0.06770634
B48: Cycle phase (text) | C48: =IF(AND(C37<0,C38>0),"Late Hypersupply -> Recovery (turning up)",IF(C37<-0.15,"Hypersupply / soft",IF(C34>0.35,"Expansion","Recovery"))) -> Late Hypersupply -> Recovery (turning up)
B50: E. VS. NAIVE STRAIGHT-LINE
B51: Flat rent growth / flat vacancy / flat exit cap | C51: 0.03 | D51: 0.04 | E51: 0.0725
B53: Year | C53: Cignal (cycle-adj) | D53: Naive flat 3%
B54: 0 | C54: 100 | D54: 100
B55: 1 | C55: =C54*(1+$C$43) -> 100.66 | D55: =D54*(1+$C$51) -> 103
B56: 2 | C56: =C55*(1+$C$44) -> 103.94152 | D56: =D55*(1+$C$51) -> 106.09
B57: 3 | C57: =C56*(1+$C$45) -> 107.05976 | D57: =D56*(1+$C$51) -> 109.2727
B58: 4 | C58: =C57*(1+$C$45) -> 110.27155 | D58: =D57*(1+$C$51) -> 112.55088
B59: 5 | C59: =C58*(1+$C$45) -> 113.5797 | D59: =D58*(1+$C$51) -> 115.92741

Sheet Exit Strategy
B2: CIGNAL · EXIT STRATEGY — Sell vs. Refinance
B3: Two paths, one cycle-driven recommendation. Sell at hold-end vs. refinance mid-hold and extend.
B5: INPUTS (editable)
B6: Base hold — sell year (Path A) | C6: 5
B7: Refi year (Path B) | C7: 3
B8: Sell year (Path B) | C8: 7
B9: Refi LTV | C9: 0.7
B10: Refi valuation cap | C10: ='Cignal Market Read'!$C$23 -> 0.06740634
B11: Refi interest rate (IO) | C11: 0.055
B12: Refi cost (% of new loan) | C12: 0.01
B13: Sale costs | C13: ='Executive Summary'!$I$17 -> 0.02
B14: Exit cap — Path A | C14: ='Cignal Market Read'!$C$47 -> 0.06770634 | E14: Path B exit cap defaults to same; edit to reflect the phase at the later sale.
B15: Exit cap — Path B (later sale) | C15: ='Cignal Market Read'!$C$47 -> 0.06770634
B17: Equity invested | C17: ='Executive Summary'!$P$5+'Executive Summary'!$P$6 -> 2082179
B18: I/O years / IO DS / Amort DS | C18: ='Executive Summary'!$L$10/12 -> 3 | D18: ='Debt Financing'!$D$8 -> 252200 | E18: ='Debt Financing'!$D$7 -> 339836.97
B20: ANNUAL STREAMS (derived from the model)
B21: Year | D21: 0 | E21: 1 | F21: 2 | G21: 3 | H21: 4 | I21: 5 | J21: 6 | K21: 7 | L21: 8 | M21: 9 | N21: 10 | O21: 11
B22: Net Operating Income | D22: 0 | E22: =SUM('Cash Flow - Monthly'!H55:S55) -> 449219.09 | F22: =SUM('Cash Flow - Monthly'!T55:AE55) -> 483398.6 | G22: =SUM('Cash Flow - Monthly'!AF55:AQ55) -> 507659.15 | H22: =SUM('Cash Flow - Monthly'!AR55:BC55) -> 525544.01 | I22: =SUM('Cash Flow - Monthly'!BD55:BO55) -> 543770.2 | J22: =SUM('Cash Flow - Monthly'!BP55:CA55) -> 606550.05 | K22: =SUM('Cash Flow - Monthly'!CB55:CM55) -> 582029.39 | L22: =SUM('Cash Flow - Monthly'!CN55:CY55) -> 602100.71 | M22: =SUM('Cash Flow - Monthly'!CZ55:DK55) -> 622826.37 | N22: =SUM('Cash Flow - Monthly'!DL55:DW55) -> 644227.06 | O22: =SUM('Cash Flow - Monthly'!DX55:EI55) -> 666324.08
B23: Debt service (original) | D23: 0 | E23: =IF(1<=$C$18,$D$18,$E$18) -> 252200 | F23: =IF(2<=$C$18,$D$18,$E$18) -> 252200 | G23: =IF(3<=$C$18,$D$18,$E$18) -> 252200 | H23: =IF(4<=$C$18,$D$18,$E$18) -> 339836.97 | I23: =IF(5<=$C$18,$D$18,$E$18) -> 339836.97 | J23: =IF(6<=$C$18,$D$18,$E$18) -> 339836.97 | K23: =IF(7<=$C$18,$D$18,$E$18) -> 339836.97 | L23: =IF(8<=$C$18,$D$18,$E$18) -> 339836.97 | M23: =IF(9<=$C$18,$D$18,$E$18) -> 339836.97 | N23: =IF(10<=$C$18,$D$18,$E$18) -> 339836.97
B24: Loan balance (EOY, original) | D24: =$C$17*0+'Executive Summary'!$C$24 -> 5200000 | E24: ='Amortization Table'!F16 -> 5200000 | F24: ='Amortization Table'!F28 -> 5200000 | G24: ='Amortization Table'!F40 -> 5200000 | H24: ='Amortization Table'!F52 -> 5110388.5 | I24: ='Amortization Table'!F64 -> 5016332.8 | J24: ='Amortization Table'!F76 -> 4917612.7 | K24: ='Amortization Table'!F88 -> 4813996.8 | L24: ='Amortization Table'!F100 -> 4705242.3 | M24: ='Amortization Table'!F112 -> 4591094.3 | N24: ='Amortization Table'!F124 -> 4471285.4
B26: REFINANCE SIZING (Path B, at refi year)
B27: NOI at refi+1 | C27: =INDEX($E$22:$O$22,$C$7+1) -> 525544.01
B28: Implied value at refi | C28: =C27/$C$10 -> 7796655.6
B29: New loan | C29: =$C$9*C28 -> 5457658.9
B30: Old loan balance at refi | C30: =INDEX($E$24:$N$24,$C$7) -> 5200000
B31: Cash-out at refi (to equity) | C31: =C29-C30-C29*$C$12 -> 203082.3
B32: New debt service (IO) | C32: =C29*$C$11 -> 300171.24
B33: Net sale proceeds — Path A | C33: =(INDEX($E$22:$O$22,$C$6+1)/$C$14)*(1-$C$13)-INDEX($E$24:$N$24,$C$6) -> 3763037.9
B34: Net sale proceeds — Path B | C34: =(INDEX($E$22:$O$22,$C$8+1)/$C$15)*(1-$C$13)-C29 -> 3257310.7
B36: PATH A — SELL AT HOLD-END
B37: Cash flow to equity | D37: =IF(0=0,-$C$17,IF(0>$C$6,0,(D22-D23)+IF(0=$C$6,$C$33,0))) -> -2082179 | E37: =IF(1=0,-$C$17,IF(1>$C$6,0,(E22-E23)+IF(1=$C$6,$C$33,0))) -> 197019.09 | F37: =IF(2=0,-$C$17,IF(2>$C$6,0,(F22-F23)+IF(2=$C$6,$C$33,0))) -> 231198.6 | G37: =IF(3=0,-$C$17,IF(3>$C$6,0,(G22-G23)+IF(3=$C$6,$C$33,0))) -> 255459.15 | H37: =IF(4=0,-$C$17,IF(4>$C$6,0,(H22-H23)+IF(4=$C$6,$C$33,0))) -> 185707.04 | I37: =IF(5=0,-$C$17,IF(5>$C$6,0,(I22-I23)+IF(5=$C$6,$C$33,0))) -> 3966971.1 | J37: =IF(6=0,-$C$17,IF(6>$C$6,0,(J22-J23)+IF(6=$C$6,$C$33,0))) -> 0 | K37: =IF(7=0,-$C$17,IF(7>$C$6,0,(K22-K23)+IF(7=$C$6,$C$33,0))) -> 0 | L37: =IF(8=0,-$C$17,IF(8>$C$6,0,(L22-L23)+IF(8=$C$6,$C$33,0))) -> 0 | M37: =IF(9=0,-$C$17,IF(9>$C$6,0,(M22-M23)+IF(9=$C$6,$C$33,0))) -> 0 | N37: =IF(10=0,-$C$17,IF(10>$C$6,0,(N22-N23)+IF(10=$C$6,$C$33,0))) -> 0 | O37: =0 -> 0
B39: IRR (levered, deal-level) | C39: =IRR(D37:O37) -> 0.20984125
B40: Equity multiple | C40: =SUM(E37:O37)/$C$17 -> 2.3227374
B41: Total profit | C41: =SUM(E37:O37)-$C$17 -> 2754176
B43: PATH B — REFINANCE MID-HOLD, THEN SELL
B44: Cash flow to equity | D44: =IF(0=0,-$C$17,IF(0>$C$8,0,(IF(0<=$C$7,D22-D23,IF(0<=$C$8,D22-$C$32,0)))+IF(0=$C$7,$C$31,0)+IF(0=$C$8,$C$34,0))) -> -2082179 | E44: =IF(1=0,-$C$17,IF(1>$C$8,0,(IF(1<=$C$7,E22-E23,IF(1<=$C$8,E22-$C$32,0)))+IF(1=$C$7,$C$31,0)+IF(1=$C$8,$C$34,0))) -> 197019.09 | F44: =IF(2=0,-$C$17,IF(2>$C$8,0,(IF(2<=$C$7,F22-F23,IF(2<=$C$8,F22-$C$32,0)))+IF(2=$C$7,$C$31,0)+IF(2=$C$8,$C$34,0))) -> 231198.6 | G44: =IF(3=0,-$C$17,IF(3>$C$8,0,(IF(3<=$C$7,G22-G23,IF(3<=$C$8,G22-$C$32,0)))+IF(3=$C$7,$C$31,0)+IF(3=$C$8,$C$34,0))) -> 458541.45 | H44: =IF(4=0,-$C$17,IF(4>$C$8,0,(IF(4<=$C$7,H22-H23,IF(4<=$C$8,H22-$C$32,0)))+IF(4=$C$7,$C$31,0)+IF(4=$C$8,$C$34,0))) -> 225372.77 | I44: =IF(5=0,-$C$17,IF(5>$C$8,0,(IF(5<=$C$7,I22-I23,IF(5<=$C$8,I22-$C$32,0)))+IF(5=$C$7,$C$31,0)+IF(5=$C$8,$C$34,0))) -> 243598.96 | J44: =IF(6=0,-$C$17,IF(6>$C$8,0,(IF(6<=$C$7,J22-J23,IF(6<=$C$8,J22-$C$32,0)))+IF(6=$C$7,$C$31,0)+IF(6=$C$8,$C$34,0))) -> 306378.82 | K44: =IF(7=0,-$C$17,IF(7>$C$8,0,(IF(7<=$C$7,K22-K23,IF(7<=$C$8,K22-$C$32,0)))+IF(7=$C$7,$C$31,0)+IF(7=$C$8,$C$34,0))) -> 3539168.9 | L44: =IF(8=0,-$C$17,IF(8>$C$8,0,(IF(8<=$C$7,L22-L23,IF(8<=$C$8,L22-$C$32,0)))+IF(8=$C$7,$C$31,0)+IF(8=$C$8,$C$34,0))) -> 0 | M44: =IF(9=0,-$C$17,IF(9>$C$8,0,(IF(9<=$C$7,M22-M23,IF(9<=$C$8,M22-$C$32,0)))+IF(9=$C$7,$C$31,0)+IF(9=$C$8,$C$34,0))) -> 0 | N44: =IF(10=0,-$C$17,IF(10>$C$8,0,(IF(10<=$C$7,N22-N23,IF(10<=$C$8,N22-$C$32,0)))+IF(10=$C$7,$C$31,0)+IF(10=$C$8,$C$34,0))) -> 0 | O44: =0 -> 0
B46: IRR (levered, deal-level) | C46: =IRR(D44:O44) -> 0.17752161
B47: Equity multiple | C47: =SUM(E44:O44)/$C$17 -> 2.4979978
B48: Total profit | C48: =SUM(E44:O44)-$C$17 -> 3119099.6
B50: CIGNAL RECOMMENDATION
B52: Math favors | C52: =IF(C46>C39,"Path B - Refi & Hold","Path A - Sell at hold-end") -> Path A - Sell at hold-end
B53: Cycle read (Market Read) | C53: =IF(AND('Cignal Market Read'!C37<0,'Cignal Market Read'!C38>0),"REFINANCE & HOLD",IF(AND('Cignal Market Read'!C34>0.35,'Cignal Market Read'!C17>0.4),"SELL INTO STRENGTH",IF(AND('Cignal Market Read'!C37<-0.15,'Cignal Market Read'!C38<0),"SELL / DE-RISK","NEUTRAL"))) -> REFINANCE & HOLD
B54: Why | C54: =IF(AND('Cignal Market Read'!C37<0,'Cignal Market Read'!C38>0),"Soft now, recovery ahead - extend the hold to capture the up-leg; refinance to return capital while you wait.",IF(AND('Cignal Market Read'!C34>0.35,'Cignal Market Read'!C17>0.4),"Strong now but supply is building - exit into strength before the softening.",IF(AND('Cignal Market Read'!C37<-0.15,'Cignal Market Read'!C38<0),"Weak and not yet turning - de-risk; do not extend into prolonged softness.","No strong cycle signal - let the deal math decide."))) -> Soft now, recovery ahead - extend the hold to capture the up-leg; refinance to return capital while you wait.
B57: Cycle vs. math | C57: =IF(OR(AND(C46>C39,LEFT(C53,3)="REF"),AND(C46<=C39,LEFT(C53,3)="SEL")),"Aligned - cycle and math agree.","Divergent - cycle and math disagree; weigh conviction vs. certainty.") -> Divergent - cycle and math disagree; weigh conviction vs. certainty.

Sheet Calibration
B2: CIGNAL · ENGINE CALIBRATION (v2026.08-msapanel-v2)
B4: MSA-panel recalibration of the Market Read coefficients — matches the live web engine.
B5: Data: Cignal warehouse, 122 metros, 2015-2026, annual, metro fixed effects (within OLS).
B7: DATA SOURCES
B8: Employment | E8: bls_metro_employment (metro nonfarm employment, YoY %)
B9: Rent (multifamily) | E9: zori_metro_mf (Zillow metro MF asking rent, YoY %)
B10: Vacancy | E10: apt_vacancy (Apartment List metro vacancy rate, %)
B11: Multifamily supply | E11: permits_5plus_metro / acs_housing_units (permits as % of stock)
B12: 10-Year Treasury | E12: FRED DGS10 (national)
B14: FITTED RELATIONSHIPS
B15: Regression | C15: Key coef | D15: R2 | E15: Reading
B16: rent_yoy ~ emp_yoy + vacancy (metro FE) | C16: -1.70 (vac) | D16: 0.53 | E16: Vacancy/slack dominates within-metro
B17: ...employment term | C17: +0.53 (emp) | E17: Employment a STRONG local driver (was +0.05 national)
B18: d_vacancy ~ permits(% stock) (metro FE) | C18: +0.21 | D18: 0.00 | E18: LOCAL supply->vacancy now estimated (low R2)
B20: HOW COEFFICIENTS WERE SET
B21: k_rent | C21: 0.065 | E21: Stronger panel elasticities (vacancy -1.7, employment +0.53)
B22: Demand weights (emp/rent/absorb) | C22: .45/.35/.20 | E22: Employment UP-weighted: strong local driver in the panel
B23: k_vac | C23: 0.010 | E23: Now empirically anchored: panel supply->vacancy +0.21 (modest R2)
B24: Exit-cap rate beta | C24: 0.50 | E24: Unchanged - cap rates not in the panel; literature-anchored
B25: Phase sensitivity / buffer | C25: 0.010 / 35bp | E25: Unchanged - judgmental underwriting parameters
B27: CAVEATS (read before trusting)
B28: • MSA panel with metro fixed effects (122 metros, 2015-2026) - far better identified than national.
B29: • k_vac still has low R2 even locally (supply is noisy) - treat as modest-confidence.
B30: • Vacancy history is shorter (apt_vacancy from 2017); permits stale to 2023.
B31: • Engine v2026.08-msapanel-v2 - matches the live Cignal web Underwriter exactly.

Sheet Debt Financing
B2: Acquisition Financing Assumptions
B3: Interest Rate | D3: ='Executive Summary'!L8 -> 0.0485
B4: Initial I/O Period | D4: ='Executive Summary'!L10 -> 36
B5: Amortization (after initial I/O period) | D5: ='Executive Summary'!L11 -> 28
B6: NOI (Trailing-3 Months) | D6: ='Operating Inputs'!G38 -> 419710
B7: Annual Debt Service (Amortizing) | D7: =-PMT(D3/12,D5*12,D17)*12 -> 339836.97
B8: Annual Debt Service (Interest-Only) | D8: =D3*D17 -> 252200
B9: Loan Sizing:
B10: Debt Yield | C10: 0.08 | D10: =(D6-'Executive Summary'!L36*'Executive Summary'!C12)/C10 -> 4971375
B11: LTC / LTV | C11: 0.75 | D11: =C11*'Executive Summary'!C33 -> 5461634.2
B12: LTPP | C12: 0.75 | D12: =C12*'Executive Summary'!C30 -> 4968750
B13: DSCR | C13: 1.2 | D13: =-PV(D3/12,30*12,(D6-'Executive Summary'!L36*'Executive Summary'!C12)/C13/12) -> 5233878.7
B14: Assumable Loan Amount | C14: - | D14: 0
B15: Actual Loan Amount:
B16: Debt Yield | C16: =D6/D17 -> 0.080713462
B17: LTC / LTV | C17: =D17/'Executive Summary'!C33 -> 0.71407198 | D17: 5200000
B18: DSCR (Amortizing) | C18: =D6/D7 -> 1.2350334
B20: Balloon Balance at Refinance | D20: =IF('Executive Summary'!L17=0,"N/A",IPMT('Debt Financing'!D3/12,'Executive Summary'!L17-'Debt Financing'!D4+1,'Debt Financing'!D5*12,-'Debt Financing'!D17)/('Debt Financing'!D3/12)) -> N/A
B21: Balloon Balance at Maturity | D21: =IPMT('Debt Financing'!D3/12,'Executive Summary'!I13-'Debt Financing'!D4+1,'Debt Financing'!D5*12,-'Debt Financing'!D17)/('Debt Financing'!D3/12) -> 5016332.8
B23: Refinance Assumptions
B24: Refinance Month | D24: =IF('Executive Summary'!L17=0,"N/A",'Executive Summary'!L17) -> N/A
B25: NOI (Trailing-3 Months) | D25: =IF(D24="N/A","N/A",4*SUM(OFFSET('Cash Flow - Monthly'!$G$55,0,'Executive Summary'!$L$17-1,1,-3))) -> N/A
B26: Implied Valuation | D26: =IF(D24="N/A","N/A",D25/'Executive Summary'!I15) -> N/A
B27: Interest Rate | D27: ='Executive Summary'!L21 -> 0
B28: Initial I/O Period | D28: ='Executive Summary'!L23 -> 0
B29: Amortization | D29: 30
B30: Annual Debt Service (Amortizing) | D30: =IF(D24="N/A","N/A",-PMT(D27/12,D29*12,D38)*12) -> N/A
B31: Annual Debt Service (Interest-Only) | D31: =IF(D24="N/A","N/A",D27*D38) -> N/A
B32: Loan Sizing:
B33: Debt Yield | C33: 0.08 | D33: =IF(D24="N/A","N/A",D25/C33) -> N/A
B34: LTV | C34: 0.75 | D34: =IF(D24="N/A","N/A",C34*D26) -> N/A
B35: DSCR | C35: 1.3 | D35: =IF(D24="N/A","N/A",-PV(D27/12,30*12,D25/C35/12)) -> N/A
B36: Actual Loan Amount:
B37: Debt Yield | C37: =IF(D24="N/A","N/A",D25/D38) -> N/A
B38: LTC / LTV | C38: =IF(D24="N/A","N/A",D38/D26) -> N/A | D38: =MIN(D33:D35) -> 0
B39: DSCR (Amortizing) | C39: =IF(D24="N/A","N/A",D25/D30) -> N/A
B41: Balloon Balance at Maturity | D41: =IF('Debt Financing'!$D$27=0,"N/A",IPMT('Debt Financing'!$D$27/12,'Executive Summary'!L22*12+1,'Debt Financing'!$D$29*12,-'Debt Financing'!$D$38)/('Debt Financing'!$D$27/12)) -> N/A

Sheet Operating Inputs
B2: ='Executive Summary'!B2 -> Riverhill TH
B3: Operating Inputs
C4: T-12 | E4: T-3 Annualized | G4: T-3 Rev / T12 Exp | I4: Pro Forma (Year 1) | K4: Pro Forma (Year 2) | M4: Pro Forma (Adj T-12) | P4: Assumptions
C5: (ended 11/17) | D5: % / $/Unit | E5: (ended 11/17) | F5: % / $/Unit | G5: (ended 11/17) | H5: % / $/Unit | I5: Total | J5: % / $/Unit | K5: Total | L5: % / $/Unit | M5: Total | N5: % / $/Unit
B6: REVENUES
B7: Rental Income
B8: Market Rent | C8: 728750 | D8: =C8/C$10 -> 1.0215768 | E8: ='T-3 Worksheet'!G7 -> 732624 | F8: =E8/E$10 -> 1.0240073 | G8: =E8 -> 732624 | H8: =G8/G$10 -> 1.0240073 | I8: ='Cash Flow - Monthly'!EK25 -> 761762.48 | J8: =I8/I$10 -> 1.0203376 | K8: ='Cash Flow - Monthly'!EL25 -> 807389.08 | L8: =K8/K$10 -> 1.0152686 | M8: =SUMPRODUCT('Unit Mix & Comparables'!C9:C38,'Unit Mix & Comparables'!G9:G38)*12 -> 746136 | N8: =M8/M$10 -> 1.0152284
B9: Gain (Loss) to Lease | C9: -15392 | D9: =C9/C$10 -> -0.021576824 | E9: ='T-3 Worksheet'!G8 -> -17176 | F9: =E9/E$10 -> -0.024007335 | G9: =E9 -> -17176 | H9: =G9/G$10 -> -0.024007335 | I9: ='Cash Flow - Monthly'!EK26 -> -15183.619 | J9: =I9/I$10 -> -0.020337596 | K9: ='Cash Flow - Monthly'!EL26 -> -12142.277 | L9: =K9/K$10 -> -0.015268564 | M9: =-('Executive Summary'!I7/2)*M8 -> -11192.04 | N9: =M9/M$10 -> -0.015228426
B10: Gross Potential Rent | C10: =SUM(C8:C9) -> 713358 | D10: =C10/C$10 -> 1 | E10: =SUM(E8:E9) -> 715448 | F10: =E10/E$10 -> 1 | G10: =SUM(G8:G9) -> 715448 | H10: =G10/G$10 -> 1 | I10: =SUM(I8:I9) -> 746578.86 | J10: =I10/I$10 -> 1 | K10: =SUM(K8:K9) -> 795246.8 | L10: =K10/K$10 -> 1 | M10: =SUM(M8:M9) -> 734943.96 | N10: =M10/M$10 -> 1 | P10: Economic Loss (%)
B11: Rental Losses | C11: 0 | D11: =C11/C$10 -> 0 | E11: ='T-3 Worksheet'!G14 -> 0 | F11: =E11/E$10 -> 0 | G11: =E11 -> 0 | H11: =G11/G$10 -> 0 | I11: ='Cash Flow - Monthly'!EK28 -> -2239.7366 | J11: =I11/I$10 -> -0.003 | K11: ='Cash Flow - Monthly'!EL28 -> -2385.7404 | L11: =K11/K$10 -> -0.003 | M11: =P11*$M$10 -> -2204.8319 | N11: =M11/M$10 -> -0.003 | P11: -0.003
B12: Vacancy | C12: -20449 | D12: =C12/C$10 -> -0.028665831 | E12: ='T-3 Worksheet'!G12 -> -49488 | F12: =E12/E$10 -> -0.069170646 | G12: =E12 -> -49488 | H12: =G12/G$10 -> -0.069170646 | I12: ='Cash Flow - Monthly'!EK29 -> -41937.452 | J12: =I12/I$10 -> -0.056172836 | K12: ='Cash Flow - Monthly'!EL29 -> -44533.821 | L12: =K12/K$10 -> -0.056 | M12: =P12*$M$10 -> -41156.862 | N12: =M12/M$10 -> -0.056 | P12: =-'Cignal Market Read'!$C$46 -> -0.056
B13: Bad Debt | C13: -12 | D13: =C13/C$10 -> -1.6821848e-05 | E13: ='T-3 Worksheet'!G15 -> -6068 | F13: =E13/E$10 -> -0.0084813991 | G13: =E13 -> -6068 | H13: =G13/G$10 -> -0.0084813991 | I13: ='Cash Flow - Monthly'!EK30 -> -2239.7366 | J13: =I13/I$10 -> -0.003 | K13: ='Cash Flow - Monthly'!EL30 -> -2385.7404 | L13: =K13/K$10 -> -0.003 | M13: =P13*$M$10 -> -2204.8319 | N13: =M13/M$10 -> -0.003 | P13: -0.003
B14: Net Rental Income | C14: =SUM(C10:C13) -> 692897 | D14: =C14/C$10 -> 0.97131735 | E14: =SUM(E10:E13) -> 659892 | F14: =E14/E$10 -> 0.92234796 | G14: =SUM(G10:G13) -> 659892 | H14: =G14/G$10 -> 0.92234796 | I14: =SUM(I10:I13) -> 700161.93 | J14: =I14/I$10 -> 0.93782716 | K14: =SUM(K10:K13) -> 745941.5 | L14: =K14/K$10 -> 0.938 | M14: =SUM(M10:M13) -> 689377.43 | N14: =M14/M$10 -> 0.938
B15: Other Income | P15: Unit Per Year
B16: Utility | C16: 37188 | D16: =C16/'Executive Summary'!$C$12 -> 464.85 | E16: ='T-3 Worksheet'!G18 -> 39684 | F16: =E16/'Executive Summary'!$C$12 -> 496.05 | G16: =E16 -> 39684 | H16: =G16/'Executive Summary'!$C$12 -> 496.05 | I16: ='Cash Flow - Monthly'!EK33 -> 41097.592 | J16: =I16/'Executive Summary'!$C$12 -> 513.7199 | K16: ='Cash Flow - Monthly'!EL33 -> 41919.543 | L16: =K16/'Executive Summary'!$C$12 -> 523.99429 | M16: =P16*M28 -> 43200 | N16: =M16/'Executive Summary'!$C$12 -> 540 | P16: 0.9
B17: Late Charges | C17: 5853 | D17: =C17/'Executive Summary'!$C$12 -> 73.1625 | E17: ='T-3 Worksheet'!G19 -> 5168 | F17: =E17/'Executive Summary'!$C$12 -> 64.6 | G17: =E17 -> 5168 | H17: =G17/'Executive Summary'!$C$12 -> 64.6 | I17: ='Cash Flow - Monthly'!EK34 -> 5327.4656 | J17: =I17/'Executive Summary'!$C$12 -> 66.59332 | K17: ='Cash Flow - Monthly'!EL34 -> 5434.0149 | L17: =K17/'Executive Summary'!$C$12 -> 67.925186 | M17: =P17*'Executive Summary'!$C$12 -> 5600 | N17: =M17/'Executive Summary'!$C$12 -> 70 | P17: 70
B18: Other | C18: 48159 | D18: =C18/'Executive Summary'!$C$12 -> 601.9875 | E18: ='T-3 Worksheet'!G20 -> 52496 | F18: =E18/'Executive Summary'!$C$12 -> 656.2 | G18: =E18 -> 52496 | H18: =G18/'Executive Summary'!$C$12 -> 656.2 | I18: ='Cash Flow - Monthly'!EK35 -> 47566.657 | J18: =I18/'Executive Summary'!$C$12 -> 594.58321 | K18: ='Cash Flow - Monthly'!EL35 -> 48517.99 | L18: =K18/'Executive Summary'!$C$12 -> 606.47488 | M18: =P18*'Executive Summary'!$C$12 -> 50000 | N18: =M18/'Executive Summary'!$C$12 -> 625 | P18: 625
B19: Total Other Income | C19: =SUM(C16:C18) -> 91200 | D19: =C19/'Executive Summary'!$C$12 -> 1140 | E19: =SUM(E16:E18) -> 97348 | F19: =E19/'Executive Summary'!$C$12 -> 1216.85 | G19: =SUM(G16:G18) -> 97348 | H19: =G19/'Executive Summary'!$C$12 -> 1216.85 | I19: =SUM(I16:I18) -> 93991.714 | J19: =I19/'Executive Summary'!$C$12 -> 1174.8964 | K19: =SUM(K16:K18) -> 95871.549 | L19: =K19/'Executive Summary'!$C$12 -> 1198.3944 | M19: =SUM(M16:M18) -> 98800 | N19: =M19/'Executive Summary'!$C$12 -> 1235
B20: TOTAL REVENUES | C20: =SUM(C14,C19) -> 784097 | D20: =C20/'Executive Summary'!$C$12 -> 9801.2125 | E20: =SUM(E14,E19) -> 757240 | F20: =E20/'Executive Summary'!$C$12 -> 9465.5 | G20: =SUM(G14,G19) -> 757240 | H20: =G20/'Executive Summary'!$C$12 -> 9465.5 | I20: =SUM(I14,I19) -> 794153.65 | J20: =I20/'Executive Summary'!$C$12 -> 9926.9206 | K20: =SUM(K14,K19) -> 841813.05 | L20: =K20/'Executive Summary'!$C$12 -> 10522.663 | M20: =SUM(M14,M19) -> 788177.43 | N20: =M20/'Executive Summary'!$C$12 -> 9852.2179
B22: EXPENSES
B23: Controllable | P23: $/Unit/Year
B24: Payroll | C24: 108802 | D24: =C24/'Executive Summary'!$C$12 -> 1360.025 | E24: ='T-3 Worksheet'!G26 -> 114772 | F24: =E24/'Executive Summary'!$C$12 -> 1434.65 | G24: =C24 -> 108802 | H24: =G24/'Executive Summary'!$C$12 -> 1360.025 | I24: ='Cash Flow - Monthly'!EK41 -> 88950.449 | J24: =I24/'Executive Summary'!$C$12 -> 1111.8806 | K24: ='Cash Flow - Monthly'!EL41 -> 90729.458 | L24: =K24/'Executive Summary'!$C$12 -> 1134.1182 | M24: =N24*'Executive Summary'!$C$12 -> 88000 | N24: =P24 -> 1100 | P24: 1100
B25: Operations & Maintenance | C25: 55527 | D25: =C25/'Executive Summary'!$C$12 -> 694.0875 | E25: ='T-3 Worksheet'!G27 -> 60488 | F25: =E25/'Executive Summary'!$C$12 -> 756.1 | G25: =C25 -> 55527 | H25: =G25/'Executive Summary'!$C$12 -> 694.0875 | I25: ='Cash Flow - Monthly'!EK42 -> 60648.034 | J25: =I25/'Executive Summary'!$C$12 -> 758.10042 | K25: ='Cash Flow - Monthly'!EL42 -> 61860.994 | L25: =K25/'Executive Summary'!$C$12 -> 773.26243 | M25: =N25*'Executive Summary'!$C$12 -> 60000 | N25: =P25 -> 750 | P25: 750
B26: Marketing | C26: 12212 | D26: =C26/'Executive Summary'!$C$12 -> 152.65 | E26: ='T-3 Worksheet'!G28 -> 13136 | F26: =E26/'Executive Summary'!$C$12 -> 164.2 | G26: =C26 -> 12212 | H26: =G26/'Executive Summary'!$C$12 -> 152.65 | I26: ='Cash Flow - Monthly'!EK43 -> 14151.208 | J26: =I26/'Executive Summary'!$C$12 -> 176.8901 | K26: ='Cash Flow - Monthly'!EL43 -> 14434.232 | L26: =K26/'Executive Summary'!$C$12 -> 180.4279 | M26: =N26*'Executive Summary'!$C$12 -> 14000 | N26: =P26 -> 175 | P26: 175
B27: General & Adminstrative | C27: 13957 | D27: =C27/'Executive Summary'!$C$12 -> 174.4625 | E27: ='T-3 Worksheet'!G29 -> 26076 | F27: =E27/'Executive Summary'!$C$12 -> 325.95 | G27: =C27 -> 13957 | H27: =G27/'Executive Summary'!$C$12 -> 174.4625 | I27: ='Cash Flow - Monthly'!EK44 -> 24259.213 | J27: =I27/'Executive Summary'!$C$12 -> 303.24017 | K27: ='Cash Flow - Monthly'!EL44 -> 24744.398 | L27: =K27/'Executive Summary'!$C$12 -> 309.30497 | M27: =N27*'Executive Summary'!$C$12 -> 24000 | N27: =P27 -> 300 | P27: 300
B28: Utilities: Reimbursable | C28: 43667 | D28: =C28/'Executive Summary'!$C$12 -> 545.8375 | E28: ='T-3 Worksheet'!G30 -> 49840 | F28: =E28/'Executive Summary'!$C$12 -> 623 | G28: =C28 -> 43667 | H28: =G28/'Executive Summary'!$C$12 -> 545.8375 | I28: ='Cash Flow - Monthly'!EK45 -> 48518.427 | J28: =I28/'Executive Summary'!$C$12 -> 606.48034 | K28: ='Cash Flow - Monthly'!EL45 -> 49488.795 | L28: =K28/'Executive Summary'!$C$12 -> 618.60994 | M28: =N28*'Executive Summary'!$C$12 -> 48000 | N28: =P28 -> 600 | P28: 600
B29: Utilities: Other | C29: 2611 | D29: =C29/'Executive Summary'!$C$12 -> 32.6375 | E29: ='T-3 Worksheet'!G31 -> 4108 | F29: =E29/'Executive Summary'!$C$12 -> 51.35 | G29: =C29 -> 2611 | H29: =G29/'Executive Summary'!$C$12 -> 32.6375 | I29: ='Cash Flow - Monthly'!EK46 -> 3638.882 | J29: =I29/'Executive Summary'!$C$12 -> 45.486025 | K29: ='Cash Flow - Monthly'!EL46 -> 3711.6597 | L29: =K29/'Executive Summary'!$C$12 -> 46.395746 | M29: =N29*'Executive Summary'!$C$12 -> 3600 | N29: =P29 -> 45 | P29: 45
B30: Total Controllable | C30: =SUM(C24:C29) -> 236776 | D30: =C30/'Executive Summary'!$C$12 -> 2959.7 | E30: =SUM(E24:E29) -> 268420 | F30: =E30/'Executive Summary'!$C$12 -> 3355.25 | G30: =SUM(G24:G29) -> 236776 | H30: =G30/'Executive Summary'!$C$12 -> 2959.7 | I30: =SUM(I24:I29) -> 240166.21 | J30: =I30/'Executive Summary'!$C$12 -> 3002.0777 | K30: =SUM(K24:K29) -> 244969.54 | L30: =K30/'Executive Summary'!$C$12 -> 3062.1192 | M30: =SUM(M24:M29) -> 237600 | N30: =SUM(N24:N29) -> 2970
B31: Noncontrollable
B32: Taxes | C32: 54846 | D32: =C32/'Executive Summary'!$C$12 -> 685.575 | E32: ='T-3 Worksheet'!G34 -> 54964 | F32: =E32/'Executive Summary'!$C$12 -> 687.05 | G32: =C32 -> 54846 | H32: =G32/'Executive Summary'!$C$12 -> 685.575 | I32: ='Cash Flow - Monthly'!EK49 -> 60800.159 | J32: =I32/'Executive Summary'!$C$12 -> 760.00199 | K32: ='Executive Summary'!I38 -> 60150.5 | L32: =K32/'Executive Summary'!$C$12 -> 751.88125 | M32: ='Executive Summary'!I38 -> 60150.5 | N32: =M32/'Executive Summary'!$C$12 -> 751.88125
B33: Insurance | C33: 22037 | D33: =C33/'Executive Summary'!$C$12 -> 275.4625 | E33: ='T-3 Worksheet'!G35 -> 24912 | F33: =E33/'Executive Summary'!$C$12 -> 311.4 | G33: =C33 -> 22037 | H33: =G33/'Executive Summary'!$C$12 -> 275.4625 | I33: ='Cash Flow - Monthly'!EK50 -> 16172.809 | J33: =I33/'Executive Summary'!$C$12 -> 202.16011 | K33: ='Cash Flow - Monthly'!EL50 -> 16496.265 | L33: =K33/'Executive Summary'!$C$12 -> 206.20331 | M33: =IF('Executive Summary'!I55>0,'Executive Summary'!I55,'Executive Summary'!I49) -> 16000 | N33: =M33/'Executive Summary'!$C$12 -> 200 | P33: % of Total Revenue
B34: Property Management Fee | C34: 23871 | D34: =C34/'Executive Summary'!$C$12 -> 298.3875 | E34: ='T-3 Worksheet'!G36 -> 18016 | F34: =E34/'Executive Summary'!$C$12 -> 225.2 | G34: =C34 -> 23871 | H34: =G34/'Executive Summary'!$C$12 -> 298.3875 | I34: ='Cash Flow - Monthly'!EK51 -> 27795.378 | J34: =I34/'Executive Summary'!$C$12 -> 347.44222 | K34: ='Cash Flow - Monthly'!EL51 -> 29463.457 | L34: =K34/'Executive Summary'!$C$12 -> 368.29321 | M34: =P34*M20 -> 27586.21 | N34: =M34/'Executive Summary'!$C$12 -> 344.82763 | P34: 0.035
B35: Total Noncontrollable | C35: =SUM(C32:C34) -> 100754 | D35: =C35/'Executive Summary'!$C$12 -> 1259.425 | E35: =SUM(E32:E34) -> 97892 | F35: =E35/'Executive Summary'!$C$12 -> 1223.65 | G35: =SUM(G32:G34) -> 100754 | H35: =G35/'Executive Summary'!$C$12 -> 1259.425 | I35: =SUM(I32:I34) -> 104768.35 | J35: =I35/'Executive Summary'!$C$12 -> 1309.6043 | K35: =SUM(K32:K34) -> 106110.22 | L35: =K35/'Executive Summary'!$C$12 -> 1326.3778 | M35: =SUM(M32:M34) -> 103736.71 | N35: =M35/'Executive Summary'!$C$12 -> 1296.7089
B36: TOTAL EXPENSES | C36: =SUM(C30,C35) -> 337530 | D36: =C36/'Executive Summary'!$C$12 -> 4219.125 | E36: =SUM(E30,E35) -> 366312 | F36: =E36/'Executive Summary'!$C$12 -> 4578.9 | G36: =SUM(G30,G35) -> 337530 | H36: =G36/'Executive Summary'!$C$12 -> 4219.125 | I36: =SUM(I30,I35) -> 344934.56 | J36: =I36/'Executive Summary'!$C$12 -> 4311.682 | K36: =SUM(K30,K35) -> 351079.76 | L36: =K36/'Executive Summary'!$C$12 -> 4388.497 | M36: =SUM(M30,M35) -> 341336.71 | N36: =M36/'Executive Summary'!$C$12 -> 4266.7089 | P36: =M36/M20 -> 0.4330709
B38: NET OPERATING INCOME | C38: =C20-C36 -> 446567 | D38: =C38/'Executive Summary'!$C$12 -> 5582.0875 | E38: =E20-E36 -> 390928 | F38: =E38/'Executive Summary'!$C$12 -> 4886.6 | G38: =G20-G36 -> 419710 | H38: =G38/'Executive Summary'!$C$12 -> 5246.375 | I38: =I20-I36 -> 449219.09 | J38: =I38/'Executive Summary'!$C$12 -> 5615.2386 | K38: =K20-K36 -> 490733.29 | L38: =K38/'Executive Summary'!$C$12 -> 6134.1662 | M38: =M20-M36 -> 446840.72 | N38: =M38/'Executive Summary'!$C$12 -> 5585.5091
B40: Yield on Purchase Price | C40: =IFERROR(C38/'Executive Summary'!$C$30,0) -> 0.06740634 | E40: =IFERROR(E38/'Executive Summary'!$C$30,0) -> 0.059008 | G40: =IFERROR(G38/'Executive Summary'!$C$30,0) -> 0.063352453 | I40: =IFERROR(I38/'Executive Summary'!$C$30,0) -> 0.067806655 | K40: =IFERROR(K38/'Executive Summary'!$C$30,0) -> 0.07407295 | M40: =IFERROR(M38/'Executive Summary'!$C$30,0) -> 0.067447656
B41: Yield on Total Cost | C41: =IFERROR(C38/'Executive Summary'!$I$23,0) -> 0.063720187 | E41: =IFERROR(E38/'Executive Summary'!$I$23,0) -> 0.055781115 | G41: =IFERROR(G38/'Executive Summary'!$I$23,0) -> 0.059887989 | I41: =IFERROR(I38/'Executive Summary'!$I$23,0) -> 0.064098611 | K41: =IFERROR(K38/'Executive Summary'!$I$23,0) -> 0.07002223 | M41: =IFERROR(M38/'Executive Summary'!$I$23,0) -> 0.063759244
B42: Return on Equity [3] | C42: =(C38+'Cash Flow - Monthly'!$H$74*12-'Cash Flow - Monthly'!$H$65*12)/'Executive Summary'!$P$7 -> 0.082764577 | E42: =(E38+'Cash Flow - Monthly'!$H$74*12-'Cash Flow - Monthly'!$H$65*12)/'Executive Summary'!$P$7 -> 0.056043052 | G42: =(G38+'Cash Flow - Monthly'!$H$74*12-'Cash Flow - Monthly'!$H$65*12)/'Executive Summary'!$P$7 -> 0.069866071 | I42: =(I38+'Cash Flow - Monthly'!$H$74*12-'Cash Flow - Monthly'!$H$65*12)/'Executive Summary'!$P$7 -> 0.084038286 | K42: =(K38+'Cash Flow - Monthly'!$H$74*12-'Cash Flow - Monthly'!$H$65*12)/'Executive Summary'!$P$7 -> 0.10397615 | M42: =(M38+'Cash Flow - Monthly'!$H$74*12-'Cash Flow - Monthly'!$H$65*12)/'Executive Summary'!$P$7 -> 0.082896038
B44: [1] T3 Adjusted is T3 income and Controllable expenses annualized, and pro forma Taxes, Insurance, and Management Fee.
B45: [2] Assumptions are pro forma numbers without factoring in any market growth or inflation projections or Y1 adjustments.
B46: [3] Trailing and Y1 assume Y1 debt, Y2 assumes Y2 debt, and all figures assume recurring reserves.

Sheet T-3 Worksheet
B2: ='Executive Summary'!B2 -> Riverhill TH
B3: T-3 Worksheet
C4: 1 | D4: 2 | E4: 3 | F4: Total | G4: Annualized
B5: REVENUES
B6: Rental Income
B7: Rent Revenue | C7: 60647 | D7: 60656 | E7: 61853 | F7: =SUM(C7:E7) -> 183156 | G7: =F7/3*12 -> 732624
B8: Gain (Loss) to Lease | C8: -2255 | D8: -130 | E8: -1909 | F8: =SUM(C8:E8) -> -4294 | G8: =F8/3*12 -> -17176
B9: Gross Potential Rent | C9: =SUM(C7:C8) -> 58392 | D9: =SUM(D7:D8) -> 60526 | E9: =SUM(E7:E8) -> 59944 | F9: =SUM(F7:F8) -> 178862 | G9: =F9/3*12 -> 715448
B11: Vacancy Rate | C11: =ABS(C12/C9) -> 0.080045212 | D11: =ABS(D12/D9) -> 0.088870898 | E11: =ABS(E12/E9) -> 0.038686107 | F11: =ABS(F12/F9) -> 0.069170646 | G11: =ABS(G12/G9) -> 0.069170646
B12: Total Vacancy | C12: -4674 | D12: -5379 | E12: -2319 | F12: =SUM(C12:E12) -> -12372 | G12: =F12/3*12 -> -49488
B14: Rental Losses | C14: 0 | D14: 0 | E14: 0 | F14: =SUM(C14:E14) -> 0 | G14: =F14/3*12 -> 0
B15: Bad Debt | C15: -1058 | D15: -220 | E15: -239 | F15: =SUM(C15:E15) -> -1517 | G15: =F15/3*12 -> -6068
B16: Net Rental Income | C16: =SUM(C9,C12,C14:C15) -> 52660 | D16: =SUM(D9,D12,D14:D15) -> 54927 | E16: =SUM(E9,E12,E14:E15) -> 57386 | F16: =SUM(F9,F12,F14:F15) -> 164973 | G16: =F16/3*12 -> 659892
B17: Other Income
B18: Utility Reimbursements | C18: 3469 | D18: 3126 | E18: 3326 | F18: =SUM(C18:E18) -> 9921 | G18: =F18/3*12 -> 39684
B19: Late Fees | C19: 690 | D19: 448 | E19: 154 | F19: =SUM(C19:E19) -> 1292 | G19: =F19/3*12 -> 5168
B20: Other | C20: 4405 | D20: 3797 | E20: 4922 | F20: =SUM(C20:E20) -> 13124 | G20: =F20/3*12 -> 52496
B21: Total Other Income | C21: =SUM(C18:C20) -> 8564 | D21: =SUM(D18:D20) -> 7371 | E21: =SUM(E18:E20) -> 8402 | F21: =SUM(F18:F20) -> 24337 | G21: =F21/3*12 -> 97348
B22: TOTAL REVENUES | C22: =SUM(C16,C21) -> 61224 | D22: =SUM(D16,D21) -> 62298 | E22: =SUM(E16,E21) -> 65788 | F22: =SUM(F16,F21) -> 189310 | G22: =F22/3*12 -> 757240
B24: EXPENSES
B25: Controllable
B26: Payroll | C26: 11393 | D26: 8182 | E26: 9118 | F26: =SUM(C26:E26) -> 28693 | G26: =F26/3*12 -> 114772
B27: Operations & Maintenance | C27: 4919 | D27: 4800 | E27: 5403 | F27: =SUM(C27:E27) -> 15122 | G27: =F27/3*12 -> 60488
B28: Marketing | C28: 1192 | D28: 1010 | E28: 1082 | F28: =SUM(C28:E28) -> 3284 | G28: =F28/3*12 -> 13136
B29: General & Administrative | C29: 2846 | D29: 2431 | E29: 1242 | F29: =SUM(C29:E29) -> 6519 | G29: =F29/3*12 -> 26076
B30: Utilities: Reimbursable | C30: 3655 | D30: 4111 | E30: 4694 | F30: =SUM(C30:E30) -> 12460 | G30: =F30/3*12 -> 49840
B31: Utilities: Other | C31: 478 | D31: 220 | E31: 329 | F31: =SUM(C31:E31) -> 1027 | G31: =F31/3*12 -> 4108
B32: Total Controllable | C32: =SUM(C26:C31) -> 24483 | D32: =SUM(D26:D31) -> 20754 | E32: =SUM(E26:E31) -> 21868 | F32: =SUM(F26:F31) -> 67105 | G32: =F32/3*12 -> 268420
B33: Noncontrollable | G33: =F33/3*12 -> 0
B34: Taxes | C34: 4621 | D34: 4560 | E34: 4560 | F34: =SUM(C34:E34) -> 13741 | G34: =F34/3*12 -> 54964
B35: Insurance | C35: 2311 | D35: 1646 | E35: 2271 | F35: =SUM(C35:E35) -> 6228 | G35: =F35/3*12 -> 24912
B36: Property Management Fee | C36: 768 | D36: 1738 | E36: 1998 | F36: =SUM(C36:E36) -> 4504 | G36: =F36/3*12 -> 18016
B37: Total Noncontrollable | C37: =SUM(C34:C36) -> 7700 | D37: =SUM(D34:D36) -> 7944 | E37: =SUM(E34:E36) -> 8829 | F37: =SUM(C37:E37) -> 24473 | G37: =F37/3*12 -> 97892
B38: TOTAL EXPENSES | C38: =SUM(C32,C37) -> 32183 | D38: =SUM(D32,D37) -> 28698 | E38: =SUM(E32,E37) -> 30697 | F38: =SUM(F32,F37) -> 91578 | G38: =F38/3*12 -> 366312
B40: NET OPERATING INCOME | C40: =C22-C38 -> 29041 | D40: =D22-D38 -> 33600 | E40: =E22-E38 -> 35091 | F40: =SUM(C40:E40) -> 97732 | G40: =F40/3*12 -> 390928

Sheet Unit Mix & Comparables
B2: ='Cash Flow - Monthly'!B2 -> Riverhill TH
B3: Unit Mix & Comparables
B5: Post Renovation | C5: Subject Pro Forma | I5: Subject Current | R5: Comparable #1 | X5: Comparable #2 | AD5: Comparable #3 | AJ5: Comparable #4 | AP5: Comparable #5 | AV5: Comparable #6 | BB5: Comparable #7
B6: Property Name | C6: ='Executive Summary'!$C$5 -> Riverhill TH | H6: B | I6: ='Executive Summary'!$C$5 -> Riverhill TH | Q6: B | R6: Johnathan's Ridge | W6: B | X6: Riverside Manor | AC6: B | AD6: Windy Lakes | AI6: B | AJ6: Riverside South | AO6: B | AP6: Country View | AU6: B | AV6: Camellia Trace | BA6: B | BB6: Bridgeway
B7: Age | C7: ='Executive Summary'!$C$9 -> 1982 | I7: ='Executive Summary'!$C$9 -> 1982 | O7: Pre Reno | P7: Avg-Reno Premium | R7: 1982 | X7: 1985 | AD7: 1979 | AJ7: 1988 | AP7: 1993 | AV7: 2004 | BB7: 2012
C8: Count | D8: Beds | E8: Baths | F8: SF | G8: $ | H8: $/SF | I8: Count | J8: Beds | K8: Baths | L8: SF | M8: $ | N8: $/SF | O8: Variance | R8: Count | S8: Beds | T8: Baths | U8: SF | V8: $ | W8: $/SF | X8: Count | Y8: Beds | Z8: Baths | AA8: SF | AB8: $ | AC8: $/SF | AD8: Count | AE8: Beds | AF8: Baths | AG8: SF | AH8: $ | AI8: $/SF | AJ8: Count | AK8: Beds | AL8: Baths | AM8: SF | AN8: $ | AO8: $/SF | AP8: Count | AQ8: Beds | AR8: Baths | AS8: SF | AT8: $ | AU8: $/SF | AV8: Count | AW8: Beds | AX8: Baths | AY8: SF | AZ8: $ | BA8: $/SF | BB8: Count | BC8: Beds | BD8: Baths | BE8: SF | BF8: $ | BG8: $/SF
B9: 2BD/1.5TH | C9: 2 | D9: 2 | E9: 1.5 | F9: 1008 | G9: 729 | H9: =IFERROR(IF(C9, G9/F9, 0),0) -> 0.72321429 | I9: =IF(C9<>"",C9,"") -> 2 | J9: =IF(D9<>"",D9,"") -> 2 | K9: =IF(E9<>"",E9,"") -> 1.5 | L9: =IF(F9<>"",F9,"") -> 1008 | M9: 703 | N9: =IFERROR(IF(I9, M9/L9, 0),0) -> 0.69742063 | O9: =G9-M9 -> 26 | P9: ='Unit Reno Premium Comp'!F5-'Unit Mix & Comparables'!G9 -> 98 | R9: 50 | S9: 2 | T9: 1 | U9: 950 | V9: 650 | W9: =IFERROR(IF(R9, V9/U9, 0),0) -> 0.68421053 | X9: 25 | Y9: 1 | Z9: 1 | AA9: 570 | AB9: 345 | AC9: =IFERROR(IF(X9, AB9/AA9, 0),0) -> 0.60526316 | AD9: 50 | AE9: 1 | AF9: 1 | AG9: 700 | AH9: 430 | AI9: =IFERROR(IF(AD9, AH9/AG9, 0),0) -> 0.61428571 | AJ9: 25 | AK9: 0 | AL9: 1 | AM9: 500 | AN9: 375 | AO9: =IFERROR(IF(AJ9, AN9/AM9, 0),0) -> 0.75 | AP9: 25 | AQ9: 1 | AR9: 1 | AS9: 450 | AT9: 395 | AU9: =IFERROR(IF(AP9, AT9/AS9, 0),0) -> 0.87777778 | AV9: 25 | AW9: 1 | AX9: 1 | AY9: 671 | AZ9: 776 | BA9: =IFERROR(IF(AV9, AZ9/AY9, 0),0) -> 1.1564829 | BG9: =IFERROR(IF(BB9, BF9/BE9, 0),0) -> 0
B10: 2BD/1.5TH-D | C10: 15 | D10: 2 | E10: 1.5 | F10: 1008 | G10: 772 | H10: =IFERROR(IF(C10, G10/F10, 0),0) -> 0.76587302 | I10: =IF(C10<>"",C10,"") -> 15 | J10: =IF(D10<>"",D10,"") -> 2 | K10: =IF(E10<>"",E10,"") -> 1.5 | L10: =IF(F10<>"",F10,"") -> 1008 | M10: 772 | N10: =IFERROR(IF(I10, M10/L10, 0),0) -> 0.76587302 | O10: =G10-M10 -> 0 | P10: ='Unit Reno Premium Comp'!F6-'Unit Mix & Comparables'!G10 -> 55 | R10: 50 | S10: 2 | T10: 1 | U10: 95 | V10: 690 | W10: =IFERROR(IF(R10, V10/U10, 0),0) -> 7.2631579 | X10: 25 | Y10: 1 | Z10: 1 | AA10: 620 | AB10: 380 | AC10: =IFERROR(IF(X10, AB10/AA10, 0),0) -> 0.61290323 | AD10: 50 | AE10: 2 | AF10: 1 | AG10: 950 | AH10: 530 | AI10: =IFERROR(IF(AD10, AH10/AG10, 0),0) -> 0.55789474 | AJ10: 25 | AK10: 1 | AL10: 1 | AM10: 583 | AN10: 404 | AO10: =IFERROR(IF(AJ10, AN10/AM10, 0),0) -> 0.69296741 | AP10: 25 | AQ10: 2 | AR10: 1 | AS10: 720 | AT10: 495 | AU10: =IFERROR(IF(AP10, AT10/AS10, 0),0) -> 0.6875 | AV10: 25 | AW10: 1 | AX10: 1 | AY10: 772 | AZ10: 836 | BA10: =IFERROR(IF(AV10, AZ10/AY10, 0),0) -> 1.0829016 | BG10: =IFERROR(IF(BB10, BF10/BE10, 0),0) -> 0
B11: 2BD/1.5TH-P | C11: 63 | D11: 2 | E11: 1.5 | F11: 1008 | G11: 780 | H11: =IFERROR(IF(C11, G11/F11, 0),0) -> 0.77380952 | I11: =IF(C11<>"",C11,"") -> 63 | J11: =IF(D11<>"",D11,"") -> 2 | K11: =IF(E11<>"",E11,"") -> 1.5 | L11: =IF(F11<>"",F11,"") -> 1008 | M11: 778 | N11: =IFERROR(IF(I11, M11/L11, 0),0) -> 0.7718254 | O11: =G11-M11 -> 2 | P11: 0 | W11: =IFERROR(IF(R11, V11/U11, 0),0) -> 0 | X11: 25 | Y11: 1 | Z11: 1 | AA11: 640 | AB11: 390 | AC11: =IFERROR(IF(X11, AB11/AA11, 0),0) -> 0.609375 | AI11: =IFERROR(IF(AD11, AH11/AG11, 0),0) -> 0 | AJ11: 25 | AK11: 2 | AL11: 1 | AM11: 750 | AN11: 457 | AO11: =IFERROR(IF(AJ11, AN11/AM11, 0),0) -> 0.60933333 | AP11: 25 | AQ11: 2 | AR11: 1 | AS11: 828 | AT11: 525 | AU11: =IFERROR(IF(AP11, AT11/AS11, 0),0) -> 0.63405797 | AV11: 25 | AW11: 1 | AX11: 1 | AY11: 907 | AZ11: 886 | BA11: =IFERROR(IF(AV11, AZ11/AY11, 0),0) -> 0.97684675 | BG11: =IFERROR(IF(BB11, BF11/BE11, 0),0) -> 0
H12: =IFERROR(IF(C12, G12/F12, 0),0) -> 0 | I12: =IF(C12<>"",C12,"") | J12: =IF(D12<>"",D12,"") | K12: =IF(E12<>"",E12,"") | L12: =IF(F12<>"",F12,"") | N12: =IFERROR(IF(I12, M12/L12, 0),0) -> 0 | O12: =G12-M12 -> 0 | P12: 0 | W12: =IFERROR(IF(R12, V12/U12, 0),0) -> 0 | X12: 25 | Y12: 2 | Z12: 1 | AA12: 680 | AB12: 400 | AC12: =IFERROR(IF(X12, AB12/AA12, 0),0) -> 0.58823529 | AI12: =IFERROR(IF(AD12, AH12/AG12, 0),0) -> 0 | AJ12: 25 | AK12: 3 | AL12: 1 | AM12: 878 | AN12: 565 | AO12: =IFERROR(IF(AJ12, AN12/AM12, 0),0) -> 0.64350797 | AU12: =IFERROR(IF(AP12, AT12/AS12, 0),0) -> 0 | AV12: 25 | AW12: 2 | AX12: 2 | AY12: 1197 | AZ12: 946 | BA12: =IFERROR(IF(AV12, AZ12/AY12, 0),0) -> 0.79030911 | BG12: =IFERROR(IF(BB12, BF12/BE12, 0),0) -> 0
H13: =IFERROR(IF(C13, G13/F13, 0),0) -> 0 | I13: =IF(C13<>"",C13,"") | J13: =IF(D13<>"",D13,"") | K13: =IF(E13<>"",E13,"") | L13: =IF(F13<>"",F13,"") | N13: =IFERROR(IF(I13, M13/L13, 0),0) -> 0 | O13: =G13-M13 -> 0 | P13: ='Unit Reno Premium Comp'!F9-'Unit Mix & Comparables'!G13 -> 0 | W13: =IFERROR(IF(R13, V13/U13, 0),0) -> 0 | X13: 25 | Y13: 2 | Z13: 1 | AA13: 740 | AB13: 425 | AC13: =IFERROR(IF(X13, AB13/AA13, 0),0) -> 0.57432432 | AI13: =IFERROR(IF(AD13, AH13/AG13, 0),0) -> 0 | AJ13: 25 | AK13: 4 | AL13: 2 | AM13: 1560 | AN13: 750 | AO13: =IFERROR(IF(AJ13, AN13/AM13, 0),0) -> 0.48076923 | AU13: =IFERROR(IF(AP13, AT13/AS13, 0),0) -> 0 | AV13: 25 | AW13: 2 | AX13: 2 | AY13: 1208 | AZ13: 996 | BA13: =IFERROR(IF(AV13, AZ13/AY13, 0),0) -> 0.82450331 | BG13: =IFERROR(IF(BB13, BF13/BE13, 0),0) -> 0
H14: =IFERROR(IF(C14, G14/F14, 0),0) -> 0 | I14: =IF(C14<>"",C14,"") | J14: =IF(D14<>"",D14,"") | K14: =IF(E14<>"",E14,"") | L14: =IF(F14<>"",F14,"") | N14: =IFERROR(IF(I14, M14/L14, 0),0) -> 0 | O14: =G14-M14 -> 0 | P14: ='Unit Reno Premium Comp'!F10-'Unit Mix & Comparables'!G14 -> 0 | W14: =IFERROR(IF(R14, V14/U14, 0),0) -> 0 | X14: 25 | Y14: 2 | Z14: 1 | AA14: 750 | AB14: 430 | AC14: =IFERROR(IF(X14, AB14/AA14, 0),0) -> 0.57333333 | AI14: =IFERROR(IF(AD14, AH14/AG14, 0),0) -> 0 | AO14: =IFERROR(IF(AJ14, AN14/AM14, 0),0) -> 0 | AU14: =IFERROR(IF(AP14, AT14/AS14, 0),0) -> 0 | AV14: 25 | AW14: 3 | AX14: 2 | AY14: 1414 | AZ14: 1206 | BA14: =IFERROR(IF(AV14, AZ14/AY14, 0),0) -> 0.85289958 | BG14: =IFERROR(IF(BB14, BF14/BE14, 0),0) -> 0
H15: =IFERROR(IF(C15, G15/F15, 0),0) -> 0 | I15: =IF(C15<>"",C15,"") | J15: =IF(D15<>"",D15,"") | K15: =IF(E15<>"",E15,"") | L15: =IF(F15<>"",F15,"") | N15: =IFERROR(IF(I15, M15/L15, 0),0) -> 0 | O15: =G15-M15 -> 0 | P15: ='Unit Reno Premium Comp'!F11-'Unit Mix & Comparables'!G15 -> 0 | W15: =IFERROR(IF(R15, V15/U15, 0),0) -> 0 | X15: 25 | Y15: 2 | Z15: 1 | AA15: 860 | AB15: 435 | AC15: =IFERROR(IF(X15, AB15/AA15, 0),0) -> 0.50581395 | AI15: =IFERROR(IF(AD15, AH15/AG15, 0),0) -> 0 | AO15: =IFERROR(IF(AJ15, AN15/AM15, 0),0) -> 0 | AU15: =IFERROR(IF(AP15, AT15/AS15, 0),0) -> 0 | BA15: =IFERROR(IF(AV15, AZ15/AY15, 0),0) -> 0 | BG15: =IFERROR(IF(BB15, BF15/BE15, 0),0) -> 0
H16: =IFERROR(IF(C16, G16/F16, 0),0) -> 0 | I16: =IF(C16<>"",C16,"") | J16: =IF(D16<>"",D16,"") | K16: =IF(E16<>"",E16,"") | L16: =IF(F16<>"",F16,"") | N16: =IFERROR(IF(I16, M16/L16, 0),0) -> 0 | O16: =G16-M16 -> 0 | P16: ='Unit Reno Premium Comp'!F12-'Unit Mix & Comparables'!G16 -> 0 | W16: =IFERROR(IF(R16, V16/U16, 0),0) -> 0 | X16: 25 | Y16: 3 | Z16: 1 | AA16: 875 | AB16: 460 | AC16: =IFERROR(IF(X16, AB16/AA16, 0),0) -> 0.52571429 | AI16: =IFERROR(IF(AD16, AH16/AG16, 0),0) -> 0 | AO16: =IFERROR(IF(AJ16, AN16/AM16, 0),0) -> 0 | AU16: =IFERROR(IF(AP16, AT16/AS16, 0),0) -> 0 | BA16: =IFERROR(IF(AV16, AZ16/AY16, 0),0) -> 0 | BG16: =IFERROR(IF(BB16, BF16/BE16, 0),0) -> 0
H17: =IFERROR(IF(C17, G17/F17, 0),0) -> 0 | I17: =IF(C17<>"",C17,"") | J17: =IF(D17<>"",D17,"") | K17: =IF(E17<>"",E17,"") | L17: =IF(F17<>"",F17,"") | N17: =IFERROR(IF(I17, M17/L17, 0),0) -> 0 | O17: =G17-M17 -> 0 | P17: ='Unit Reno Premium Comp'!F13-'Unit Mix & Comparables'!G17 -> 0 | W17: =IFERROR(IF(R17, V17/U17, 0),0) -> 0 | AC17: =IFERROR(IF(X17, AB17/AA17, 0),0) -> 0 | AI17: =IFERROR(IF(AD17, AH17/AG17, 0),0) -> 0 | AO17: =IFERROR(IF(AJ17, AN17/AM17, 0),0) -> 0 | AU17: =IFERROR(IF(AP17, AT17/AS17, 0),0) -> 0 | BA17: =IFERROR(IF(AV17, AZ17/AY17, 0),0) -> 0 | BG17: =IFERROR(IF(BB17, BF17/BE17, 0),0) -> 0
H18: =IFERROR(IF(C18, G18/F18, 0),0) -> 0 | I18: =IF(C18<>"",C18,"") | J18: =IF(D18<>"",D18,"") | K18: =IF(E18<>"",E18,"") | L18: =IF(F18<>"",F18,"") | N18: =IFERROR(IF(I18, M18/L18, 0),0) -> 0 | O18: =G18-M18 -> 0 | P18: ='Unit Reno Premium Comp'!F14-'Unit Mix & Comparables'!G18 -> 0 | W18: =IFERROR(IF(R18, V18/U18, 0),0) -> 0 | AC18: =IFERROR(IF(X18, AB18/AA18, 0),0) -> 0 | AI18: =IFERROR(IF(AD18, AH18/AG18, 0),0) -> 0 | AO18: =IFERROR(IF(AJ18, AN18/AM18, 0),0) -> 0 | AU18: =IFERROR(IF(AP18, AT18/AS18, 0),0) -> 0 | BA18: =IFERROR(IF(AV18, AZ18/AY18, 0),0) -> 0 | BG18: =IFERROR(IF(BB18, BF18/BE18, 0),0) -> 0
H19: =IFERROR(IF(C19, G19/F19, 0),0) -> 0 | I19: =IF(C19<>"",C19,"") | J19: =IF(D19<>"",D19,"") | K19: =IF(E19<>"",E19,"") | L19: =IF(F19<>"",F19,"") | N19: =IFERROR(IF(I19, M19/L19, 0),0) -> 0 | O19: =G19-M19 -> 0 | P19: ='Unit Reno Premium Comp'!F15-'Unit Mix & Comparables'!G19 -> 0 | W19: =IFERROR(IF(R19, V19/U19, 0),0) -> 0 | AC19: =IFERROR(IF(X19, AB19/AA19, 0),0) -> 0 | AI19: =IFERROR(IF(AD19, AH19/AG19, 0),0) -> 0 | AO19: =IFERROR(IF(AJ19, AN19/AM19, 0),0) -> 0 | AU19: =IFERROR(IF(AP19, AT19/AS19, 0),0) -> 0 | BA19: =IFERROR(IF(AV19, AZ19/AY19, 0),0) -> 0 | BG19: =IFERROR(IF(BB19, BF19/BE19, 0),0) -> 0
H20: =IFERROR(IF(C20, G20/F20, 0),0) -> 0 | I20: =IF(C20<>"",C20,"") | J20: =IF(D20<>"",D20,"") | K20: =IF(E20<>"",E20,"") | L20: =IF(F20<>"",F20,"") | N20: =IFERROR(IF(I20, M20/L20, 0),0) -> 0 | O20: =G20-M20 -> 0 | P20: ='Unit Reno Premium Comp'!F16-'Unit Mix & Comparables'!G20 -> 0 | AU20: =IFERROR(IF(AP20, AT20/AS20, 0),0) -> 0 | BG20: =IFERROR(IF(BB20, BF20/BE20, 0),0) -> 0
H21: =IFERROR(IF(C21, G21/F21, 0),0) -> 0 | I21: =IF(C21<>"",C21,"") | J21: =IF(D21<>"",D21,"") | K21: =IF(E21<>"",E21,"") | L21: =IF(F21<>"",F21,"") | N21: =IFERROR(IF(I21, M21/L21, 0),0) -> 0 | O21: =G21-M21 -> 0 | P21: ='Unit Reno Premium Comp'!F17-'Unit Mix & Comparables'!G21 -> 0 | AU21: =IFERROR(IF(AP21, AT21/AS21, 0),0) -> 0 | BG21: =IFERROR(IF(BB21, BF21/BE21, 0),0) -> 0
H22: =IFERROR(IF(C22, G22/F22, 0),0) -> 0 | I22: =IF(C22<>"",C22,"") | J22: =IF(D22<>"",D22,"") | K22: =IF(E22<>"",E22,"") | L22: =IF(F22<>"",F22,"") | N22: =IFERROR(IF(I22, M22/L22, 0),0) -> 0 | O22: =G22-M22 -> 0 | P22: ='Unit Reno Premium Comp'!F18-'Unit Mix & Comparables'!G22 -> 0 | AU22: =IFERROR(IF(AP22, AT22/AS22, 0),0) -> 0 | BG22: =IFERROR(IF(BB22, BF22/BE22, 0),0) -> 0
H23: =IFERROR(IF(C23, G23/F23, 0),0) -> 0 | I23: =IF(C23<>"",C23,"") | J23: =IF(D23<>"",D23,"") | K23: =IF(E23<>"",E23,"") | L23: =IF(F23<>"",F23,"") | N23: =IFERROR(IF(I23, M23/L23, 0),0) -> 0 | O23: =G23-M23 -> 0 | P23: ='Unit Reno Premium Comp'!F19-'Unit Mix & Comparables'!G23 -> 0 | AU23: =IFERROR(IF(AP23, AT23/AS23, 0),0) -> 0 | BG23: =IFERROR(IF(BB23, BF23/BE23, 0),0) -> 0
H24: =IFERROR(IF(C24, G24/F24, 0),0) -> 0 | I24: =IF(C24<>"",C24,"") | J24: =IF(D24<>"",D24,"") | K24: =IF(E24<>"",E24,"") | L24: =IF(F24<>"",F24,"") | N24: =IFERROR(IF(I24, M24/L24, 0),0) -> 0 | O24: =G24-M24 -> 0 | P24: ='Unit Reno Premium Comp'!F20-'Unit Mix & Comparables'!G24 -> 0 | AU24: =IFERROR(IF(AP24, AT24/AS24, 0),0) -> 0 | BG24: =IFERROR(IF(BB24, BF24/BE24, 0),0) -> 0
H25: =IFERROR(IF(C25, G25/F25, 0),0) -> 0 | I25: =IF(C25<>"",C25,"") | J25: =IF(D25<>"",D25,"") | K25: =IF(E25<>"",E25,"") | L25: =IF(F25<>"",F25,"") | N25: =IFERROR(IF(I25, M25/L25, 0),0) -> 0 | O25: =G25-M25 -> 0 | P25: ='Unit Reno Premium Comp'!F21-'Unit Mix & Comparables'!G25 -> 0 | AU25: =IFERROR(IF(AP25, AT25/AS25, 0),0) -> 0 | BG25: =IFERROR(IF(BB25, BF25/BE25, 0),0) -> 0
H26: =IFERROR(IF(C26, G26/F26, 0),0) -> 0 | I26: =IF(C26<>"",C26,"") | J26: =IF(D26<>"",D26,"") | K26: =IF(E26<>"",E26,"") | L26: =IF(F26<>"",F26,"") | N26: =IFERROR(IF(I26, M26/L26, 0),0) -> 0 | O26: =G26-M26 -> 0 | P26: ='Unit Reno Premium Comp'!F22-'Unit Mix & Comparables'!G26 -> 0 | AU26: =IFERROR(IF(AP26, AT26/AS26, 0),0) -> 0 | BG26: =IFERROR(IF(BB26, BF26/BE26, 0),0) -> 0
H27: =IFERROR(IF(C27, G27/F27, 0),0) -> 0 | I27: =IF(C27<>"",C27,"") | J27: =IF(D27<>"",D27,"") | K27: =IF(E27<>"",E27,"") | L27: =IF(F27<>"",F27,"") | N27: =IFERROR(IF(I27, M27/L27, 0),0) -> 0 | O27: =G27-M27 -> 0 | P27: ='Unit Reno Premium Comp'!F23-'Unit Mix & Comparables'!G27 -> 0 | AU27: =IFERROR(IF(AP27, AT27/AS27, 0),0) -> 0 | BG27: =IFERROR(IF(BB27, BF27/BE27, 0),0) -> 0
H28: =IFERROR(IF(C28, G28/F28, 0),0) -> 0 | I28: =IF(C28<>"",C28,"") | J28: =IF(D28<>"",D28,"") | K28: =IF(E28<>"",E28,"") | L28: =IF(F28<>"",F28,"") | N28: =IFERROR(IF(I28, M28/L28, 0),0) -> 0 | O28: =G28-M28 -> 0 | P28: ='Unit Reno Premium Comp'!F24-'Unit Mix & Comparables'!G28 -> 0 | AU28: =IFERROR(IF(AP28, AT28/AS28, 0),0) -> 0 | BG28: =IFERROR(IF(BB28, BF28/BE28, 0),0) -> 0
H29: =IFERROR(IF(C29, G29/F29, 0),0) -> 0 | I29: =IF(C29<>"",C29,"") | J29: =IF(D29<>"",D29,"") | K29: =IF(E29<>"",E29,"") | L29: =IF(F29<>"",F29,"") | N29: =IFERROR(IF(I29, M29/L29, 0),0) -> 0 | O29: =G29-M29 -> 0 | P29: ='Unit Reno Premium Comp'!F25-'Unit Mix & Comparables'!G29 -> 0 | AU29: =IFERROR(IF(AP29, AT29/AS29, 0),0) -> 0 | BG29: =IFERROR(IF(BB29, BF29/BE29, 0),0) -> 0
H30: =IFERROR(IF(C30, G30/F30, 0),0) -> 0 | I30: =IF(C30<>"",C30,"") | J30: =IF(D30<>"",D30,"") | K30: =IF(E30<>"",E30,"") | L30: =IF(F30<>"",F30,"") | N30: =IFERROR(IF(I30, M30/L30, 0),0) -> 0 | O30: =G30-M30 -> 0 | P30: ='Unit Reno Premium Comp'!F26-'Unit Mix & Comparables'!G30 -> 0 | AU30: =IFERROR(IF(AP30, AT30/AS30, 0),0) -> 0 | BG30: =IFERROR(IF(BB30, BF30/BE30, 0),0) -> 0
H31: =IFERROR(IF(C31, G31/F31, 0),0) -> 0 | I31: =IF(C31<>"",C31,"") | J31: =IF(D31<>"",D31,"") | K31: =IF(E31<>"",E31,"") | L31: =IF(F31<>"",F31,"") | N31: =IFERROR(IF(I31, M31/L31, 0),0) -> 0 | O31: =G31-M31 -> 0 | P31: ='Unit Reno Premium Comp'!F27-'Unit Mix & Comparables'!G31 -> 0 | AU31: =IFERROR(IF(AP31, AT31/AS31, 0),0) -> 0 | BG31: =IFERROR(IF(BB31, BF31/BE31, 0),0) -> 0
H32: =IFERROR(IF(C32, G32/F32, 0),0) -> 0 | I32: =IF(C32<>"",C32,"") | J32: =IF(D32<>"",D32,"") | K32: =IF(E32<>"",E32,"") | L32: =IF(F32<>"",F32,"") | N32: =IFERROR(IF(I32, M32/L32, 0),0) -> 0 | O32: =G32-M32 -> 0 | P32: ='Unit Reno Premium Comp'!F28-'Unit Mix & Comparables'!G32 -> 0 | AU32: =IFERROR(IF(AP32, AT32/AS32, 0),0) -> 0
H33: =IFERROR(IF(C33, G33/F33, 0),0) -> 0 | I33: =IF(C33<>"",C33,"") | J33: =IF(D33<>"",D33,"") | K33: =IF(E33<>"",E33,"") | L33: =IF(F33<>"",F33,"") | N33: =IFERROR(IF(I33, M33/L33, 0),0) -> 0 | O33: =G33-M33 -> 0 | P33: ='Unit Reno Premium Comp'!F29-'Unit Mix & Comparables'!G33 -> 0 | AU33: =IFERROR(IF(AP33, AT33/AS33, 0),0) -> 0
H34: =IFERROR(IF(C34, G34/F34, 0),0) -> 0 | I34: =IF(C34<>"",C34,"") | J34: =IF(D34<>"",D34,"") | K34: =IF(E34<>"",E34,"") | L34: =IF(F34<>"",F34,"") | N34: =IFERROR(IF(I34, M34/L34, 0),0) -> 0 | O34: =G34-M34 -> 0 | P34: 0 | AU34: =IFERROR(IF(AP34, AT34/AS34, 0),0) -> 0
H35: =IFERROR(IF(C35, G35/F35, 0),0) -> 0 | I35: =IF(C35<>"",C35,"") | J35: =IF(D35<>"",D35,"") | K35: =IF(E35<>"",E35,"") | L35: =IF(F35<>"",F35,"") | N35: =IFERROR(IF(I35, M35/L35, 0),0) -> 0 | O35: =G35-M35 -> 0 | P35: ='Unit Reno Premium Comp'!F31-'Unit Mix & Comparables'!G35 -> 0 | AU35: =IFERROR(IF(AP35, AT35/AS35, 0),0) -> 0
H36: =IFERROR(IF(C36, G36/F36, 0),0) -> 0 | I36: =IF(C36<>"",C36,"") | J36: =IF(D36<>"",D36,"") | K36: =IF(E36<>"",E36,"") | L36: =IF(F36<>"",F36,"") | N36: =IFERROR(IF(I36, M36/L36, 0),0) -> 0 | O36: =G36-M36 -> 0 | P36: ='Unit Reno Premium Comp'!F32-'Unit Mix & Comparables'!G36 -> 0 | AU36: =IFERROR(IF(AP36, AT36/AS36, 0),0) -> 0
H37: =IFERROR(IF(C37, G37/F37, 0),0) -> 0 | I37: =IF(C37<>"",C37,"") | J37: =IF(D37<>"",D37,"") | K37: =IF(E37<>"",E37,"") | L37: =IF(F37<>"",F37,"") | N37: =IFERROR(IF(I37, M37/L37, 0),0) -> 0 | O37: =G37-M37 -> 0 | P37: ='Unit Reno Premium Comp'!F33-'Unit Mix & Comparables'!G37 -> 0 | AU37: =IFERROR(IF(AP37, AT37/AS37, 0),0) -> 0
H38: =IFERROR(IF(C38, G38/F38, 0),0) -> 0 | I38: =IF(C38<>"",C38,"") | J38: =IF(D38<>"",D38,"") | K38: =IF(E38<>"",E38,"") | L38: =IF(F38<>"",F38,"") | N38: =IFERROR(IF(I38, M38/L38, 0),0) -> 0 | O38: =G38-M38 -> 0 | P38: ='Unit Reno Premium Comp'!F34-'Unit Mix & Comparables'!M38 -> 0
B39: Total/Average | C39: =SUM(C9:C38) -> 80 | F39: =SUMPRODUCT(C9:C38, F9:F38)/C39 -> 1008 | G39: =SUMPRODUCT(C9:C38, G9:G38)/C39 -> 777.225 | H39: =IFERROR(G39/F39,0) -> 0.77105655 | I39: =SUM(I9:I38) -> 80 | L39: =SUMPRODUCT(I9:I38, L9:L38)/I39 -> 1008 | M39: =SUMPRODUCT(I9:I38, M9:M38)/I39 -> 775 | N39: =IFERROR(M39/L39,0) -> 0.76884921 | Q39: 0 | R39: =SUM(R9:R38) -> 100 | U39: =IFERROR(SUMPRODUCT(R9:R38, U9:U38)/R39,0) -> 522.5 | V39: =IFERROR(SUMPRODUCT(R9:R38, V9:V38)/R39,0) -> 670 | W39: =IFERROR(IF(R39, V39/U39, 0),0) -> 1.2822967 | X39: =SUM(X9:X38) -> 200 | AA39: =IFERROR(SUMPRODUCT(X9:X38, AA9:AA38)/X39,0) -> 716.875 | AB39: =IFERROR(SUMPRODUCT(X9:X38, AB9:AB38)/X39,0) -> 408.125 | AC39: =IFERROR(IF(X39, AB39/AA39, 0),0) -> 0.56931125 | AD39: =SUM(AD9:AD38) -> 100 | AG39: =IFERROR(SUMPRODUCT(AD9:AD38, AG9:AG38)/AD39,0) -> 825 | AH39: =IFERROR(SUMPRODUCT(AD9:AD38, AH9:AH38)/AD39,0) -> 480 | AI39: =IFERROR(IF(AD39, AH39/AG39, 0),0) -> 0.58181818 | AJ39: =SUM(AJ9:AJ38) -> 125 | AM39: =IFERROR(SUMPRODUCT(AJ9:AJ38, AM9:AM38)/AJ39,0) -> 854.2 | AN39: =IFERROR(SUMPRODUCT(AJ9:AJ38, AN9:AN38)/AJ39,0) -> 510.2 | AO39: =IFERROR(IF(AJ39, AN39/AM39, 0),0) -> 0.59728401 | AP39: =SUM(AP9:AP38) -> 75 | AS39: =IFERROR(SUMPRODUCT(AP9:AP38, AS9:AS38)/AP39,0) -> 666 | AT39: =IFERROR(SUMPRODUCT(AP9:AP38, AT9:AT38)/AP39,0) -> 471.66667 | AU39: =IFERROR(IF(AP39, AT39/AS39, 0),0) -> 0.70820821 | AV39: =SUM(AV9:AV38) -> 150 | AY39: =IFERROR(SUMPRODUCT(AV9:AV38, AY9:AY38)/AV39,0) -> 1028.1667 | AZ39: =IFERROR(SUMPRODUCT(AV9:AV38, AZ9:AZ38)/AV39,0) -> 941 | BA39: =IFERROR(IF(AV39, AZ39/AY39, 0),0) -> 0.91522127 | BB39: =SUM(BB9:BB38) -> 0 | BE39: =IFERROR(SUMPRODUCT(BB9:BB38, BE9:BE38)/BB39,0) -> 0 | BF39: =IFERROR(SUMPRODUCT(BB9:BB38, BF9:BF38)/BB39,0) -> 0 | BG39: =IFERROR(IF(BB39, BF39/BE39, 0),0) -> 0
B40: Valet Trash | C40: 0 | H40: =IFERROR(G40/F39,0) -> 0
B41: Rent Premiums | C41: =N55 -> 50
B42: Utilities/Fee Structure | C42: RUBS
B43: Washer/Dryer Charge | C43: 0
B44: Comparison Notes
AD47: Comparable #8 | AJ47: Comparable #9 | AP47: Comparable #10 | AV47: Comparable #11
B48: Rent Increase Breakdown [1] | I48: Unit Summary | AD48: Reserve at Maryville | AI48: B | AO48: B | AU48: B | BA48: A
F49: $ | G49: Share | M49: Pro Forma | AD49: 2008
B50: Increase Due to Unit Upgrades | F50: =N55 -> 50 | G50: =IF(F52, F50/$F$53, 0) -> 0.95739588 | I50: Bedrooms | J50: Count | K50: Avg. SF | L50: Current | M50: Initial | N50: Upgrade | O50: Renovation | Q50: Final | AD50: Count | AE50: Beds | AF50: Baths | AG50: SF | AH50: $ | AI50: $/SF | AJ50: Count | AK50: Beds | AL50: Baths | AM50: SF | AN50: $ | AO50: $/SF | AP50: Count | AQ50: Beds | AR50: Baths | AS50: SF | AT50: $ | AU50: $/SF | AV50: Count | AW50: Beds | AX50: Baths | AY50: SF | AZ50: $ | BA50: $/SF
B51: Premium for Property Renovation | D51: 0 | F51: =O55 -> 0 | G51: =IF(F53, F51/$F$53, 0) -> 0 | I51: 0 | J51: =SUMPRODUCT(($D$9:$D$38=I51)*($C$9:$C$38)) -> 0 | K51: =IF(J51,SUMPRODUCT(($D$9:$D$38=$I51)*($C$9:$C$38)*($F$9:$F$38))/SUMPRODUCT(($D$9:$D$38=$I51)*($C$9:$C$38)),0) -> 0 | L51: =IF(J51,SUMPRODUCT(($D$9:$D$38=$I51)*($C$9:$C$38)*($M$9:$M$38))/SUMPRODUCT(($D$9:$D$38=$I51)*($C$9:$C$38)),0) -> 0 | M51: =Q51-O51-N51 -> 0 | N51: 0 | O51: =Q51/(1+$D$51)*$D$51 -> 0 | Q51: =IF(J51, SUMPRODUCT(($D$9:$D$38=$I51)*($C$9:$C$38)*($G$9:$G$38))/SUMPRODUCT(($D$9:$D$38=$I51)*($C$9:$C$38)),0) -> 0 | R51: =Q51*J51 -> 0 | AD51: 25 | AE51: 1 | AF51: 1 | AG51: 923 | AH51: 873 | AI51: =IFERROR(IF(AD51, AH51/AG51, 0),0) -> 0.94582882 | AO51: =IFERROR(IF(AJ51, AN51/AM51, 0),0) -> 0 | AU51: =IFERROR(IF(AP51, AT51/AS51, 0),0) -> 0 | BA51: =IFERROR(AZ51/AY51,0) -> 0
B52: Increase to Market Rents | F52: =F53-(F50+F51) -> 2.225 | G52: =IF(F54, F52/$F$53, 0) -> 0 | I52: 1 | J52: =SUMPRODUCT(($D$9:$D$38=I52)*($C$9:$C$38)) -> 0 | K52: =IF(J52,SUMPRODUCT(($D$9:$D$38=$I52)*($C$9:$C$38)*($F$9:$F$38))/SUMPRODUCT(($D$9:$D$38=$I52)*($C$9:$C$38)),0) -> 0 | L52: =IF(J52,SUMPRODUCT(($D$9:$D$38=$I52)*($C$9:$C$38)*($M$9:$M$38))/SUMPRODUCT(($D$9:$D$38=$I52)*($C$9:$C$38)),0) -> 0 | M52: =IF(J52,SUMPRODUCT(($D$9:$D$38=$I52)*($C$9:$C$38)*($G$9:$G$38))/SUMPRODUCT(($D$9:$D$38=$I52)*($C$9:$C$38)),0) -> 0 | N52: 0 | O52: =Q52/(1+$D$51)*$D$51 -> 0 | Q52: =IF(J52, SUMPRODUCT(($D$9:$D$38=$I52)*($C$9:$C$38)*($G$9:$G$38))/SUMPRODUCT(($D$9:$D$38=$I52)*($C$9:$C$38)),0)+N52 -> 0 | R52: =Q52*J52 -> 0 | AD52: 25 | AE52: 2 | AF52: 2 | AG52: 1122 | AH52: 1123 | AI52: =IFERROR(IF(AD52, AH52/AG52, 0),0) -> 1.0008913 | AO52: =IFERROR(IF(AJ52, AN52/AM52, 0),0) -> 0 | AU52: =IFERROR(IF(AP52, AT52/AS52, 0),0) -> 0 | BA52: 0
B53: Total Rent Increase | F53: =Q55-L55 -> 52.225 | G53: =IF(F53, F53/$F$53, 0) -> 1 | I53: 2 | J53: =SUMPRODUCT(($D$9:$D$38=I53)*($C$9:$C$38)) -> 80 | K53: =IF(J53,SUMPRODUCT(($D$9:$D$38=$I53)*($C$9:$C$38)*($F$9:$F$38))/SUMPRODUCT(($D$9:$D$38=$I53)*($C$9:$C$38)),0) -> 1008 | L53: =IF(J53,SUMPRODUCT(($D$9:$D$38=$I53)*($C$9:$C$38)*($M$9:$M$38))/SUMPRODUCT(($D$9:$D$38=$I53)*($C$9:$C$38)),0) -> 775 | M53: =IF(J53,SUMPRODUCT(($D$9:$D$38=$I53)*($C$9:$C$38)*($G$9:$G$38))/SUMPRODUCT(($D$9:$D$38=$I53)*($C$9:$C$38)),0) -> 777.225 | N53: 50 | O53: =Q53/(1+$D$51)*$D$51 -> 0 | Q53: =IF(J53, SUMPRODUCT(($D$9:$D$38=$I53)*($C$9:$C$38)*($G$9:$G$38))/SUMPRODUCT(($D$9:$D$38=$I53)*($C$9:$C$38)),0)+N53 -> 827.225 | R53: =Q53*J53 -> 66178 | AD53: 25 | AE53: 2 | AF53: 2 | AG53: 1200 | AH53: 1211 | AI53: =IFERROR(IF(AD53, AH53/AG53, 0),0) -> 1.0091667 | AO53: =IFERROR(IF(AJ53, AN53/AM53, 0),0) -> 0 | AU53: =IFERROR(IF(AP53, AT53/AS53, 0),0) -> 0 | BA53: 0
I54: 3 | J54: =SUMPRODUCT(($D$9:$D$38=I54)*($C$9:$C$38)) -> 0 | K54: =IF(J54,SUMPRODUCT(($D$9:$D$38=$I54)*($C$9:$C$38)*($F$9:$F$38))/SUMPRODUCT(($D$9:$D$38=$I54)*($C$9:$C$38)),0) -> 0 | L54: =IF(J54,SUMPRODUCT(($D$9:$D$38=$I54)*($C$9:$C$38)*($M$9:$M$38))/SUMPRODUCT(($D$9:$D$38=$I54)*($C$9:$C$38)),0) -> 0 | M54: =IF(J54,SUMPRODUCT(($D$9:$D$38=$I54)*($C$9:$C$38)*($G$9:$G$38))/SUMPRODUCT(($D$9:$D$38=$I54)*($C$9:$C$38)),0) -> 0 | N54: 0 | O54: =Q54/(1+$D$51)*$D$51 -> 0 | Q54: =IF(J54, SUMPRODUCT(($D$9:$D$38=$I54)*($C$9:$C$38)*($G$9:$G$38))/SUMPRODUCT(($D$9:$D$38=$I54)*($C$9:$C$38)),0)+N54 -> 0 | R54: =Q54*J54 -> 0 | AD54: 25 | AE54: 2 | AF54: 2 | AG54: 1222 | AH54: 961 | AI54: =IFERROR(IF(AD54, AH54/AG54, 0),0) -> 0.78641571 | AO54: =IFERROR(IF(AJ54, AN54/AM54, 0),0) -> 0 | AU54: =IFERROR(IF(AP54, AT54/AS54, 0),0) -> 0 | BA54: 0
B55: [1] The increase due to unit upgrades broken down by unit type (in Unit Summary section), the increase due to renovations is a % of rent (this % will be multiplied by the % the renovations are complete to calculate for a particular unit), and the balance is management differences or an adjustment to "true" market. | I55: Total | J55: =SUM(J51:J54) -> 80 | K55: =F39 -> 1008 | L55: =M39 -> 775 | M55: =G39 -> 777.225 | N55: =SUM(N51:N54) -> 50 | O55: =SUM(O51:O54) -> 0 | Q55: =SUM(M55:O55) -> 827.225 | R55: =SUM(R51:R54) -> 66178 | AD55: 25 | AE55: 2 | AF55: 2 | AG55: 1347 | AH55: 940 | AI55: =IFERROR(IF(AD55, AH55/AG55, 0),0) -> 0.69784707 | AO55: =IFERROR(IF(AJ55, AN55/AM55, 0),0) -> 0 | AU55: =IFERROR(IF(AP55, AT55/AS55, 0),0) -> 0 | BA55: 0
R56: =R55/J55 -> 827.225 | AD56: 25 | AE56: 3 | AF56: 2 | AG56: 1464 | AH56: 1236 | AI56: =IFERROR(IF(AD56, AH56/AG56, 0),0) -> 0.8442623 | AO56: =IFERROR(IF(AJ56, AN56/AM56, 0),0) -> 0 | AU56: =IFERROR(IF(AP56, AT56/AS56, 0),0) -> 0 | BA56: 0
AI57: =IFERROR(IF(AD57, AH57/AG57, 0),0) -> 0 | AO57: =IFERROR(IF(AJ57, AN57/AM57, 0),0) -> 0 | AU57: =IFERROR(IF(AP57, AT57/AS57, 0),0) -> 0 | BA57: 0
AI58: =IFERROR(IF(AD58, AH58/AG58, 0),0) -> 0 | AO58: =IFERROR(IF(AJ58, AN58/AM58, 0),0) -> 0 | AU58: =IFERROR(IF(AP58, AT58/AS58, 0),0) -> 0 | BA58: 0
AI59: =IFERROR(IF(AD59, AH59/AG59, 0),0) -> 0 | AO59: =IFERROR(IF(AJ59, AN59/AM59, 0),0) -> 0 | AU59: =IFERROR(IF(AP59, AT59/AS59, 0),0) -> 0 | BA59: 0
AI60: =IFERROR(IF(AD60, AH60/AG60, 0),0) -> 0 | AO60: =IFERROR(IF(AJ60, AN60/AM60, 0),0) -> 0 | AU60: =IFERROR(IF(AP60, AT60/AS60, 0),0) -> 0 | BA60: 0
AI61: =IFERROR(IF(AD61, AH61/AG61, 0),0) -> 0 | AO61: =IFERROR(IF(AJ61, AN61/AM61, 0),0) -> 0 | AU61: =IFERROR(IF(AP61, AT61/AS61, 0),0) -> 0 | BA61: 0
B68: Rents Worksheet
B69: Property Name | C69: Count | D69: Beds | E69: Baths | F69: SF | G69: $ | H69: $/SF | I69: Fees | J69: All-in $ | K69: All-in $/SF | L69: W/D | M69: Rating | N69: Year | AI69: =IFERROR(IF(AD69, AH69/AG69, 0),0) -> 0 | AO69: =IFERROR(IF(AJ69, AN69/AM69, 0),0) -> 0 | AU69: =IFERROR(IF(AP69, AT69/AS69, 0),0) -> 0 | BA69: 0
B70: =$R$6 -> Johnathan's Ridge | C70: =IF('unit mix & comparables'!#ref!<>"",'unit mix & comparables'!#ref!,"") -> #VALUE! | D70: =IF('unit mix & comparables'!#ref!<>"",'unit mix & comparables'!#ref!,"") -> #VALUE! | E70: =IF('unit mix & comparables'!#ref!<>"",'unit mix & comparables'!#ref!,"") -> #VALUE! | F70: =IF('unit mix & comparables'!#ref!<>"",'unit mix & comparables'!#ref!,"") -> #VALUE! | G70: =IF('unit mix & comparables'!#ref!<>"",'unit mix & comparables'!#ref!,"") -> #VALUE! | H70: =IF('unit mix & comparables'!#ref!<>"",'unit mix & comparables'!#ref!,"") -> #VALUE! | I70: ='Unit Mix & Comparables'!$V$40 -> 0 | J70: =IFERROR(G70+I70,"") | K70: =IFERROR(J70/F70,"") | L70: =$R$43 -> 0 | M70: ='Unit Mix & Comparables'!$W$6 -> B | N70: =$R$7 -> 1982
B71: =$X$6 -> Riverside Manor | C71: =IF('unit mix & comparables'!#ref!<>"",'unit mix & comparables'!#ref!,"") -> #VALUE! | D71: =IF('unit mix & comparables'!#ref!<>"",'unit mix & comparables'!#ref!,"") -> #VALUE! | E71: =IF('unit mix & comparables'!#ref!<>"",'unit mix & comparables'!#ref!,"") -> #VALUE! | F71: =IF('unit mix & comparables'!#ref!<>"",'unit mix & comparables'!#ref!,"") -> #VALUE! | G71: =IF('unit mix & comparables'!#ref!<>"",'unit mix & comparables'!#ref!,"") -> #VALUE! | H71: =IF('unit mix & comparables'!#ref!<>"",'unit mix & comparables'!#ref!,"") -> #VALUE! | I71: ='Unit Mix & Comparables'!$AB$40 -> 0 | J71: =IFERROR(G71+I71,"") | K71: =IFERROR(J71/F71,"") | L71: =$AV$43 -> 0 | M71: ='Unit Mix & Comparables'!$W$6 -> B | N71: =$X$7 -> 1985
B72: =$AD$6 -> Windy Lakes | C72: =IF('unit mix & comparables'!#ref!<>"",'unit mix & comparables'!#ref!,"") -> #VALUE! | D72: =IF('unit mix & comparables'!#ref!<>"",'unit mix & comparables'!#ref!,"") -> #VALUE! | E72: =IF('unit mix & comparables'!#ref!<>"",'unit mix & comparables'!#ref!,"") -> #VALUE! | F72: =IF('unit mix & comparables'!#ref!<>"",'unit mix & comparables'!#ref!,"") -> #VALUE! | G72: =IF('unit mix & comparables'!#ref!<>"",'unit mix & comparables'!#ref!,"") -> #VALUE! | H72: =IF('unit mix & comparables'!#ref!<>"",'unit mix & comparables'!#ref!,"") -> #VALUE! | I72: ='Unit Mix & Comparables'!$AH$40 -> 0 | J72: =IFERROR(G72+I72,"") | K72: =IFERROR(J72/F72,"") | L72: =$AD$43 -> 0 | M72: ='Unit Mix & Comparables'!$AI$6 -> B | N72: =$AD$7 -> 1979
B73: =$AJ$6 -> Riverside South | C73: =IF('unit mix & comparables'!#ref!<>"",'unit mix & comparables'!#ref!,"") -> #VALUE! | D73: =IF('unit mix & comparables'!#ref!<>"",'unit mix & comparables'!#ref!,"") -> #VALUE! | E73: =IF('unit mix & comparables'!#ref!<>"",'unit mix & comparables'!#ref!,"") -> #VALUE! | F73: =IF('unit mix & comparables'!#ref!<>"",'unit mix & comparables'!#ref!,"") -> #VALUE! | G73: =IF('unit mix & comparables'!#ref!<>"",'unit mix & comparables'!#ref!,"") -> #VALUE! | H73: =IF('unit mix & comparables'!#ref!<>"",'unit mix & comparables'!#ref!,"") -> #VALUE! | I73: ='Unit Mix & Comparables'!$V$40 -> 0 | J73: =IFERROR(G73+I73,"") | K73: =IFERROR(J73/F73,"") | L73: =$AV$43 -> 0 | M73: ='Unit Mix & Comparables'!$AO$6 -> B | N73: =$AJ$7 -> 1988
B74: =$AP$6 -> Country View | C74: =IF('unit mix & comparables'!#ref!<>"",'unit mix & comparables'!#ref!,"") -> #VALUE! | D74: =IF('unit mix & comparables'!#ref!<>"",'unit mix & comparables'!#ref!,"") -> #VALUE! | E74: =IF('unit mix & comparables'!#ref!<>"",'unit mix & comparables'!#ref!,"") -> #VALUE! | F74: =IF('unit mix & comparables'!#ref!<>"",'unit mix & comparables'!#ref!,"") -> #VALUE! | G74: =IF('unit mix & comparables'!#ref!<>"",'unit mix & comparables'!#ref!,"") -> #VALUE! | H74: =IF('unit mix & comparables'!#ref!<>"",'unit mix & comparables'!#ref!,"") -> #VALUE! | I74: ='Unit Mix & Comparables'!$AT$40 -> 0 | J74: =IFERROR(G74+I74,"") | K74: =IFERROR(J74/F74,"") | L74: =$AP$43 -> 0 | M74: ='Unit Mix & Comparables'!$AU$6 -> B | N74: ='Unit Mix & Comparables'!$AP$7 -> 1993
B75: =$AV$6 -> Camellia Trace | C75: =IF('unit mix & comparables'!#ref!<>"",'unit mix & comparables'!#ref!,"") -> #VALUE! | D75: =IF('unit mix & comparables'!#ref!<>"",'unit mix & comparables'!#ref!,"") -> #VALUE! | E75: =IF('unit mix & comparables'!#ref!<>"",'unit mix & comparables'!#ref!,"") -> #VALUE! | F75: =IF('unit mix & comparables'!#ref!<>"",'unit mix & comparables'!#ref!,"") -> #VALUE! | G75: =IF('unit mix & comparables'!#ref!<>"",'unit mix & comparables'!#ref!,"") -> #VALUE! | H75: =IF('unit mix & comparables'!#ref!<>"",'unit mix & comparables'!#ref!,"") -> #VALUE! | I75: ='Unit Mix & Comparables'!$AZ$40 -> 0 | J75: =IFERROR(G75+I75,"") | K75: =IFERROR(J75/F75,"") | L75: =$AV$43 -> 0 | M75: ='Unit Mix & Comparables'!$BA$6 -> B | N75: ='Unit Mix & Comparables'!$AV$7 -> 2004
B76: =$BB$6 -> Bridgeway | C76: =IF('unit mix & comparables'!#ref!<>"",'unit mix & comparables'!#ref!,"") -> #VALUE! | D76: =IF('unit mix & comparables'!#ref!<>"",'unit mix & comparables'!#ref!,"") -> #VALUE! | E76: =IF('unit mix & comparables'!#ref!<>"",'unit mix & comparables'!#ref!,"") -> #VALUE! | F76: =IF('unit mix & comparables'!#ref!<>"",'unit mix & comparables'!#ref!,"") -> #VALUE! | G76: =IF('unit mix & comparables'!#ref!<>"",'unit mix & comparables'!#ref!,"") -> #VALUE! | H76: =IF('unit mix & comparables'!#ref!<>"",'unit mix & comparables'!#ref!,"") -> #VALUE! | I76: ='Unit Mix & Comparables'!$BF$40 -> 0 | J76: =IFERROR(G76+I76,"") | K76: =IFERROR(J76/F76,"") | L76: =$BB$43 -> 0 | M76: ='Unit Mix & Comparables'!$BG$6 -> 0 | N76: ='Unit Mix & Comparables'!$BB$7 -> 2012
B77: =CONCATENATE($I$6," Current") -> Riverhill TH Current | C77: =IF('unit mix & comparables'!#ref!<>"",'unit mix & comparables'!#ref!,"") -> #VALUE! | D77: =IF('unit mix & comparables'!#ref!<>"",'unit mix & comparables'!#ref!,"") -> #VALUE! | E77: =IF('unit mix & comparables'!#ref!<>"",'unit mix & comparables'!#ref!,"") -> #VALUE! | F77: =IF('unit mix & comparables'!#ref!<>"",'unit mix & comparables'!#ref!,"") -> #VALUE! | G77: =IF('unit mix & comparables'!#ref!<>"",'unit mix & comparables'!#ref!,"") -> #VALUE! | H77: =IF('unit mix & comparables'!#ref!<>"",'unit mix & comparables'!#ref!,"") -> #VALUE! | I77: ='Unit Mix & Comparables'!$M$40 -> 0 | J77: =IFERROR(G77+I77,"") | K77: =IFERROR(J77/F77,"") | L77: =$I$43 -> 0 | M77: ='Unit Mix & Comparables'!$H$6 -> B | N77: ='Unit Mix & Comparables'!$C$7 -> 1982
B78: =CONCATENATE($C$6," Pro Forma") -> Riverhill TH Pro Forma | C78: =IF('unit mix & comparables'!#ref!<>"",'unit mix & comparables'!#ref!,"") -> #VALUE! | D78: =IF('unit mix & comparables'!#ref!<>"",'unit mix & comparables'!#ref!,"") -> #VALUE! | E78: =IF('unit mix & comparables'!#ref!<>"",'unit mix & comparables'!#ref!,"") -> #VALUE! | F78: =IF('unit mix & comparables'!#ref!<>"",'unit mix & comparables'!#ref!,"") -> #VALUE! | G78: =IF('unit mix & comparables'!#ref!<>"",'unit mix & comparables'!#ref!,"") -> #VALUE! | H78: =IF('unit mix & comparables'!#ref!<>"",'unit mix & comparables'!#ref!,"") -> #VALUE! | I78: ='Unit Mix & Comparables'!$G$40 -> 0 | J78: =IFERROR(G78+I78,"") | K78: =IFERROR(J78/F78,"") | L78: =C4 -> 0 | M78: ='Unit Mix & Comparables'!$H$6 -> B | N78: ='Unit Mix & Comparables'!$C$7 -> 1982
B79: =$AP$6 -> Country View | C79: =IF('Unit Mix & Comparables'!$AP34<>"",'Unit Mix & Comparables'!$AP34,"") | D79: =IF('Unit Mix & Comparables'!$AQ$34<>"",'Unit Mix & Comparables'!$AQ$34,"") | E79: =IF('Unit Mix & Comparables'!$AR$34<>"",'Unit Mix & Comparables'!$AR$34,"") | F79: =IF('Unit Mix & Comparables'!$AS$34<>"",'Unit Mix & Comparables'!$AS$34,"") | G79: =IF('Unit Mix & Comparables'!$AT$34<>"",'Unit Mix & Comparables'!$AT$34,"") | H79: =IF('Unit Mix & Comparables'!$AU$34<>"",'Unit Mix & Comparables'!$AU$34,"") -> 0 | I79: ='Unit Mix & Comparables'!$AT$40 -> 0 | J79: =IFERROR(G79+I79,"") | K79: =IFERROR(J79/F79,"") | L79: =$AP$43 -> 0 | M79: ='Unit Mix & Comparables'!$AU$6 -> B | N79: ='Unit Mix & Comparables'!$AP$7 -> 1993
B80: =$AD$6 -> Windy Lakes | C80: =IF('Unit Mix & Comparables'!$AD15<>"",'Unit Mix & Comparables'!$AD15,"") | D80: =IF('Unit Mix & Comparables'!$AE15<>"",'Unit Mix & Comparables'!$AE15,"") | E80: =IF('Unit Mix & Comparables'!$AF15<>"",'Unit Mix & Comparables'!$AF15,"") | F80: =IF('Unit Mix & Comparables'!$AG15<>"",'Unit Mix & Comparables'!$AG15,"") | G80: =IF('Unit Mix & Comparables'!$AH15<>"",'Unit Mix & Comparables'!$AH15,"") | H80: =IF('Unit Mix & Comparables'!$AI15<>"",'Unit Mix & Comparables'!$AI15,"") -> 0 | I80: ='Unit Mix & Comparables'!$AH$40 -> 0 | J80: =IFERROR(G80+I80,"") | K80: =IFERROR(J80/F80,"") | L80: =$AD$43 -> 0 | M80: ='Unit Mix & Comparables'!$AI$6 -> B | N80: =$AD$7 -> 1979
B81: =$AP$6 -> Country View | C81: =IF('Unit Mix & Comparables'!$AP30<>"",'Unit Mix & Comparables'!$AP30,"") | D81: =IF('Unit Mix & Comparables'!$AQ$30<>"",'Unit Mix & Comparables'!$AQ$30,"") | E81: =IF('Unit Mix & Comparables'!$AR$30<>"",'Unit Mix & Comparables'!$AR$30,"") | F81: =IF('Unit Mix & Comparables'!$AS$30<>"",'Unit Mix & Comparables'!$AS$30,"") | G81: =IF('Unit Mix & Comparables'!$AT$30<>"",'Unit Mix & Comparables'!$AT$30,"") | H81: =IF('Unit Mix & Comparables'!$AU$30<>"",'Unit Mix & Comparables'!$AU$30,"") -> 0 | I81: ='Unit Mix & Comparables'!$AT$40 -> 0 | J81: =IFERROR(G81+I81,"") | K81: =IFERROR(J81/F81,"") | L81: =$AP$43 -> 0 | M81: ='Unit Mix & Comparables'!$AU$6 -> B | N81: ='Unit Mix & Comparables'!$AP$7 -> 1993
B82: =$AP$6 -> Country View | C82: =IF('Unit Mix & Comparables'!$AP37<>"",'Unit Mix & Comparables'!$AP37,"") | D82: =IF('Unit Mix & Comparables'!$AQ$37<>"",'Unit Mix & Comparables'!$AQ$37,"") | E82: =IF('Unit Mix & Comparables'!$AR$37<>"",'Unit Mix & Comparables'!$AR$37,"") | F82: =IF('Unit Mix & Comparables'!$AS$37<>"",'Unit Mix & Comparables'!$AS$37,"") | G82: =IF('Unit Mix & Comparables'!$AT$37<>"",'Unit Mix & Comparables'!$AT$37,"") | H82: =IF('Unit Mix & Comparables'!$AU$37<>"",'Unit Mix & Comparables'!$AU$37,"") -> 0 | I82: ='Unit Mix & Comparables'!$AT$40 -> 0 | J82: =IFERROR(G82+I82,"") | K82: =IFERROR(J82/F82,"") | L82: =$AP$43 -> 0 | M82: ='Unit Mix & Comparables'!$AU$6 -> B | N82: ='Unit Mix & Comparables'!$AP$7 -> 1993
B83: =$AP$6 -> Country View | C83: =IF('Unit Mix & Comparables'!$AP36<>"",'Unit Mix & Comparables'!$AP36,"") | D83: =IF('Unit Mix & Comparables'!$AQ$36<>"",'Unit Mix & Comparables'!$AQ$36,"") | E83: =IF('Unit Mix & Comparables'!$AR$36<>"",'Unit Mix & Comparables'!$AR$36,"") | F83: =IF('Unit Mix & Comparables'!$AS$36<>"",'Unit Mix & Comparables'!$AS$36,"") | G83: =IF('Unit Mix & Comparables'!$AT$36<>"",'Unit Mix & Comparables'!$AT$36,"") | H83: =IF('Unit Mix & Comparables'!$AU$36<>"",'Unit Mix & Comparables'!$AU$36,"") -> 0 | I83: ='Unit Mix & Comparables'!$AT$40 -> 0 | J83: =IFERROR(G83+I83,"") | K83: =IFERROR(J83/F83,"") | L83: =$AP$43 -> 0 | M83: ='Unit Mix & Comparables'!$AU$6 -> B | N83: ='Unit Mix & Comparables'!$AP$7 -> 1993
B84: =$AV$6 -> Camellia Trace | C84: =IF('Unit Mix & Comparables'!$AV15<>"",'Unit Mix & Comparables'!$AV15,"") | D84: =IF('Unit Mix & Comparables'!$AW$15<>"",'Unit Mix & Comparables'!$AW$15,"") | E84: =IF('Unit Mix & Comparables'!$AX$15<>"",'Unit Mix & Comparables'!$AX$15,"") | F84: =IF('Unit Mix & Comparables'!$AY$15<>"",'Unit Mix & Comparables'!$AY$15,"") | G84: =IF('Unit Mix & Comparables'!$AZ$15<>"",'Unit Mix & Comparables'!$AZ$15,"") | H84: =IF('Unit Mix & Comparables'!$BA$15<>"",'Unit Mix & Comparables'!$BA$15,"") -> 0 | I84: ='Unit Mix & Comparables'!$AZ$40 -> 0 | J84: =IFERROR(G84+I84,"") | K84: =IFERROR(J84/F84,"") | L84: =$AV$43 -> 0 | M84: ='Unit Mix & Comparables'!$BA$6 -> B | N84: ='Unit Mix & Comparables'!$AV$7 -> 2004 | AD84: =SUM(AD51:AD69) -> 150 | AG84: =IFERROR(SUMPRODUCT(AD51:AD69, AG51:AG69)/AD84,0) -> 1213 | AH84: =IFERROR(SUMPRODUCT(AD51:AD69, AH51:AH69)/AD84,0) -> 1057.3333 | AI84: =IFERROR(IF(AD84, AH84/AG84, 0),0) -> 0.87166804 | AJ84: =SUM(AJ51:AJ69) -> 0 | AM84: =IFERROR(SUMPRODUCT(AJ51:AJ69, AM51:AM69)/AJ84,0) -> 0 | AN84: =IFERROR(SUMPRODUCT(AJ51:AJ69, AN51:AN69)/AJ84,0) -> 0 | AO84: =IFERROR(IF(AJ84, AN84/AM84, 0),0) -> 0 | AP84: =SUM(AP51:AP69) -> 0 | AS84: =IFERROR(SUMPRODUCT(AP51:AP69, AS51:AS69)/AP84,0) -> 0 | AT84: =IFERROR(SUMPRODUCT(AP51:AP69, AT51:AT69)/AP84,0) -> 0 | AU84: =IFERROR(IF(AP84, AT84/AS84, 0),0) -> 0 | AV84: =SUM(AV51:AV69) -> 0 | AY84: =IFERROR(SUMPRODUCT(AV51:AV69, AY51:AY69)/AV84,0) -> 0 | AZ84: =IFERROR(SUMPRODUCT(AV51:AV69, AZ51:AZ69)/AV84,0) -> 0 | BA84: =IFERROR(IF(AV84, AZ84/AY84, 0),0) -> 0
B85: =$AP$6 -> Country View | C85: =IF('Unit Mix & Comparables'!$AP35<>"",'Unit Mix & Comparables'!$AP35,"") | D85: =IF('Unit Mix & Comparables'!$AQ$35<>"",'Unit Mix & Comparables'!$AQ$35,"") | E85: =IF('Unit Mix & Comparables'!$AR$35<>"",'Unit Mix & Comparables'!$AR$35,"") | F85: =IF('Unit Mix & Comparables'!$AS$35<>"",'Unit Mix & Comparables'!$AS$35,"") | G85: =IF('Unit Mix & Comparables'!$AT$35<>"",'Unit Mix & Comparables'!$AT$35,"") | H85: =IF('Unit Mix & Comparables'!$AU$35<>"",'Unit Mix & Comparables'!$AU$35,"") -> 0 | I85: ='Unit Mix & Comparables'!$AT$40 -> 0 | J85: =IFERROR(G85+I85,"") | K85: =IFERROR(J85/F85,"") | L85: =$AP$43 -> 0 | M85: ='Unit Mix & Comparables'!$AU$6 -> B | N85: ='Unit Mix & Comparables'!$AP$7 -> 1993
B86: =AV48 -> 0 | C86: =IF('Unit Mix & Comparables'!$AV53<>"",'Unit Mix & Comparables'!$AV53,"") | D86: =IF('Unit Mix & Comparables'!$AW$53<>"",'Unit Mix & Comparables'!$AW$53,"") | E86: =IF('Unit Mix & Comparables'!$AX$53<>"",'Unit Mix & Comparables'!$AX$53,"") | F86: =IF('Unit Mix & Comparables'!$AY$53<>"",'Unit Mix & Comparables'!$AY$53,"") | G86: =IF('Unit Mix & Comparables'!$AZ$53<>"",'Unit Mix & Comparables'!$AZ$53,"") | H86: =IF('Unit Mix & Comparables'!$BA$53<>"",'Unit Mix & Comparables'!$BA$53,"") -> 0 | I86: ='Unit Mix & Comparables'!$AT$40 -> 0 | J86: =IFERROR(G86+I86,"") | K86: =IFERROR(J86/F86,"") | L86: =$AV$86 -> 0 | M86: ='Unit Mix & Comparables'!$BA$48 -> A | N86: ='Unit Mix & Comparables'!$AV$49 -> 0
B87: =$AP$6 -> Country View | C87: =IF('Unit Mix & Comparables'!$AP33<>"",'Unit Mix & Comparables'!$AP33,"") | D87: =IF('Unit Mix & Comparables'!$AQ$33<>"",'Unit Mix & Comparables'!$AQ$33,"") | E87: =IF('Unit Mix & Comparables'!$AR$33<>"",'Unit Mix & Comparables'!$AR$33,"") | F87: =IF('Unit Mix & Comparables'!$AS$33<>"",'Unit Mix & Comparables'!$AS$33,"") | G87: =IF('Unit Mix & Comparables'!$AT$33<>"",'Unit Mix & Comparables'!$AT$33,"") | H87: =IF('Unit Mix & Comparables'!$AU$33<>"",'Unit Mix & Comparables'!$AU$33,"") -> 0 | I87: ='Unit Mix & Comparables'!$AT$40 -> 0 | J87: =IFERROR(G87+I87,"") | K87: =IFERROR(J87/F87,"") | L87: =$AP$43 -> 0 | M87: ='Unit Mix & Comparables'!$AU$6 -> B | N87: ='Unit Mix & Comparables'!$AP$7 -> 1993
B88: =$AP$6 -> Country View | C88: =IF('Unit Mix & Comparables'!$AP27<>"",'Unit Mix & Comparables'!$AP27,"") | D88: =IF('Unit Mix & Comparables'!$AQ$27<>"",'Unit Mix & Comparables'!$AQ$27,"") | E88: =IF('Unit Mix & Comparables'!$AR$27<>"",'Unit Mix & Comparables'!$AR$27,"") | F88: =IF('Unit Mix & Comparables'!$AS$27<>"",'Unit Mix & Comparables'!$AS$27,"") | G88: =IF('Unit Mix & Comparables'!$AT$27<>"",'Unit Mix & Comparables'!$AT$27,"") | H88: =IF('Unit Mix & Comparables'!$AU$27<>"",'Unit Mix & Comparables'!$AU$27,"") -> 0 | I88: ='Unit Mix & Comparables'!$AT$40 -> 0 | J88: =IFERROR(G88+I88,"") | K88: =IFERROR(J88/F88,"") | L88: =$AP$43 -> 0 | M88: ='Unit Mix & Comparables'!$AU$6 -> B | N88: ='Unit Mix & Comparables'!$AP$7 -> 1993
B89: =AP48 -> 0 | C89: =IF('Unit Mix & Comparables'!$AP53<>"",'Unit Mix & Comparables'!$AP53,"") | D89: =IF('Unit Mix & Comparables'!$AQ$53<>"",'Unit Mix & Comparables'!$AQ$53,"") | E89: =IF('Unit Mix & Comparables'!$AR$53<>"",'Unit Mix & Comparables'!$AR$53,"") | F89: =IF('Unit Mix & Comparables'!$AS$53<>"",'Unit Mix & Comparables'!$AS$53,"") | G89: =IF('Unit Mix & Comparables'!$AT$53<>"",'Unit Mix & Comparables'!$AT$53,"") | H89: =IF('Unit Mix & Comparables'!$AU$53<>"",'Unit Mix & Comparables'!$AU$53,"") -> 0 | I89: ='Unit Mix & Comparables'!$AT$40 -> 0 | J89: =IFERROR(G89+I89,"") | K89: =IFERROR(J89/F89,"") | L89: =$AP$86 -> 0 | M89: ='Unit Mix & Comparables'!$AU$48 -> B | N89: ='Unit Mix & Comparables'!$AP$49 -> 0
B90: =AD58 -> 0 | C90: =IF('Unit Mix & Comparables'!$AD53<>"",'Unit Mix & Comparables'!$AD53,"") -> 25 | D90: =IF('Unit Mix & Comparables'!$AE$53<>"",'Unit Mix & Comparables'!$AE$53,"") -> 2 | E90: =IF('Unit Mix & Comparables'!$AF$53<>"",'Unit Mix & Comparables'!$AF$53,"") -> 2 | F90: =IF('Unit Mix & Comparables'!$AG$53<>"",'Unit Mix & Comparables'!$AG$53,"") -> 1200 | G90: =IF('Unit Mix & Comparables'!$AH$53<>"",'Unit Mix & Comparables'!$AH$53,"") -> 1211 | H90: =IF('Unit Mix & Comparables'!$AI$53<>"",'Unit Mix & Comparables'!$AI$53,"") -> 1.0091667 | I90: ='Unit Mix & Comparables'!$AT$40 -> 0 | J90: =IFERROR(G90+I90,"") -> 1211 | K90: =IFERROR(J90/F90,"") -> 1.0091667 | L90: =$AD$86 -> 0 | M90: ='Unit Mix & Comparables'!$AI$48 -> B | N90: ='Unit Mix & Comparables'!$AD$49 -> 2008
B91: =$AD$6 -> Windy Lakes | C91: =IF('Unit Mix & Comparables'!$AD14<>"",'Unit Mix & Comparables'!$AD14,"") | D91: =IF('Unit Mix & Comparables'!$AE14<>"",'Unit Mix & Comparables'!$AE14,"") | E91: =IF('Unit Mix & Comparables'!$AF14<>"",'Unit Mix & Comparables'!$AF14,"") | F91: =IF('Unit Mix & Comparables'!$AG14<>"",'Unit Mix & Comparables'!$AG14,"") | G91: =IF('Unit Mix & Comparables'!$AH14<>"",'Unit Mix & Comparables'!$AH14,"") | H91: =IF('Unit Mix & Comparables'!$AI14<>"",'Unit Mix & Comparables'!$AI14,"") -> 0 | I91: ='Unit Mix & Comparables'!$AH$40 -> 0 | J91: =IFERROR(G91+I91,"") | K91: =IFERROR(J91/F91,"") | L91: =$AD$43 -> 0 | M91: ='Unit Mix & Comparables'!$AI$6 -> B | N91: =$AD$7 -> 1979
B92: =$AV$6 -> Camellia Trace | C92: =IF('Unit Mix & Comparables'!$AV14<>"",'Unit Mix & Comparables'!$AV14,"") -> 25 | D92: =IF('Unit Mix & Comparables'!$AW$14<>"",'Unit Mix & Comparables'!$AW$14,"") -> 3 | E92: =IF('Unit Mix & Comparables'!$AX$14<>"",'Unit Mix & Comparables'!$AX$14,"") -> 2 | F92: =IF('Unit Mix & Comparables'!$AY$14<>"",'Unit Mix & Comparables'!$AY$14,"") -> 1414 | G92: =IF('Unit Mix & Comparables'!$AZ$14<>"",'Unit Mix & Comparables'!$AZ$14,"") -> 1206 | H92: =IF('Unit Mix & Comparables'!$BA$14<>"",'Unit Mix & Comparables'!$BA$14,"") -> 0.85289958 | I92: ='Unit Mix & Comparables'!$AZ$40 -> 0 | J92: =IFERROR(G92+I92,"") -> 1206 | K92: =IFERROR(J92/F92,"") -> 0.85289958 | L92: =$AV$43 -> 0 | M92: ='Unit Mix & Comparables'!$BA$6 -> B | N92: ='Unit Mix & Comparables'!$AV$7 -> 2004
B93: =$R$6 -> Johnathan's Ridge | C93: =IF('Unit Mix & Comparables'!$R13<>"",'Unit Mix & Comparables'!$R13,"") | D93: =IF('Unit Mix & Comparables'!$S13<>"",'Unit Mix & Comparables'!$S13,"") | E93: =IF('Unit Mix & Comparables'!$T13<>"",'Unit Mix & Comparables'!$T13,"") | F93: =IF('Unit Mix & Comparables'!$U13<>"",'Unit Mix & Comparables'!$U13,"") | G93: =IF('Unit Mix & Comparables'!$V13<>"",'Unit Mix & Comparables'!$V13,"") | H93: =IF('Unit Mix & Comparables'!$W13<>"",'Unit Mix & Comparables'!$W13,"") -> 0 | I93: ='Unit Mix & Comparables'!$V$40 -> 0 | J93: =IFERROR(G93+I93,"") | K93: =IFERROR(J93/F93,"") | L93: =$R$43 -> 0 | M93: ='Unit Mix & Comparables'!$W$6 -> B | N93: =$R$7 -> 1982
B94: =$AP$6 -> Country View | C94: =IF('Unit Mix & Comparables'!$AP23<>"",'Unit Mix & Comparables'!$AP23,"") | D94: =IF('Unit Mix & Comparables'!$AQ$23<>"",'Unit Mix & Comparables'!$AQ$23,"") | E94: =IF('Unit Mix & Comparables'!$AR$23<>"",'Unit Mix & Comparables'!$AR$23,"") | F94: =IF('Unit Mix & Comparables'!$AS$23<>"",'Unit Mix & Comparables'!$AS$23,"") | G94: =IF('Unit Mix & Comparables'!$AT$23<>"",'Unit Mix & Comparables'!$AT$23,"") | H94: =IF('Unit Mix & Comparables'!$AU$23<>"",'Unit Mix & Comparables'!$AU$23,"") -> 0 | I94: ='Unit Mix & Comparables'!$AT$40 -> 0 | J94: =IFERROR(G94+I94,"") | K94: =IFERROR(J94/F94,"") | L94: =$AP$43 -> 0 | M94: ='Unit Mix & Comparables'!$AU$6 -> B | N94: ='Unit Mix & Comparables'!$AP$7 -> 1993
B95: =$X$6 -> Riverside Manor | C95: =IF('Unit Mix & Comparables'!$X11<>"",'Unit Mix & Comparables'!$X11,"") -> 25 | D95: =IF('Unit Mix & Comparables'!$Y11<>"",'Unit Mix & Comparables'!$Y11,"") -> 1 | E95: =IF('Unit Mix & Comparables'!$Z11<>"",'Unit Mix & Comparables'!$Z11,"") -> 1 | F95: =IF('Unit Mix & Comparables'!$AA11<>"",'Unit Mix & Comparables'!$AA11,"") -> 640 | G95: =IF('Unit Mix & Comparables'!$AB11<>"",'Unit Mix & Comparables'!$AB11,"") -> 390 | H95: =IF('Unit Mix & Comparables'!$AC11<>"",'Unit Mix & Comparables'!$AC11,"") -> 0.609375 | I95: ='Unit Mix & Comparables'!$AB$40 -> 0 | J95: =IFERROR(G95+I95,"") -> 390 | K95: =IFERROR(J95/F95,"") -> 0.609375 | L95: =X68 -> 0 | M95: ='Unit Mix & Comparables'!$W$6 -> B | N95: =$X$7 -> 1985
B96: =CONCATENATE($C$6," Pro Forma") -> Riverhill TH Pro Forma | C96: =IF('Unit Mix & Comparables'!$C$38<>"",'Unit Mix & Comparables'!$C$38,"") | D96: =IF('Unit Mix & Comparables'!$D$38<>"",'Unit Mix & Comparables'!$D$38,"") | E96: =IF('Unit Mix & Comparables'!$E$38<>"",'Unit Mix & Comparables'!$E$38,"") | F96: =IF('Unit Mix & Comparables'!$F$38<>"",'Unit Mix & Comparables'!$F$38,"") | G96: =IF('Unit Mix & Comparables'!$G$38<>"",'Unit Mix & Comparables'!$G$38,"") | H96: =IF('Unit Mix & Comparables'!$H$38<>"",'Unit Mix & Comparables'!$H$38,"") -> 0 | I96: ='Unit Mix & Comparables'!$G$40 -> 0 | J96: =IFERROR(G96+I96,"") | K96: =IFERROR(J96/F96,"") | L96: =C43 -> 0 | M96: ='Unit Mix & Comparables'!$H$6 -> B | N96: ='Unit Mix & Comparables'!$C$7 -> 1982
B97: =CONCATENATE($C$6," Pro Forma") -> Riverhill TH Pro Forma | C97: =IF('Unit Mix & Comparables'!$C$37<>"",'Unit Mix & Comparables'!$C$37,"") | D97: =IF('Unit Mix & Comparables'!$D$37<>"",'Unit Mix & Comparables'!$D$37,"") | E97: =IF('Unit Mix & Comparables'!$E$37<>"",'Unit Mix & Comparables'!$E$37,"") | F97: =IF('Unit Mix & Comparables'!$F$37<>"",'Unit Mix & Comparables'!$F$37,"") | G97: =IF('Unit Mix & Comparables'!$G$37<>"",'Unit Mix & Comparables'!$G$37,"") | H97: =IF('Unit Mix & Comparables'!$H$37<>"",'Unit Mix & Comparables'!$H$37,"") -> 0 | I97: ='Unit Mix & Comparables'!$G$40 -> 0 | J97: =IFERROR(G97+I97,"") | K97: =IFERROR(J97/F97,"") | L97: =C43 -> 0 | M97: ='Unit Mix & Comparables'!$H$6 -> B | N97: ='Unit Mix & Comparables'!$C$7 -> 1982
B98: =CONCATENATE($I$6," Current") -> Riverhill TH Current | C98: =IF('Unit Mix & Comparables'!$I$38<>"",'Unit Mix & Comparables'!$I$38,"") | D98: =IF('Unit Mix & Comparables'!$J$38<>"",'Unit Mix & Comparables'!$J$38,"") | E98: =IF('Unit Mix & Comparables'!$K$38<>"",'Unit Mix & Comparables'!$K$38,"") | F98: =IF('Unit Mix & Comparables'!$L$38<>"",'Unit Mix & Comparables'!$L$38,"") | G98: =IF('Unit Mix & Comparables'!$M$38<>"",'Unit Mix & Comparables'!$M$38,"") | H98: =IF('Unit Mix & Comparables'!$N$38<>"",'Unit Mix & Comparables'!$N$38,"") -> 0 | I98: ='Unit Mix & Comparables'!$M$40 -> 0 | J98: =IFERROR(G98+I98,"") | K98: =IFERROR(J98/F98,"") | L98: =$I$43 -> 0 | M98: ='Unit Mix & Comparables'!$H$6 -> B | N98: ='Unit Mix & Comparables'!$C$7 -> 1982
B99: =$AP$6 -> Country View | C99: =IF('Unit Mix & Comparables'!$AP32<>"",'Unit Mix & Comparables'!$AP32,"") | D99: =IF('Unit Mix & Comparables'!$AQ$32<>"",'Unit Mix & Comparables'!$AQ$32,"") | E99: =IF('Unit Mix & Comparables'!$AR$32<>"",'Unit Mix & Comparables'!$AR$32,"") | F99: =IF('Unit Mix & Comparables'!$AS$32<>"",'Unit Mix & Comparables'!$AS$32,"") | G99: =IF('Unit Mix & Comparables'!$AT$32<>"",'Unit Mix & Comparables'!$AT$32,"") | H99: =IF('Unit Mix & Comparables'!$AU$32<>"",'Unit Mix & Comparables'!$AU$32,"") -> 0 | I99: ='Unit Mix & Comparables'!$AT$40 -> 0 | J99: =IFERROR(G99+I99,"") | K99: =IFERROR(J99/F99,"") | L99: =$AP$43 -> 0 | M99: ='Unit Mix & Comparables'!$AU$6 -> B | N99: ='Unit Mix & Comparables'!$AP$7 -> 1993
B100: =$BB$6 -> Bridgeway | C100: =IF('Unit Mix & Comparables'!$BB11<>"",'Unit Mix & Comparables'!$BB11,"") | D100: =IF('Unit Mix & Comparables'!$BC$11<>"",'Unit Mix & Comparables'!$BC$11,"") | E100: =IF('Unit Mix & Comparables'!$BD$11<>"",'Unit Mix & Comparables'!$BD$11,"") | F100: =IF('Unit Mix & Comparables'!$BE$11<>"",'Unit Mix & Comparables'!$BE$11,"") | G100: =IF('Unit Mix & Comparables'!$BF$11<>"",'Unit Mix & Comparables'!$BF$11,"") | H100: =IF('Unit Mix & Comparables'!$BG$11<>"",'Unit Mix & Comparables'!$BG$11,"") -> 0 | I100: ='Unit Mix & Comparables'!$BF$40 -> 0 | J100: =IFERROR(G100+I100,"") | K100: =IFERROR(J100/F100,"") | L100: =$BB$43 -> 0 | M100: ='Unit Mix & Comparables'!$BG$6 -> 0 | N100: ='Unit Mix & Comparables'!$BB$7 -> 2012
B101: =AV28 -> 0 | C101: =IF('Unit Mix & Comparables'!$AV52<>"",'Unit Mix & Comparables'!$AV52,"") | D101: =IF('Unit Mix & Comparables'!$AW$52<>"",'Unit Mix & Comparables'!$AW$52,"") | E101: =IF('Unit Mix & Comparables'!$AX$52<>"",'Unit Mix & Comparables'!$AX$52,"") | F101: =IF('Unit Mix & Comparables'!$AY$52<>"",'Unit Mix & Comparables'!$AY$52,"") | G101: =IF('Unit Mix & Comparables'!$AZ$52<>"",'Unit Mix & Comparables'!$AZ$52,"") | H101: =IF('Unit Mix & Comparables'!$BA$52<>"",'Unit Mix & Comparables'!$BA$52,"") -> 0 | I101: ='Unit Mix & Comparables'!$AT$40 -> 0 | J101: =IFERROR(G101+I101,"") | K101: =IFERROR(J101/F101,"") | L101: =$AV$86 -> 0 | M101: ='Unit Mix & Comparables'!$BA$48 -> A | N101: ='Unit Mix & Comparables'!$AV$49 -> 0
B102: =$AV$6 -> Camellia Trace | C102: =IF('Unit Mix & Comparables'!$AV13<>"",'Unit Mix & Comparables'!$AV13,"") -> 25 | D102: =IF('Unit Mix & Comparables'!$AW$13<>"",'Unit Mix & Comparables'!$AW$13,"") -> 2 | E102: =IF('Unit Mix & Comparables'!$AX$13<>"",'Unit Mix & Comparables'!$AX$13,"") -> 2 | F102: =IF('Unit Mix & Comparables'!$AY$13<>"",'Unit Mix & Comparables'!$AY$13,"") -> 1208 | G102: =IF('Unit Mix & Comparables'!$AZ$13<>"",'Unit Mix & Comparables'!$AZ$13,"") -> 996 | H102: =IF('Unit Mix & Comparables'!$BA$13<>"",'Unit Mix & Comparables'!$BA$13,"") -> 0.82450331 | I102: ='Unit Mix & Comparables'!$AZ$40 -> 0 | J102: =IFERROR(G102+I102,"") -> 996 | K102: =IFERROR(J102/F102,"") -> 0.82450331 | L102: =$AV$43 -> 0 | M102: ='Unit Mix & Comparables'!$BA$6 -> B | N102: ='Unit Mix & Comparables'!$AV$7 -> 2004
B103: =$AV$6 -> Camellia Trace | C103: =IF('Unit Mix & Comparables'!$AV11<>"",'Unit Mix & Comparables'!$AV11,"") -> 25 | D103: =IF('Unit Mix & Comparables'!$AW$12<>"",'Unit Mix & Comparables'!$AW$12,"") -> 2 | E103: =IF('Unit Mix & Comparables'!$AX$12<>"",'Unit Mix & Comparables'!$AX$12,"") -> 2 | F103: =IF('Unit Mix & Comparables'!$AY$12<>"",'Unit Mix & Comparables'!$AY$12,"") -> 1197 | G103: =IF('Unit Mix & Comparables'!$AZ$12<>"",'Unit Mix & Comparables'!$AZ$12,"") -> 946 | H103: =IF('Unit Mix & Comparables'!$BA$12<>"",'Unit Mix & Comparables'!$BA$12,"") -> 0.79030911 | I103: ='Unit Mix & Comparables'!$AZ$40 -> 0 | J103: =IFERROR(G103+I103,"") -> 946 | K103: =IFERROR(J103/F103,"") -> 0.79030911 | L103: =$AV$43 -> 0 | M103: ='Unit Mix & Comparables'!$BA$6 -> B | N103: ='Unit Mix & Comparables'!$AV$7 -> 2004
B104: =$X$6 -> Riverside Manor | C104: =IF('Unit Mix & Comparables'!$X12<>"",'Unit Mix & Comparables'!$X12,"") -> 25 | D104: =IF('Unit Mix & Comparables'!$Y12<>"",'Unit Mix & Comparables'!$Y12,"") -> 2 | E104: =IF('Unit Mix & Comparables'!$Z12<>"",'Unit Mix & Comparables'!$Z12,"") -> 1 | F104: =IF('Unit Mix & Comparables'!$AA12<>"",'Unit Mix & Comparables'!$AA12,"") -> 680 | G104: =IF('Unit Mix & Comparables'!$AB12<>"",'Unit Mix & Comparables'!$AB12,"") -> 400 | H104: =IF('Unit Mix & Comparables'!$AC12<>"",'Unit Mix & Comparables'!$AC12,"") -> 0.58823529 | I104: ='Unit Mix & Comparables'!$AB$40 -> 0 | J104: =IFERROR(G104+I104,"") -> 400 | K104: =IFERROR(J104/F104,"") -> 0.58823529 | L104: =$AV$43 -> 0 | M104: ='Unit Mix & Comparables'!$W$6 -> B | N104: =$X$7 -> 1985
B105: =CONCATENATE($I$6," Current") -> Riverhill TH Current | C105: =IF('Unit Mix & Comparables'!$I$37<>"",'Unit Mix & Comparables'!$I$37,"") | D105: =IF('Unit Mix & Comparables'!$J$37<>"",'Unit Mix & Comparables'!$J$37,"") | E105: =IF('Unit Mix & Comparables'!$K$37<>"",'Unit Mix & Comparables'!$K$37,"") | F105: =IF('Unit Mix & Comparables'!$L$37<>"",'Unit Mix & Comparables'!$L$37,"") | G105: =IF('Unit Mix & Comparables'!$M$37<>"",'Unit Mix & Comparables'!$M$37,"") | H105: =IF('Unit Mix & Comparables'!$N$37<>"",'Unit Mix & Comparables'!$N$37,"") -> 0 | I105: ='Unit Mix & Comparables'!$M$40 -> 0 | J105: =IFERROR(G105+I105,"") | K105: =IFERROR(J105/F105,"") | L105: =$I$43 -> 0 | M105: ='Unit Mix & Comparables'!$H$6 -> B | N105: ='Unit Mix & Comparables'!$C$7 -> 1982
B106: =$AD$6 -> Windy Lakes | C106: =IF('Unit Mix & Comparables'!$AD13<>"",'Unit Mix & Comparables'!$AD13,"") | D106: =IF('Unit Mix & Comparables'!$AE13<>"",'Unit Mix & Comparables'!$AE13,"") | E106: =IF('Unit Mix & Comparables'!$AF13<>"",'Unit Mix & Comparables'!$AF13,"") | F106: =IF('Unit Mix & Comparables'!$AG13<>"",'Unit Mix & Comparables'!$AG13,"") | G106: =IF('Unit Mix & Comparables'!$AH13<>"",'Unit Mix & Comparables'!$AH13,"") | H106: =IF('Unit Mix & Comparables'!$AI13<>"",'Unit Mix & Comparables'!$AI13,"") -> 0 | I106: ='Unit Mix & Comparables'!$AH$40 -> 0 | J106: =IFERROR(G106+I106,"") | K106: =IFERROR(J106/F106,"") | L106: =$AD$43 -> 0 | M106: ='Unit Mix & Comparables'!$AI$6 -> B | N106: =$AD$7 -> 1979
B107: =$AP$6 -> Country View | C107: =IF('Unit Mix & Comparables'!$AP29<>"",'Unit Mix & Comparables'!$AP29,"") | D107: =IF('Unit Mix & Comparables'!$AQ$29<>"",'Unit Mix & Comparables'!$AQ$29,"") | E107: =IF('Unit Mix & Comparables'!$AR$29<>"",'Unit Mix & Comparables'!$AR$29,"") | F107: =IF('Unit Mix & Comparables'!$AS$29<>"",'Unit Mix & Comparables'!$AS$29,"") | G107: =IF('Unit Mix & Comparables'!$AT$29<>"",'Unit Mix & Comparables'!$AT$29,"") | H107: =IF('Unit Mix & Comparables'!$AU$29<>"",'Unit Mix & Comparables'!$AU$29,"") -> 0 | I107: ='Unit Mix & Comparables'!$AT$40 -> 0 | J107: =IFERROR(G107+I107,"") | K107: =IFERROR(J107/F107,"") | L107: =$AP$43 -> 0 | M107: ='Unit Mix & Comparables'!$AU$6 -> B | N107: ='Unit Mix & Comparables'!$AP$7 -> 1993
B108: =$AP$6 -> Country View | C108: =IF('Unit Mix & Comparables'!$AP26<>"",'Unit Mix & Comparables'!$AP26,"") | D108: =IF('Unit Mix & Comparables'!$AQ$26<>"",'Unit Mix & Comparables'!$AQ$26,"") | E108: =IF('Unit Mix & Comparables'!$AR$26<>"",'Unit Mix & Comparables'!$AR$26,"") | F108: =IF('Unit Mix & Comparables'!$AS$26<>"",'Unit Mix & Comparables'!$AS$26,"") | G108: =IF('Unit Mix & Comparables'!$AT$26<>"",'Unit Mix & Comparables'!$AT$26,"") | H108: =IF('Unit Mix & Comparables'!$AU$26<>"",'Unit Mix & Comparables'!$AU$26,"") -> 0 | I108: ='Unit Mix & Comparables'!$AT$40 -> 0 | J108: =IFERROR(G108+I108,"") | K108: =IFERROR(J108/F108,"") | L108: =$AP$43 -> 0 | M108: ='Unit Mix & Comparables'!$AU$6 -> B | N108: ='Unit Mix & Comparables'!$AP$7 -> 1993
B109: =$AV$6 -> Camellia Trace | C109: =IF('Unit Mix & Comparables'!$AV17<>"",'Unit Mix & Comparables'!$AV17,"") | D109: =IF('Unit Mix & Comparables'!$AW$17<>"",'Unit Mix & Comparables'!$AW$17,"") | E109: =IF('Unit Mix & Comparables'!$AX$17<>"",'Unit Mix & Comparables'!$AX$17,"") | F109: =IF('Unit Mix & Comparables'!$AY$17<>"",'Unit Mix & Comparables'!$AY$17,"") | G109: =IF('Unit Mix & Comparables'!$AZ$17<>"",'Unit Mix & Comparables'!$AZ$17,"") | H109: =IF('Unit Mix & Comparables'!$BA$17<>"",'Unit Mix & Comparables'!$BA$17,"") -> 0 | I109: ='Unit Mix & Comparables'!$AZ$40 -> 0 | J109: =IFERROR(G109+I109,"") | K109: =IFERROR(J109/F109,"") | L109: =$AV$43 -> 0 | M109: ='Unit Mix & Comparables'!$BA$6 -> B | N109: ='Unit Mix & Comparables'!$AV$7 -> 2004
B110: =$AV$6 -> Camellia Trace | C110: =IF('Unit Mix & Comparables'!$AV12<>"",'Unit Mix & Comparables'!$AV12,"") -> 25 | D110: =IF('Unit Mix & Comparables'!$AW$11<>"",'Unit Mix & Comparables'!$AW$11,"") -> 1 | E110: =IF('Unit Mix & Comparables'!$AX$11<>"",'Unit Mix & Comparables'!$AX$11,"") -> 1 | F110: =IF('Unit Mix & Comparables'!$AY$11<>"",'Unit Mix & Comparables'!$AY$11,"") -> 907 | G110: =IF('Unit Mix & Comparables'!$AZ$11<>"",'Unit Mix & Comparables'!$AZ$11,"") -> 886 | H110: =IF('Unit Mix & Comparables'!$BA$11<>"",'Unit Mix & Comparables'!$BA$11,"") -> 0.97684675 | I110: ='Unit Mix & Comparables'!$AZ$40 -> 0 | J110: =IFERROR(G110+I110,"") -> 886 | K110: =IFERROR(J110/F110,"") -> 0.97684675 | L110: =$AV$43 -> 0 | M110: ='Unit Mix & Comparables'!$BA$6 -> B | N110: ='Unit Mix & Comparables'!$AV$7 -> 2004
...

Sheet Renovation Plan
B2: ='Executive Summary'!B2 -> Riverhill TH
B3: Renovation Plan
C5: Acquisition | D5: 1 | E5: 2 | F5: 3 | G5: 4 | H5: 5 | I5: 6 | J5: 7 | K5: 8 | L5: 9 | M5: 10 | N5: 11 | O5: 12 | P5: 2
B6: Concessions Adjustment | D6: 0 | E6: 0 | F6: 0 | G6: 0 | H6: 0 | I6: 0 | J6: 0 | K6: 0 | L6: 0 | M6: 0 | N6: 0 | O6: 0 | P6: 0
B7: Occupancy adjustment | D7: 0 | E7: 0 | F7: 0 | G7: 0 | H7: 0 | I7: 0 | J7: 0 | K7: 0 | L7: 0 | M7: 0 | N7: 0 | O7: 0 | P7: 0
B8: Bad Debt Adjustment | D8: 0 | E8: 0 | F8: 0 | G8: 0 | H8: 0 | I8: 0 | J8: 0 | K8: 0 | L8: 0 | M8: 0 | N8: 0 | O8: 0 | P8: 0
B9: Units Upgraded | D9: 0 | E9: 3 | F9: 5 | G9: 3 | H9: 5 | I9: 3 | J9: 5 | K9: 3 | L9: 5 | M9: 3 | N9: 5 | O9: 3 | P9: 5
B10: Concessions | D10: ='Operating Inputs'!$P$11+'Renovation Plan'!D6 -> -0.003 | E10: ='Operating Inputs'!$P$11+'Renovation Plan'!E6 -> -0.003 | F10: ='Operating Inputs'!$P$11+'Renovation Plan'!F6 -> -0.003 | G10: ='Operating Inputs'!$P$11+'Renovation Plan'!G6 -> -0.003 | H10: ='Operating Inputs'!$P$11+'Renovation Plan'!H6 -> -0.003 | I10: ='Operating Inputs'!$P$11+'Renovation Plan'!I6 -> -0.003 | J10: ='Operating Inputs'!$P$11+'Renovation Plan'!J6 -> -0.003 | K10: ='Operating Inputs'!$P$11+'Renovation Plan'!K6 -> -0.003 | ... P10: ='Operating Inputs'!$P$11+'Renovation Plan'!P6 -> -0.003
B11: Current Occupancy | C11: 0.97 | D11: =(1+'Operating Inputs'!$P$12)+'Renovation Plan'!D7 -> 0.944 | E11: =(1+'Operating Inputs'!$P$12)+'Renovation Plan'!E7 -> 0.944 | F11: =(1+'Operating Inputs'!$P$12)+'Renovation Plan'!F7 -> 0.944 | G11: =(1+'Operating Inputs'!$P$12)+'Renovation Plan'!G7 -> 0.944 | H11: =(1+'Operating Inputs'!$P$12)+'Renovation Plan'!H7 -> 0.944 | I11: =(1+'Operating Inputs'!$P$12)+'Renovation Plan'!I7 -> 0.944 | J11: =(1+'Operating Inputs'!$P$12)+'Renovation Plan'!J7 -> 0.944 | K11: =(1+'Operating Inputs'!$P$12)+'Renovation Plan'!K7 -> 0.944 | ... P11: =(1+'Operating Inputs'!$P$12)+'Renovation Plan'!P7 -> 0.944
B12: Bad Debt | D12: ='Operating Inputs'!$P$13+'Renovation Plan'!D8 -> -0.003 | E12: ='Operating Inputs'!$P$13+'Renovation Plan'!E8 -> -0.003 | F12: ='Operating Inputs'!$P$13+'Renovation Plan'!F8 -> -0.003 | G12: ='Operating Inputs'!$P$13+'Renovation Plan'!G8 -> -0.003 | H12: ='Operating Inputs'!$P$13+'Renovation Plan'!H8 -> -0.003 | I12: ='Operating Inputs'!$P$13+'Renovation Plan'!I8 -> -0.003 | J12: ='Operating Inputs'!$P$13+'Renovation Plan'!J8 -> -0.003 | K12: ='Operating Inputs'!$P$13+'Renovation Plan'!K8 -> -0.003 | ... P12: ='Operating Inputs'!$P$13+'Renovation Plan'!P8 -> -0.003
B13: Upgraded Units at Closing | C13: 0 | D13: =IF(C13+D9<='Executive Summary'!$C$12,'Renovation Plan'!C13+'Renovation Plan'!D9,'Executive Summary'!$C$12) -> 0 | E13: =IF(D13+E9<='Executive Summary'!$C$12,'Renovation Plan'!D13+'Renovation Plan'!E9,'Executive Summary'!$C$12) -> 3 | F13: =IF(E13+F9<='Executive Summary'!$C$12,'Renovation Plan'!E13+'Renovation Plan'!F9,'Executive Summary'!$C$12) -> 8 | G13: =IF(F13+G9<='Executive Summary'!$C$12,'Renovation Plan'!F13+'Renovation Plan'!G9,'Executive Summary'!$C$12) -> 11 | H13: =IF(G13+H9<='Executive Summary'!$C$12,'Renovation Plan'!G13+'Renovation Plan'!H9,'Executive Summary'!$C$12) -> 16 | I13: =IF(H13+I9<='Executive Summary'!$C$12,'Renovation Plan'!H13+'Renovation Plan'!I9,'Executive Summary'!$C$12) -> 19 | J13: =IF(I13+J9<='Executive Summary'!$C$12,'Renovation Plan'!I13+'Renovation Plan'!J9,'Executive Summary'!$C$12) -> 24 | K13: =IF(J13+K9<='Executive Summary'!$C$12,'Renovation Plan'!J13+'Renovation Plan'!K9,'Executive Summary'!$C$12) -> 27 | ... P13: =IF(O13+P9<='Executive Summary'!$C$12,'Renovation Plan'!O13+'Renovation Plan'!P9,'Executive Summary'!$C$12) -> 48
B16: Other Construction Assumptions | F16: 5-year Capital Budget (uninflated) | I16: Immediate | J16: 1 | K16: 2 | L16: 3 | M16: 4 | N16: 5 | O16: Total
B17: Construction Management | D17: 0.05 | F17: Total Capital Budget | I17: =SUM(I18,I19) -> 383250 | J17: =SUM(J18,J19) -> 0 | K17: =SUM(K18,K19) -> 0 | L17: =SUM(L18,L19) -> 0 | M17: =SUM(M18,M19) -> 0 | N17: =SUM(N18,N19) -> 0 | O17: =SUM(O18,O19) -> 383250
B18: Contingency | D18: 0 | F18: Unit Upgrade Costs | J18: =$D$24*SUM(OFFSET('Cash Flow - Monthly'!G9,0,J16*12-11,1,12)) -> 0 | K18: =$D$24*SUM(OFFSET('Cash Flow - Monthly'!H9,0,K16*12-11,1,12)) -> 0 | L18: =$D$24*SUM(OFFSET('Cash Flow - Monthly'!I9,0,L16*12-11,1,12)) -> 0 | M18: =$D$24*SUM(OFFSET('Cash Flow - Monthly'!J9,0,M16*12-11,1,12)) -> 0 | N18: =$D$24*SUM(OFFSET('Cash Flow - Monthly'!K9,0,N16*12-11,1,12)) -> 0 | O18: =SUM(I18:N18) -> 0
B19: Primary Renovation Timetable (months) | D19: 36 | F19: Property Renovation | I19: =SUM(I21,I35) -> 383250 | J19: =SUM(J21,J35) -> 0 | K19: =SUM(K21,K35) -> 0 | L19: =SUM(L21,L35) -> 0 | M19: =SUM(M21,M35) -> 0 | N19: =SUM(N21,N35) -> 0 | O19: =SUM(O21,O35) -> 383250
B20: Units Upgrades/Month (after year 1) | D20: 3
B21: Unit Renovation Timetable (months) | D21: =COUNTIF('Cash Flow - Monthly'!H64:EI64,">0") -> 0 | F21: Value-add: | I21: =SUM(I22:I34) -> 204750 | J21: =SUM(J22:J34) -> 0 | K21: =SUM(K22:K34) -> 0 | L21: =SUM(L22:L34) -> 0 | M21: =SUM(M22:M34) -> 0 | N21: =SUM(N22:N34) -> 0 | O21: =SUM(O22:O34) -> 204750
F22: Construction Management | I22: =$D$17*SUM(I23:I34) -> 9750 | J22: =$D$17*SUM(J23:J34) -> 0 | K22: =$D$17*SUM(K23:K34) -> 0 | L22: =$D$17*SUM(L23:L34) -> 0 | M22: =$D$17*SUM(M23:M34) -> 0 | N22: =$D$17*SUM(N23:N34) -> 0 | O22: =SUM(I22:N22) -> 9750
B23: Unit Upgrades from Cash Flow | F23: Contingency | I23: =$D$18*SUM(I24:I34) -> 0 | J23: =$D$18*SUM(J24:J34) -> 0 | K23: =$D$18*SUM(K24:K34) -> 0 | L23: =$D$18*SUM(L24:L34) -> 0 | M23: =$D$18*SUM(M24:M34) -> 0 | N23: =$D$18*SUM(N24:N34) -> 0 | O23: =SUM(I23:N23) -> 0
B24: Average Unit Upgrade Cost | D24: =SUM(D27:D40)*(1+D18)*(1+D17) -> 0 | F24: Up Front Unit Upgrade Capital | I24: 160000 | J24: 0 | K24: 0 | L24: 0 | M24: 0 | N24: 0 | O24: =SUM(I24:N24) -> 160000
F25: Pool Remarsite | I25: 0 | J25: 0 | K25: 0 | L25: 0 | M25: 0 | N25: 0 | O25: =SUM(I25:N25) -> 0
B26: Itemized:Standard Upgrade Plan (1) | F26: Pool Area Upgrades | I26: 35000 | J26: 0 | K26: 0 | L26: 0 | M26: 0 | N26: 0 | O26: =SUM(I26:N26) -> 35000
B27: Appliances | D27: 0 | F27: Dog park | J27: 0 | K27: 0 | L27: 0 | M27: 0 | N27: 0 | O27: =SUM(I27:N27) -> 0
B28: Flooring | D28: 0 | F28: Volly Ball conversion to Bocce Ball | I28: 0 | J28: 0 | K28: 0 | L28: 0 | M28: 0 | N28: 0 | O28: =SUM(I28:N28) -> 0
B29: Cabinets | D29: 0 | F29: Tennis Ct Repurpose | I29: 0 | J29: 0 | K29: 0 | L29: 0 | M29: 0 | N29: 0 | O29: =SUM(I29:N29) -> 0
B30: Countertops | D30: 0 | F30: Leasing Office | I30: 0 | J30: 0 | K30: 0 | L30: 0 | M30: 0 | N30: 0 | O30: =SUM(I30:N30) -> 0
B31: Interior Redevelopment | D31: 0 | F31: Lighting / Security | I31: 0 | J31: 0 | K31: 0 | L31: 0 | M31: 0 | N31: 0 | O31: =SUM(I31:N31) -> 0
B32: Washer/Dryer Machines: | F32: Water Savings | I32: 0 | J32: 0 | K32: 0 | L32: 0 | M32: 0 | N32: 0 | O32: =SUM(I32:N32) -> 0
B33: Cost per Installation | F33: Washer/Dryer | I33: 0 | J33: 0 | K33: 0 | L33: 0 | M33: 0 | N33: 0 | O33: =SUM(I33:N33) -> 0
B34: Number of Units | C34: 0 | F34: Signage | I34: 0 | J34: 0 | K34: 0 | L34: 0 | M34: 0 | N34: 0 | O34: =SUM(I34:N34) -> 0
B35: Average W/D Connection Cost/Unit | D35: =IFERROR(C33*C34/('Executive Summary'!$C$12-C13),0) -> 0 | F35: Asset Preservation: | I35: =SUM(I36:I53) -> 178500 | J35: =SUM(J36:J53) -> 0 | K35: =SUM(K36:K53) -> 0 | L35: =SUM(L36:L53) -> 0 | M35: =SUM(M36:M53) -> 0 | N35: =SUM(N36:N53) -> 0 | O35: =SUM(O36:O53) -> 178500
F36: Construction Management | I36: =$D$17*SUM(I37:I53) -> 8500 | J36: =$D$17*SUM(J37:J53) -> 0 | K36: =$D$17*SUM(K37:K53) -> 0 | L36: =$D$17*SUM(L37:L53) -> 0 | M36: =$D$17*SUM(M37:M53) -> 0 | N36: =$D$17*SUM(N37:N53) -> 0 | O36: =SUM(I36:N36) -> 8500
B37: Superior Upgrade Plan | F37: Contingency | I37: =$D$18*SUM(I38:I53) -> 0 | J37: =$D$18*SUM(J38:J53) -> 0 | K37: =$D$18*SUM(K38:K53) -> 0 | L37: =$D$18*SUM(L38:L53) -> 0 | M37: =$D$18*SUM(M38:M53) -> 0 | N37: =$D$18*SUM(N38:N53) -> 0 | O37: =SUM(I37:N37) -> 0
B38: Incremental Cost per Unit (over base) | D38: 0 | F38: Roof Repair | I38: 0 | J38: 0 | K38: 0 | L38: 0 | M38: 0 | N38: 0 | O38: =SUM(I38:N38) -> 0
B39: Number of Units | D39: 0 | F39: General Carpentry / Front Doors | I39: 0 | J39: 0 | K39: 0 | L39: 0 | M39: 0 | N39: 0 | O39: =SUM(I39:N39) -> 0
B40: Average Cost per Turn | D40: =IFERROR(C38*C39/('Executive Summary'!$C$12-C13),0) -> 0 | F40: Exterior Siding | I40: 0 | J40: 0 | K40: 0 | L40: 0 | M40: 0 | N40: 0 | O40: =SUM(I40:N40) -> 0
B41: (1) These numbers are estimates of excess cost over ordinary recurring replacements: | F41: Paving | I41: 25000 | J41: 0 | K41: 0 | L41: 0 | M41: 0 | N41: 0 | O41: =SUM(I41:N41) -> 25000
F42: Fencing & Railing | I42: 0 | J42: 0 | K42: 0 | L42: 0 | M42: 0 | N42: 0 | O42: =SUM(I42:N42) -> 0
F43: Gutters | I43: 0 | J43: 0 | K43: 0 | L43: 0 | M43: 0 | N43: 0 | O43: =SUM(I43:N43) -> 0
B44: Asset Preservation Summary | F44: Stoops Landings & Breezeways | I44: 15000 | J44: 0 | K44: 0 | L44: 0 | M44: 0 | N44: 0 | O44: =SUM(I44:N44) -> 15000
B45: Total AP, O&M, & Reserves, Years 1-5 | D45: =SUM(J35:N35)/5/'Executive Summary'!$C$12+'Executive Summary'!C54+'Operating Inputs'!P25 -> 1025 | F45: Foundation | I45: 0 | J45: 0 | K45: 0 | L45: 0 | M45: 0 | N45: 0 | O45: =SUM(I45:N45) -> 0
B46: Total AP, O&M, & Reserves, Years 6-10 | D46: ='Executive Summary'!C55+'Operating Inputs'!P25 -> 1025 | F46: Landscaping | J46: 0 | K46: 0 | L46: 0 | M46: 0 | N46: 0 | O46: =SUM(I46:N46) -> 0
F47: Misc. | I47: 80000 | J47: 0 | K47: 0 | L47: 0 | M47: 0 | N47: 0 | O47: =SUM(I47:N47) -> 80000
F48: HVAC | I48: 50000 | J48: 0 | K48: 0 | L48: 0 | M48: 0 | N48: 0 | O48: =SUM(I48:N48) -> 50000
F49: Plumbing Allowance | I49: 0 | J49: 0 | K49: 0 | L49: 0 | M49: 0 | N49: 0 | O49: =SUM(I49:N49) -> 0
F50: Painting | I50: 0 | J50: 0 | K50: 0 | L50: 0 | M50: 0 | N50: 0 | O50: =SUM(I50:N50) -> 0
F51: Fire Stops | I51: 0 | J51: 0 | K51: 0 | L51: 0 | M51: 0 | N51: 0 | O51: =SUM(I51:N51) -> 0
F52: Fencing | I52: 0 | J52: 0 | K52: 0 | L52: 0 | M52: 0 | N52: 0 | O52: =SUM(I52:N52) -> 0
F53: Windows | J53: 0 | K53: 0 | M53: 0 | N53: 0 | O53: =SUM(I53:N53) -> 0

Sheet Unit Reno Premium Comp
B1: Subject Post Renovation | I1: Subject Pro Forma | P1: Subject Current
B2: ='Executive Summary'!$C$5 -> Riverhill TH | G2: B | I2: ='Executive Summary'!$C$5 -> Riverhill TH | N2: B | P2: ='Executive Summary'!$C$5 -> Riverhill TH | X2: B
B3: ='Executive Summary'!$C$9 -> 1982 | I3: ='Executive Summary'!$C$9 -> 1982 | P3: ='Executive Summary'!$C$9 -> 1982
B4: Count | C4: Beds | D4: Baths | E4: SF | F4: $ | G4: $/SF | H4: Variance | I4: Count | J4: Beds | K4: Baths | L4: SF | M4: $ | N4: $/SF | O4: Variance | P4: Count | Q4: Beds | R4: Baths | S4: SF | T4: $ | U4: $/SF | V4: T12 Avg | W4: T3 Avg | X4: T3 Leases
A5: Level 1 | B5: 2 | C5: 2 | D5: 1.5 | E5: 1008 | F5: 827 | G5: =IFERROR(IF(B5, F5/E5, 0),0) -> 0.82043651 | H5: =F5-M5 -> 98 | I5: 2 | J5: 2 | K5: 1.5 | L5: 1008 | M5: 729 | N5: =IFERROR(IF(I5, M5/L5, 0),0) -> 0.72321429 | O5: =M5-T5 -> 26 | P5: =IF(I5<>"",I5,"") -> 2 | Q5: =IF(J5<>"",J5,"") -> 2 | R5: =IF(K5<>"",K5,"") -> 1.5 | S5: =IF(L5<>"",L5,"") -> 1008 | T5: 703 | U5: =IFERROR(IF(P5, T5/S5, 0),0) -> 0.69742063
A6: Level 2 | B6: 15 | C6: 2 | D6: 1.5 | E6: 1008 | F6: 827 | G6: =IFERROR(IF(B6, F6/E6, 0),0) -> 0.82043651 | H6: =F6-M6 -> 55 | I6: 15 | J6: 2 | K6: 1.5 | L6: 1008 | M6: 772 | N6: =IFERROR(IF(I6, M6/L6, 0),0) -> 0.76587302 | O6: =M6-T6 -> 0 | P6: =IF(I6<>"",I6,"") -> 15 | Q6: =IF(J6<>"",J6,"") -> 2 | R6: =IF(K6<>"",K6,"") -> 1.5 | S6: =IF(L6<>"",L6,"") -> 1008 | T6: 772 | U6: =IFERROR(IF(P6, T6/S6, 0),0) -> 0.76587302
A7: Level 3 | B7: 63 | C7: 2 | D7: 1.5 | E7: 1008 | F7: 827 | G7: =IFERROR(IF(B7, F7/E7, 0),0) -> 0.82043651 | H7: =F7-M7 -> 47 | I7: 63 | J7: 2 | K7: 1.5 | L7: 1008 | M7: 780 | N7: =IFERROR(IF(I7, M7/L7, 0),0) -> 0.77380952 | O7: =M7-T7 -> 2 | P7: =IF(I7<>"",I7,"") -> 63 | Q7: =IF(J7<>"",J7,"") -> 2 | R7: =IF(K7<>"",K7,"") -> 1.5 | S7: =IF(L7<>"",L7,"") -> 1008 | T7: 778 | U7: =IFERROR(IF(P7, T7/S7, 0),0) -> 0.7718254
A8: Level 4 | G8: =IFERROR(IF(B8, F8/E8, 0),0) -> 0 | H8: =F8-M8 -> 0 | N8: =IFERROR(IF(I8, M8/L8, 0),0) -> 0 | O8: =M8-T8 -> 0 | P8: =IF(I8<>"",I8,"") | Q8: =IF(J8<>"",J8,"") | R8: =IF(K8<>"",K8,"") | S8: =IF(L8<>"",L8,"") | U8: =IFERROR(IF(P8, T8/S8, 0),0) -> 0
A9: Level 1 | G9: =IFERROR(IF(B9, F9/E9, 0),0) -> 0 | H9: =F9-M9 -> 0 | N9: =IFERROR(IF(I9, M9/L9, 0),0) -> 0 | O9: =M9-T9 -> 0 | P9: =IF(I9<>"",I9,"") | Q9: =IF(J9<>"",J9,"") | R9: =IF(K9<>"",K9,"") | S9: =IF(L9<>"",L9,"") | U9: =IFERROR(IF(P9, T9/S9, 0),0) -> 0
A10: Level 2 | G10: =IFERROR(IF(B10, F10/E10, 0),0) -> 0 | H10: =F10-M10 -> 0 | N10: =IFERROR(IF(I10, M10/L10, 0),0) -> 0 | O10: =M10-T10 -> 0 | P10: =IF(I10<>"",I10,"") | Q10: =IF(J10<>"",J10,"") | R10: =IF(K10<>"",K10,"") | S10: =IF(L10<>"",L10,"") | U10: =IFERROR(IF(P10, T10/S10, 0),0) -> 0
A11: Level 4 | G11: =IFERROR(IF(B11, F11/E11, 0),0) -> 0 | H11: =F11-M11 -> 0 | N11: =IFERROR(IF(I11, M11/L11, 0),0) -> 0 | O11: =M11-T11 -> 0 | P11: =IF(I11<>"",I11,"") | Q11: =IF(J11<>"",J11,"") | R11: =IF(K11<>"",K11,"") | S11: =IF(L11<>"",L11,"") | U11: =IFERROR(IF(P11, T11/S11, 0),0) -> 0
A12: Level 3 | G12: =IFERROR(IF(B12, F12/E12, 0),0) -> 0 | H12: =F12-M12 -> 0 | N12: =IFERROR(IF(I12, M12/L12, 0),0) -> 0 | O12: =M12-T12 -> 0 | P12: =IF(I12<>"",I12,"") | Q12: =IF(J12<>"",J12,"") | R12: =IF(K12<>"",K12,"") | S12: =IF(L12<>"",L12,"") | U12: =IFERROR(IF(P12, T12/S12, 0),0) -> 0
A13: Level 2 | G13: =IFERROR(IF(B13, F13/E13, 0),0) -> 0 | H13: =F13-M13 -> 0 | N13: =IFERROR(IF(I13, M13/L13, 0),0) -> 0 | O13: =M13-T13 -> 0 | P13: =IF(I13<>"",I13,"") | Q13: =IF(J13<>"",J13,"") | R13: =IF(K13<>"",K13,"") | S13: =IF(L13<>"",L13,"") | U13: =IFERROR(IF(P13, T13/S13, 0),0) -> 0
A14: Level 3 | G14: =IFERROR(IF(B14, F14/E14, 0),0) -> 0 | H14: =F14-M14 -> 0 | N14: =IFERROR(IF(I14, M14/L14, 0),0) -> 0 | O14: =M14-T14 -> 0 | P14: =IF(I14<>"",I14,"") | Q14: =IF(J14<>"",J14,"") | R14: =IF(K14<>"",K14,"") | S14: =IF(L14<>"",L14,"") | U14: =IFERROR(IF(P14, T14/S14, 0),0) -> 0
A15: Level 4 | G15: =IFERROR(IF(B15, F15/E15, 0),0) -> 0 | H15: =F15-M15 -> 0 | N15: =IFERROR(IF(I15, M15/L15, 0),0) -> 0 | O15: =M15-T15 -> 0 | P15: =IF(I15<>"",I15,"") | Q15: =IF(J15<>"",J15,"") | R15: =IF(K15<>"",K15,"") | S15: =IF(L15<>"",L15,"") | U15: =IFERROR(IF(P15, T15/S15, 0),0) -> 0
A16: Level 2 | G16: =IFERROR(IF(B16, F16/E16, 0),0) -> 0 | H16: =F16-M16 -> 0 | N16: =IFERROR(IF(I16, M16/L16, 0),0) -> 0 | O16: =M16-T16 -> 0 | P16: =IF(I16<>"",I16,"") | Q16: =IF(J16<>"",J16,"") | R16: =IF(K16<>"",K16,"") | S16: =IF(L16<>"",L16,"") | U16: =IFERROR(IF(P16, T16/S16, 0),0) -> 0
A17: Level 1 | G17: =IFERROR(IF(B17, F17/E17, 0),0) -> 0 | H17: =F17-M17 -> 0 | N17: =IFERROR(IF(I17, M17/L17, 0),0) -> 0 | O17: =M17-T17 -> 0 | P17: =IF(I17<>"",I17,"") | Q17: =IF(J17<>"",J17,"") | R17: =IF(K17<>"",K17,"") | S17: =IF(L17<>"",L17,"") | U17: =IFERROR(IF(P17, T17/S17, 0),0) -> 0
A18: Level 3 | G18: =IFERROR(IF(B18, F18/E18, 0),0) -> 0 | H18: =F18-M18 -> 0 | N18: =IFERROR(IF(I18, M18/L18, 0),0) -> 0 | O18: =M18-T18 -> 0 | P18: =IF(I18<>"",I18,"") | Q18: =IF(J18<>"",J18,"") | R18: =IF(K18<>"",K18,"") | S18: =IF(L18<>"",L18,"") | U18: =IFERROR(IF(P18, T18/S18, 0),0) -> 0
A19: Level 4 | G19: =IFERROR(IF(B19, F19/E19, 0),0) -> 0 | H19: =F19-M19 -> 0 | N19: =IFERROR(IF(I19, M19/L19, 0),0) -> 0 | O19: =M19-T19 -> 0 | P19: =IF(I19<>"",I19,"") | Q19: =IF(J19<>"",J19,"") | R19: =IF(K19<>"",K19,"") | S19: =IF(L19<>"",L19,"") | U19: =IFERROR(IF(P19, T19/S19, 0),0) -> 0
... A34: Level 3 | G34: =IFERROR(IF(B34, F34/E34, 0),0) -> 0 | H34: =F34-M34 -> 0 | N34: =IFERROR(IF(I34, M34/L34, 0),0) -> 0 | O34: =M34-T34 -> 0 | P34: =IF(I34<>"",I34,"") | Q34: =IF(J34<>"",J34,"") | R34: =IF(K34<>"",K34,"") | S34: =IF(L34<>"",L34,"") | U34: =IFERROR(IF(P34, T34/S34, 0),0) -> 0
B35: =SUM(B5:B34) -> 80 | E35: =SUMPRODUCT(B5:B34, E5:E34)/B35 -> 1008 | F35: =SUMPRODUCT(B5:B34, F5:F34)/B35 -> 827 | G35: =IFERROR(F35/E35,0) -> 0.82043651 | I35: =SUM(I5:I34) -> 80 | L35: =SUMPRODUCT(I5:I34, L5:L34)/I35 -> 1008 | M35: =SUMPRODUCT(I5:I34, M5:M34)/I35 -> 777.225 | N35: =IFERROR(M35/L35,0) -> 0.77105655 | P35: =SUM(P5:P34) -> 80 | S35: =SUMPRODUCT(P5:P34, S5:S34)/P35 -> 1008 | T35: =SUMPRODUCT(P5:P34, T5:T34)/P35 -> 775 | U35: =IFERROR(T35/S35,0) -> 0.76884921 | V35: 0 | W35: 0 | X35: 0
N36: =IFERROR(M36/L35,0) -> 0

Sheet Cash Flow - Monthly
B2: ='Executive Summary'!B2 -> Riverhill TH | G2: 43160 | H2: =EDATE(G2,1) -> 43191 | I2: =EDATE(H2,1) -> 43221 | J2: =EDATE(I2,1) -> 43252 | K2: =EDATE(J2,1) -> 43282 | L2: =EDATE(K2,1) -> 43313 | M2: =EDATE(L2,1) -> 43344 | N2: =EDATE(M2,1) -> 43374 | O2: =EDATE(N2,1) -> 43405 | ... EI2: =EDATE(EH2,1) -> 47178
B3: Cash Flow - Monthly | E3: ='Executive Summary'!I13/12 -> 5 | G3: 0 | H3: 1 | I3: 1 | J3: 1 | K3: 1 | L3: 1 | M3: 1 | N3: 1 | O3: 1 | P3: 1 | Q3: 1 | R3: 1 | S3: 1 | T3: 2 | U3: 2 | V3: 2 | W3: 2 | X3: 2 | Y3: 2 | Z3: 2 | AA3: 2 | AB3: 2 | AC3: 2 | AD3: 2 | AE3: 2 | AF3: 3 | AG3: 3 | AH3: 3 | AI3: 3 | AJ3: 3 | AK3: 3 | AL3: 3 | AM3: 3 | AN3: 3 | AO3: 3 | AP3: 3 | AQ3: 3 | AR3: 4 | AS3: 4 | AT3: 4 | AU3: 4 | AV3: 4 | AW3: 4 | AX3: 4 | AY3: 4 | AZ3: 4 | BA3: 4 | BB3: 4 | BC3: 4 | BD3: 5 | BE3: 5 | BF3: 5 | BG3: 5 | BH3: 5 | BI3: 5 | BJ3: 5 | BK3: 5 | BL3: 5 | BM3: 5 | BN3: 5 | BO3: 5 | BP3: 6 | BQ3: 6 | BR3: 6 | BS3: 6 | BT3: 6 | BU3: 6 | BV3: 6 | BW3: 6 | BX3: 6 | BY3: 6 | BZ3: 6 | CA3: 6 | CB3: 7 | CC3: 7 | CD3: 7 | CE3: 7 | CF3: 7 | CG3: 7 | CH3: 7 | CI3: 7 | CJ3: 7 | CK3: 7 | CL3: 7 | CM3: 7 | CN3: 8 | CO3: 8 | CP3: 8 | CQ3: 8 | CR3: 8 | CS3: 8 | CT3: 8 | CU3: 8 | CV3: 8 | CW3: 8 | CX3: 8 | CY3: 8 | CZ3: 9 | DA3: 9 | DB3: 9 | DC3: 9 | DD3: 9 | DE3: 9 | DF3: 9 | DG3: 9 | DH3: 9 | DI3: 9 | DJ3: 9 | DK3: 9 | DL3: 10 | DM3: 10 | DN3: 10 | DO3: 10 | DP3: 10 | DQ3: 10 | DR3: 10 | DS3: 10 | DT3: 10 | DU3: 10 | DV3: 10 | DW3: 10 | DX3: 11 | DY3: 11 | DZ3: 11 | EA3: 11 | EB3: 11 | EC3: 11 | ED3: 11 | EE3: 11 | EF3: 11 | EG3: 11 | EH3: 11 | EI3: 11
G4: 0 | H4: 1 | I4: 2 | J4: 3 | K4: 4 | L4: 5 | M4: 6 | N4: 7 | O4: 8 | P4: 9 | Q4: 10 | R4: 11 | S4: 12 | T4: 13 | U4: 14 | V4: 15 | W4: 16 | X4: 17 | Y4: 18 | Z4: 19 | AA4: 20 | AB4: 21 | AC4: 22 | AD4: 23 | AE4: 24 | AF4: 25 | AG4: 26 | AH4: 27 | AI4: 28 | AJ4: 29 | AK4: 30 | AL4: 31 | AM4: 32 | AN4: 33 | AO4: 34 | AP4: 35 | AQ4: 36 | AR4: 37 | AS4: 38 | AT4: 39 | AU4: 40 | AV4: 41 | AW4: 42 | AX4: 43 | AY4: 44 | AZ4: 45 | BA4: 46 | BB4: 47 | BC4: 48 | BD4: 49 | BE4: 50 | BF4: 51 | BG4: 52 | BH4: 53 | BI4: 54 | BJ4: 55 | BK4: 56 | BL4: 57 | BM4: 58 | BN4: 59 | BO4: 60 | BP4: 61 | BQ4: 62 | BR4: 63 | BS4: 64 | BT4: 65 | BU4: 66 | BV4: 67 | BW4: 68 | BX4: 69 | BY4: 70 | BZ4: 71 | CA4: 72 | CB4: 73 | CC4: 74 | CD4: 75 | CE4: 76 | CF4: 77 | CG4: 78 | CH4: 79 | CI4: 80 | CJ4: 81 | CK4: 82 | CL4: 83 | CM4: 84 | CN4: 85 | CO4: 86 | CP4: 87 | CQ4: 88 | CR4: 89 | CS4: 90 | CT4: 91 | CU4: 92 | CV4: 93 | CW4: 94 | CX4: 95 | CY4: 96 | CZ4: 97 | DA4: 98 | DB4: 99 | DC4: 100 | DD4: 101 | DE4: 102 | DF4: 103 | DG4: 104 | DH4: 105 | DI4: 106 | DJ4: 107 | DK4: 108 | DL4: 109 | DM4: 110 | DN4: 111 | DO4: 112 | DP4: 113 | DQ4: 114 | DR4: 115 | DS4: 116 | DT4: 117 | DU4: 118 | DV4: 119 | DW4: 120 | DX4: 121 | DY4: 122 | DZ4: 123 | EA4: 124 | EB4: 125 | EC4: 126 | ED4: 127 | EE4: 128 | EF4: 129 | EG4: 130 | EH4: 131 | EI4: 132
B6: Revenue Calculations
B7: Cumulative Rent Growth Factor | G7: 1 | H7: =G7*((1+'Executive Summary'!$I$5)^(1/12)) -> 1.0005483 | I7: =H7*((1+'Executive Summary'!$I$5)^(1/12)) -> 1.001097 | J7: =I7*((1+'Executive Summary'!$I$5)^(1/12)) -> 1.0016459 | K7: =J7*((1+'Executive Summary'!$I$5)^(1/12)) -> 1.0021952 | L7: =K7*((1+'Executive Summary'!$I$5)^(1/12)) -> 1.0027447 | M7: =L7*((1+'Executive Summary'!$I$5)^(1/12)) -> 1.0032946 | N7: =M7*((1+'Executive Summary'!$I$5)^(1/12)) -> 1.0038447 | O7: =N7*((1+'Executive Summary'!$I$5)^(1/12)) -> 1.0043952 | ... S7: =R7*((1+'Executive Summary'!$I$5)^(1/12)) -> 1.0066 | T7: =S7*((1+'Executive Summary'!$I$6)^(1/12)) -> 1.0092946 | U7: =T7*((1+'Executive Summary'!$I$6)^(1/12)) -> 1.0119964 | V7: =U7*((1+'Executive Summary'!$I$6)^(1/12)) -> 1.0147054 | W7: =V7*((1+'Executive Summary'!$I$6)^(1/12)) -> 1.0174216 | X7: =W7*((1+'Executive Summary'!$I$6)^(1/12)) -> 1.0201452 | Y7: =X7*((1+'Executive Summary'!$I$6)^(1/12)) -> 1.022876 | Z7: =Y7*((1+'Executive Summary'!$I$6)^(1/12)) -> 1.0256141 | AA7: =Z7*((1+'Executive Summary'!$I$6)^(1/12)) -> 1.0283596 | ... AE7: =AD7*((1+'Executive Summary'!$I$6)^(1/12)) -> 1.0394152 | AF7: =AE7*((1+'Executive Summary'!$I$7)^(1/12)) -> 1.0419786 | AG7: =AF7*((1+'Executive Summary'!$I$7)^(1/12)) -> 1.0445484 | AH7: =AG7*((1+'Executive Summary'!$I$7)^(1/12)) -> 1.0471246 | AI7: =AH7*((1+'Executive Summary'!$I$7)^(1/12)) -> 1.0497071 | AJ7: =AI7*((1+'Executive Summary'!$I$7)^(1/12)) -> 1.0522959 | AK7: =AJ7*((1+'Executive Summary'!$I$7)^(1/12)) -> 1.0548912 | AL7: =AK7*((1+'Executive Summary'!$I$7)^(1/12)) -> 1.0574928 | AM7: =AL7*((1+'Executive Summary'!$I$7)^(1/12)) -> 1.0601009 | ... EI7: =EH7*((1+'Executive Summary'!$I$7)^(1/12)) -> 1.356201
B8: Cumulative Other Growth Factor | G8: 1 | H8: =G8*((1+'Executive Summary'!$I$8)^(1/12)) -> 1.0016516 | I8: =H8*((1+'Executive Summary'!$I$8)^(1/12)) -> 1.0033059 | J8: =I8*((1+'Executive Summary'!$I$8)^(1/12)) -> 1.0049629 | K8: =J8*((1+'Executive Summary'!$I$8)^(1/12)) -> 1.0066227 | L8: =K8*((1+'Executive Summary'!$I$8)^(1/12)) -> 1.0082852 | M8: =L8*((1+'Executive Summary'!$I$8)^(1/12)) -> 1.0099505 | N8: =M8*((1+'Executive Summary'!$I$8)^(1/12)) -> 1.0116185 | O8: =N8*((1+'Executive Summary'!$I$8)^(1/12)) -> 1.0132893 | ... S8: =R8*((1+'Executive Summary'!$I$8)^(1/12)) -> 1.02 | T8: =S8*((1+'Executive Summary'!$I$9)^(1/12)) -> 1.0216846 | U8: =T8*((1+'Executive Summary'!$I$9)^(1/12)) -> 1.023372 | V8: =U8*((1+'Executive Summary'!$I$9)^(1/12)) -> 1.0250622 | W8: =V8*((1+'Executive Summary'!$I$9)^(1/12)) -> 1.0267552 | X8: =W8*((1+'Executive Summary'!$I$9)^(1/12)) -> 1.0284509 | Y8: =X8*((1+'Executive Summary'!$I$9)^(1/12)) -> 1.0301495 | Z8: =Y8*((1+'Executive Summary'!$I$9)^(1/12)) -> 1.0318509 | AA8: =Z8*((1+'Executive Summary'!$I$9)^(1/12)) -> 1.0335551 | ... AE8: =AD8*((1+'Executive Summary'!$I$9)^(1/12)) -> 1.0404 | AF8: =AE8*((1+'Executive Summary'!$I$10)^(1/12)) -> 1.0421183 | AG8: =AF8*((1+'Executive Summary'!$I$10)^(1/12)) -> 1.0438394 | AH8: =AG8*((1+'Executive Summary'!$I$10)^(1/12)) -> 1.0455634 | AI8: =AH8*((1+'Executive Summary'!$I$10)^(1/12)) -> 1.0472903 | AJ8: =AI8*((1+'Executive Summary'!$I$10)^(1/12)) -> 1.04902 | AK8: =AJ8*((1+'Executive Summary'!$I$10)^(1/12)) -> 1.0507525 | AL8: =AK8*((1+'Executive Summary'!$I$10)^(1/12)) -> 1.0524879 | AM8: =AL8*((1+'Executive Summary'!$I$10)^(1/12)) -> 1.0542262 | ... EI8: =EH8*((1+'Executive Summary'!$I$10)^(1/12)) -> 1.2433743
B9: Units Upgraded | H9: =MIN('Renovation Plan'!D9,'Executive Summary'!$C$12-G10) -> 0 | I9: =MIN('Renovation Plan'!E9,'Executive Summary'!$C$12-H10) -> 3 | J9: =MIN('Renovation Plan'!F9,'Executive Summary'!$C$12-I10) -> 5 | K9: =MIN('Renovation Plan'!G9,'Executive Summary'!$C$12-J10) -> 3 | L9: =MIN('Renovation Plan'!H9,'Executive Summary'!$C$12-K10) -> 5 | M9: =MIN('Renovation Plan'!I9,'Executive Summary'!$C$12-L10) -> 3 | N9: =MIN('Renovation Plan'!J9,'Executive Summary'!$C$12-M10) -> 5 | O9: =MIN('Renovation Plan'!K9,'Executive Summary'!$C$12-N10) -> 3 | ... S9: =MIN('Renovation Plan'!O9,'Executive Summary'!$C$12-R10) -> 3 | T9: =MIN('Renovation Plan'!$P$9,'Executive Summary'!$C$12-S10) -> 5 | U9: =MIN('Renovation Plan'!$P$9,'Executive Summary'!$C$12-T10) -> 5 | V9: =MIN('Renovation Plan'!$P$9,'Executive Summary'!$C$12-U10) -> 5 | W9: =MIN('Renovation Plan'!$P$9,'Executive Summary'!$C$12-V10) -> 5 | X9: =MIN('Renovation Plan'!$P$9,'Executive Summary'!$C$12-W10) -> 5 | Y9: =MIN('Renovation Plan'!$P$9,'Executive Summary'!$C$12-X10) -> 5 | Z9: =MIN('Renovation Plan'!$P$9,'Executive Summary'!$C$12-Y10) -> 5 | AA9: =MIN('Renovation Plan'!$P$9,'Executive Summary'!$C$12-Z10) -> 2 | ... EI9: =MIN('Renovation Plan'!$P$9,'Executive Summary'!$C$12-EH10) -> 0
B10: Upgraded Units EOP | G10: ='Renovation Plan'!C13 -> 0 | H10: =G10+H9 -> 0 | I10: =H10+I9 -> 3 | J10: =I10+J9 -> 8 | K10: =J10+K9 -> 11 | L10: =K10+L9 -> 16 | M10: =L10+M9 -> 19 | N10: =M10+N9 -> 24 | O10: =N10+O9 -> 27 | ... EI10: =EH10+EI9 -> 80
B11: Average Market Rent- Post Renovation | G11: =('Unit Mix & Comparables'!$Q$55-((('Executive Summary'!$C$12-G10)/'Executive Summary'!$C$12)*'Unit Mix & Comparables'!$N$55))/MAX(1,1+'Unit Mix & Comparables'!$D$51-('Unit Mix & Comparables'!$D$51*G4/'Renovation Plan'!$D$19))*G7 -> 777.225 | H11: =('Unit Mix & Comparables'!$Q$55-((('Executive Summary'!$C$12-H10)/'Executive Summary'!$C$12)*'Unit Mix & Comparables'!$N$55))/MAX(1,1+'Unit Mix & Comparables'!$D$51-('Unit Mix & Comparables'!$D$51*H4/'Renovation Plan'!$D$19))*H7 -> 777.65119 | I11: =('Unit Mix & Comparables'!$Q$55-((('Executive Summary'!$C$12-I10)/'Executive Summary'!$C$12)*'Unit Mix & Comparables'!$N$55))/MAX(1,1+'Unit Mix & Comparables'!$D$51-('Unit Mix & Comparables'!$D$51*I4/'Renovation Plan'!$D$19))*I7 -> 779.95466 | J11: =('Unit Mix & Comparables'!$Q$55-((('Executive Summary'!$C$12-J10)/'Executive Summary'!$C$12)*'Unit Mix & Comparables'!$N$55))/MAX(1,1+'Unit Mix & Comparables'!$D$51-('Unit Mix & Comparables'!$D$51*J4/'Renovation Plan'!$D$19))*J7 -> 783.51249 | K11: =('Unit Mix & Comparables'!$Q$55-((('Executive Summary'!$C$12-K10)/'Executive Summary'!$C$12)*'Unit Mix & Comparables'!$N$55))/MAX(1,1+'Unit Mix & Comparables'!$D$51-('Unit Mix & Comparables'!$D$51*K4/'Renovation Plan'!$D$19))*K7 -> 785.82124 | L11: =('Unit Mix & Comparables'!$Q$55-((('Executive Summary'!$C$12-L10)/'Executive Summary'!$C$12)*'Unit Mix & Comparables'!$N$55))/MAX(1,1+'Unit Mix & Comparables'!$D$51-('Unit Mix & Comparables'!$D$51*L4/'Renovation Plan'!$D$19))*L7 -> 789.38572 | M11: =('Unit Mix & Comparables'!$Q$55-((('Executive Summary'!$C$12-M10)/'Executive Summary'!$C$12)*'Unit Mix & Comparables'!$N$55))/MAX(1,1+'Unit Mix & Comparables'!$D$51-('Unit Mix & Comparables'!$D$51*M4/'Renovation Plan'!$D$19))*M7 -> 791.69975 | N11: =('Unit Mix & Comparables'!$Q$55-((('Executive Summary'!$C$12-N10)/'Executive Summary'!$C$12)*'Unit Mix & Comparables'!$N$55))/MAX(1,1+'Unit Mix & Comparables'!$D$51-('Unit Mix & Comparables'!$D$51*N4/'Renovation Plan'!$D$19))*N7 -> 795.27089 | ... EI11: =('Unit Mix & Comparables'!$Q$55-((('Executive Summary'!$C$12-EI10)/'Executive Summary'!$C$12)*'Unit Mix & Comparables'!$N$55))/MAX(1,1+'Unit Mix & Comparables'!$D$51-('Unit Mix & Comparables'!$D$51*EI4/'Renovation Plan'!$D$19))*EI7 -> 1121.8834
B12: Occupancy | G12: ='Renovation Plan'!C11 -> 0.97 | H12: ='Renovation Plan'!D11 -> 0.944 | I12: ='Renovation Plan'!E11 -> 0.944 | J12: ='Renovation Plan'!F11 -> 0.944 | K12: ='Renovation Plan'!G11 -> 0.944 | L12: ='Renovation Plan'!H11 -> 0.944 | M12: ='Renovation Plan'!I11 -> 0.944 | N12: ='Renovation Plan'!J11 -> 0.944 | ... S12: ='Renovation Plan'!O11 -> 0.944 | T12: ='Renovation Plan'!$P$11 -> 0.944 | U12: ='Renovation Plan'!$P$11 -> 0.944 | V12: ='Renovation Plan'!$P$11 -> 0.944 | W12: ='Renovation Plan'!$P$11 -> 0.944 | X12: ='Renovation Plan'!$P$11 -> 0.944 | Y12: ='Renovation Plan'!$P$11 -> 0.944 | Z12: ='Renovation Plan'!$P$11 -> 0.944 | AA12: ='Renovation Plan'!$P$11 -> 0.944 | ... AE12: ='Renovation Plan'!$P$11 -> 0.944 | AF12: =1+'Operating Inputs'!$P$12 -> 0.944 | AG12: =1+'Operating Inputs'!$P$12 -> 0.944 | AH12: =1+'Operating Inputs'!$P$12 -> 0.944 | AI12: =1+'Operating Inputs'!$P$12 -> 0.944 | AJ12: =1+'Operating Inputs'!$P$12 -> 0.944 | AK12: =1+'Operating Inputs'!$P$12 -> 0.944 | AL12: =1+'Operating Inputs'!$P$12 -> 0.944 | AM12: =1+'Operating Inputs'!$P$12 -> 0.944 | ... EI12: =1+'Operating Inputs'!$P$12 -> 0.944
B13: Non-Upgraded Units Vacated | H13: =$G$18/12 -> 6.4666667 | I13: =$G$18/12 -> 6.4666667 | J13: =$G$18/12 -> 6.4666667 | K13: =$G$18/12 -> 6.4666667 | L13: =$G$18/12 -> 6.4666667 | M13: =$G$18/12 -> 6.4666667 | N13: =$G$18/12 -> 6.4666667 | O13: =$G$18/12 -> 6.4666667 | ... S13: =$G$18/12 -> 6.4666667 | T13: =H16 -> 4.3866667 | U13: =I16 -> 3.4666667 | V13: =J16 -> 1.4666667 | W13: =K16 -> 3.4666667 | X13: =L16 -> 1.4666667 | Y13: =M16 -> 3.4666667 | Z13: =N16 -> 1.4666667 | AA13: =O16 -> 3.4666667 | ... EI13: =DW16 -> 0
B14: Upgraded Units Vacated | H14: =$G$19/12 -> 0 | I14: =$G$19/12 -> 0 | J14: =$G$19/12 -> 0 | K14: =$G$19/12 -> 0 | L14: =$G$19/12 -> 0 | M14: =$G$19/12 -> 0 | N14: =$G$19/12 -> 0 | O14: =$G$19/12 -> 0 | ... S14: =$G$19/12 -> 0 | T14: =H17 -> 0 | U14: =I17 -> 3 | V14: =J17 -> 5 | W14: =K17 -> 3 | X14: =L17 -> 5 | Y14: =M17 -> 3 | Z14: =N17 -> 5 | AA14: =O17 -> 3 | ... EI14: =DW17 -> 6.4666667
B15: Total Units Leased | H15: =(H13+H14)+(H12-G12)*'Executive Summary'!$C$12 -> 4.3866667 | I15: =(I13+I14)+(I12-H12)*'Executive Summary'!$C$12 -> 6.4666667 | J15: =(J13+J14)+(J12-I12)*'Executive Summary'!$C$12 -> 6.4666667 | K15: =(K13+K14)+(K12-J12)*'Executive Summary'!$C$12 -> 6.4666667 | L15: =(L13+L14)+(L12-K12)*'Executive Summary'!$C$12 -> 6.4666667 | M15: =(M13+M14)+(M12-L12)*'Executive Summary'!$C$12 -> 6.4666667 | N15: =(N13+N14)+(N12-M12)*'Executive Summary'!$C$12 -> 6.4666667 | O15: =(O13+O14)+(O12-N12)*'Executive Summary'!$C$12 -> 6.4666667 | ... EI15: =(EI13+EI14)+(EI12-EH12)*'Executive Summary'!$C$12 -> 6.4666667
B16: Non-Upgraded Units Leased | H16: =H15-H17 -> 4.3866667 | I16: =I15-I17 -> 3.4666667 | J16: =J15-J17 -> 1.4666667 | K16: =K15-K17 -> 3.4666667 | L16: =L15-L17 -> 1.4666667 | M16: =M15-M17 -> 3.4666667 | N16: =N15-N17 -> 1.4666667 | O16: =O15-O17 -> 3.4666667 | ... EI16: =EI15-EI17 -> 0
B17: Upgraded Units Leased | H17: =MIN(H15, MIN(H10,'Executive Summary'!$C$12*H12)-G19+H14) -> 0 | I17: =MIN(I15, MIN(I10,'Executive Summary'!$C$12*I12)-H19+I14) -> 3 | J17: =MIN(J15, MIN(J10,'Executive Summary'!$C$12*J12)-I19+J14) -> 5 | K17: =MIN(K15, MIN(K10,'Executive Summary'!$C$12*K12)-J19+K14) -> 3 | L17: =MIN(L15, MIN(L10,'Executive Summary'!$C$12*L12)-K19+L14) -> 5 | M17: =MIN(M15, MIN(M10,'Executive Summary'!$C$12*M12)-L19+M14) -> 3 | N17: =MIN(N15, MIN(N10,'Executive Summary'!$C$12*N12)-M19+N14) -> 5 | O17: =MIN(O15, MIN(O10,'Executive Summary'!$C$12*O12)-N19+O14) -> 3 | ... EI17: =MIN(EI15, MIN(EI10,'Executive Summary'!$C$12*EI12)-EH19+EI14) -> 6.4666667
B18: Occupied Non-Upgraded Units EOP | G18: =G12*'Executive Summary'!C12-G19 -> 77.6 | H18: =G18-H13+H16 -> 75.52 | I18: =H18-I13+I16 -> 72.52 | J18: =I18-J13+J16 -> 67.52 | K18: =J18-K13+K16 -> 64.52 | L18: =K18-L13+L16 -> 59.52 | M18: =L18-M13+M16 -> 56.52 | N18: =M18-N13+N16 -> 51.52 | O18: =N18-O13+O16 -> 48.52 | ... EI18: =EH18-EI13+EI16 -> 1.5099033e-14
B19: Occupied Upgraded Units EOP | G19: =G12*G10 -> 0 | H19: =G19-H14+H17 -> 0 | I19: =H19-I14+I17 -> 3 | J19: =I19-J14+J17 -> 8 | K19: =J19-K14+K17 -> 11 | L19: =K19-L14+L17 -> 16 | M19: =L19-M14+M17 -> 19 | N19: =M19-N14+N17 -> 24 | O19: =N19-O14+O17 -> 27 | ... EI19: =EH19-EI14+EI17 -> 75.52
B20: New Leases | H20: =((H16*('Unit Mix & Comparables'!$Q$55-'Unit Mix & Comparables'!$N$55)+(H17*'Unit Mix & Comparables'!$Q$55))/MAX(1,1+'Unit Mix & Comparables'!$D$51-('Unit Mix & Comparables'!$D$51*H4/'Renovation Plan'!$D$19)))*H7 -> 3411.2965 | I20: =((I16*('Unit Mix & Comparables'!$Q$55-'Unit Mix & Comparables'!$N$55)+(I17*'Unit Mix & Comparables'!$Q$55))/MAX(1,1+'Unit Mix & Comparables'!$D$51-('Unit Mix & Comparables'!$D$51*I4/'Renovation Plan'!$D$19)))*I7 -> 5181.7331 | J20: =((J16*('Unit Mix & Comparables'!$Q$55-'Unit Mix & Comparables'!$N$55)+(J17*'Unit Mix & Comparables'!$Q$55))/MAX(1,1+'Unit Mix & Comparables'!$D$51-('Unit Mix & Comparables'!$D$51*J4/'Renovation Plan'!$D$19)))*J7 -> 5284.739 | K20: =((K16*('Unit Mix & Comparables'!$Q$55-'Unit Mix & Comparables'!$N$55)+(K17*'Unit Mix & Comparables'!$Q$55))/MAX(1,1+'Unit Mix & Comparables'!$D$51-('Unit Mix & Comparables'!$D$51*K4/'Renovation Plan'!$D$19)))*K7 -> 5187.4174 | L20: =((L16*('Unit Mix & Comparables'!$Q$55-'Unit Mix & Comparables'!$N$55)+(L17*'Unit Mix & Comparables'!$Q$55))/MAX(1,1+'Unit Mix & Comparables'!$D$51-('Unit Mix & Comparables'!$D$51*L4/'Renovation Plan'!$D$19)))*L7 -> 5290.5363 | M20: =((M16*('Unit Mix & Comparables'!$Q$55-'Unit Mix & Comparables'!$N$55)+(M17*'Unit Mix & Comparables'!$Q$55))/MAX(1,1+'Unit Mix & Comparables'!$D$51-('Unit Mix & Comparables'!$D$51*M4/'Renovation Plan'!$D$19)))*M7 -> 5193.1079 | N20: =((N16*('Unit Mix & Comparables'!$Q$55-'Unit Mix & Comparables'!$N$55)+(N17*'Unit Mix & Comparables'!$Q$55))/MAX(1,1+'Unit Mix & Comparables'!$D$51-('Unit Mix & Comparables'!$D$51*N4/'Renovation Plan'!$D$19)))*N7 -> 5296.34 | O20: =((O16*('Unit Mix & Comparables'!$Q$55-'Unit Mix & Comparables'!$N$55)+(O17*'Unit Mix & Comparables'!$Q$55))/MAX(1,1+'Unit Mix & Comparables'!$D$51-('Unit Mix & Comparables'!$D$51*O4/'Renovation Plan'!$D$19)))*O7 -> 5198.8047 | ... EI20: =((EI16*('Unit Mix & Comparables'!$Q$55-'Unit Mix & Comparables'!$N$55)+(EI17*'Unit Mix & Comparables'!$Q$55))/MAX(1,1+'Unit Mix & Comparables'!$D$51-('Unit Mix & Comparables'!$D$51*EI4/'Renovation Plan'!$D$19)))*EI7 -> 7254.846
B21: Total Rent Roll | G21: ='Operating Inputs'!G10/12*G12 -> 57832.047 | H21: =G21-($G$21/12)+H20 -> 56424.006 | I21: =H21-($G$21/12)+I20 -> 56786.402 | J21: =I21-($G$21/12)+J20 -> 57251.804 | K21: =J21-($G$21/12)+K20 -> 57619.884 | L21: =K21-($G$21/12)+L20 -> 58091.083 | M21: =L21-($G$21/12)+M20 -> 58464.854 | N21: =M21-($G$21/12)+N20 -> 58941.856 | O21: =N21-($G$21/12)+O20 -> 59321.324 | ... S21: =R21-($G$21/12)+S20 -> 61068.816 | T21: =S21-H20+T20 -> 61320.007 | U21: =T21-I20+U20 -> 61551.836 | V21: =U21-J20+V20 -> 61695.15 | W21: =V21-K20+W20 -> 61950.316 | X21: =W21-L20+X20 -> 62116.932 | Y21: =X21-M20+Y20 -> 62395.585 | Z21: =Y21-N20+Z20 -> 62585.654 | AA21: =Z21-O20+AA20 -> 62887.944 | ... EI21: =EH21-DW20+EI20 -> 83618.627
B23: REVENUES
B24: Rental Income | EK24: 1 | EL24: 2 | EM24: 3 | EN24: 4 | EO24: 5 | EP24: 6 | EQ24: 7 | ER24: 8 | ES24: 9 | ET24: 10
B25: Market Rent | E25: =SUM(OFFSET(G25,0,0,1,'Executive Summary'!$I$13+1)) -> 4161766.9 | G25: 0 | H25: =H11*'Executive Summary'!$C$12 -> 62212.095 | I25: =I11*'Executive Summary'!$C$12 -> 62396.373 | J25: =J11*'Executive Summary'!$C$12 -> 62680.999 | K25: =K11*'Executive Summary'!$C$12 -> 62865.699 | L25: =L11*'Executive Summary'!$C$12 -> 63150.857 | M25: =M11*'Executive Summary'!$C$12 -> 63335.98 | N25: =N11*'Executive Summary'!$C$12 -> 63621.671 | O25: =O11*'Executive Summary'!$C$12 -> 63807.217 | ... EI25: =EI11*'Executive Summary'!$C$12 -> 89750.672 | EK25: =SUM(OFFSET($G25,0,EK$24*12-11,1,12)) -> 761762.48 | EL25: =SUM(OFFSET($G25,0,EL$24*12-11,1,12)) -> 807389.08 | EM25: =SUM(OFFSET($G25,0,EM$24*12-11,1,12)) -> 838789.78 | EN25: =SUM(OFFSET($G25,0,EN$24*12-11,1,12)) -> 863953.47 | EO25: =SUM(OFFSET($G25,0,EO$24*12-11,1,12)) -> 889872.07 | EP25: =SUM(OFFSET($G25,0,EP$24*12-11,1,12)) -> 916568.24 | EQ25: =SUM(OFFSET($G25,0,EQ$24*12-11,1,12)) -> 944065.28 | ER25: =SUM(OFFSET($G25,0,ER$24*12-11,1,12)) -> 972387.24 | ... ET25: =SUM(OFFSET($G25,0,ET$24*12-11,1,12)) -> 1031605.6
B26: Gain (Loss) to Lease | E26: =SUM(OFFSET(G26,0,0,1,'Executive Summary'!$I$13+1)) -> -62384.097 | G26: 0 | H26: =H21-(H12*H25) -> -2304.2116 | I26: =I21/I12-I25 -> -2241.2863 | J26: =J21/J12-J25 -> -2032.9021 | K26: =K21/K12-K25 -> -1827.6866 | L26: =L21/L12-L25 -> -1613.6932 | M26: =M21/M12-M25 -> -1402.8722 | N26: =N21/N12-N25 -> -1183.2638 | O26: =O21/O12-O25 -> -966.83133 | P26: =P21/P12-P25 -> -741.60187 | ... EI26: =EI21/EI12-EI25 -> -1171.6181 | EK26: =SUM(OFFSET($G26,0,EK$24*12-11,1,12)) -> -15183.619 | EL26: =SUM(OFFSET($G26,0,EL$24*12-11,1,12)) -> -12142.277 | EM26: =SUM(OFFSET($G26,0,EM$24*12-11,1,12)) -> -11523.975 | EN26: =SUM(OFFSET($G26,0,EN$24*12-11,1,12)) -> -11593.215 | EO26: =SUM(OFFSET($G26,0,EO$24*12-11,1,12)) -> -11941.011 | EP26: =SUM(OFFSET($G26,0,EP$24*12-11,1,12)) -> -12299.242 | EQ26: =SUM(OFFSET($G26,0,EQ$24*12-11,1,12)) -> -12668.219 | ER26: =SUM(OFFSET($G26,0,ER$24*12-11,1,12)) -> -13048.265 | ... ET26: =SUM(OFFSET($G26,0,ET$24*12-11,1,12)) -> -13842.905
B27: Gross Potential Rent | E27: =SUM(OFFSET(G27,0,0,1,'Executive Summary'!$I$13+1)) -> 4099382.8 | G27: =SUM(G25:G26) -> 0 | H27: =SUM(H25:H26) -> 59907.883 | I27: =SUM(I25:I26) -> 60155.087 | J27: =SUM(J25:J26) -> 60648.097 | K27: =SUM(K25:K26) -> 61038.012 | L27: =SUM(L25:L26) -> 61537.164 | M27: =SUM(M25:M26) -> 61933.108 | N27: =SUM(N25:N26) -> 62438.407 | ... EI27: =SUM(EI25:EI26) -> 88579.054 | EK27: =SUM(OFFSET($G27,0,EK$24*12-11,1,12)) -> 746578.86 | EL27: =SUM(OFFSET($G27,0,EL$24*12-11,1,12)) -> 795246.8 | EM27: =SUM(OFFSET($G27,0,EM$24*12-11,1,12)) -> 827265.8 | EN27: =SUM(OFFSET($G27,0,EN$24*12-11,1,12)) -> 852360.25 | EO27: =SUM(OFFSET($G27,0,EO$24*12-11,1,12)) -> 877931.06 | EP27: =SUM(OFFSET($G27,0,EP$24*12-11,1,12)) -> 904268.99 | EQ27: =SUM(OFFSET($G27,0,EQ$24*12-11,1,12)) -> 931397.06 | ER27: =SUM(OFFSET($G27,0,ER$24*12-11,1,12)) -> 959338.98 | ... ET27: =SUM(OFFSET($G27,0,ET$24*12-11,1,12)) -> 1017762.7
B28: Concessions | E28: =SUM(OFFSET(G28,0,0,1,'Executive Summary'!$I$13+1)) -> -12298.148 | G28: 0 | H28: ='Renovation Plan'!D10*H27 -> -179.72365 | I28: ='Renovation Plan'!E10*I27 -> -180.46526 | J28: ='Renovation Plan'!F10*J27 -> -181.94429 | K28: ='Renovation Plan'!G10*K27 -> -183.11404 | L28: ='Renovation Plan'!H10*L27 -> -184.61149 | M28: ='Renovation Plan'!I10*M27 -> -185.79932 | N28: ='Renovation Plan'!J10*N27 -> -187.31522 | O28: ='Renovation Plan'!K10*O27 -> -188.52116 | ... S28: ='Renovation Plan'!O10*S27 -> -194.07463 | T28: ='Renovation Plan'!$P$10*T27 -> -194.8729 | U28: ='Renovation Plan'!$P$10*U27 -> -195.60965 | V28: ='Renovation Plan'!$P$10*V27 -> -196.06509 | W28: ='Renovation Plan'!$P$10*W27 -> -196.876 | X28: ='Renovation Plan'!$P$10*X27 -> -197.4055 | Y28: ='Renovation Plan'!$P$10*Y27 -> -198.29105 | Z28: ='Renovation Plan'!$P$10*Z27 -> -198.89509 | AA28: ='Renovation Plan'!$P$10*AA27 -> -199.85575 | ... AE28: ='Renovation Plan'!$P$10*AE27 -> -203.43793 | AF28: ='Operating Inputs'!$P$11*AF27 -> -203.81485 | AG28: ='Operating Inputs'!$P$11*AG27 -> -204.36824 | AH28: ='Operating Inputs'!$P$11*AH27 -> -204.91937 | AI28: ='Operating Inputs'!$P$11*AI27 -> -205.46823 | AJ28: ='Operating Inputs'!$P$11*AJ27 -> -206.0148 | AK28: ='Operating Inputs'!$P$11*AK27 -> -206.55906 | AL28: ='Operating Inputs'!$P$11*AL27 -> -207.101 | AM28: ='Operating Inputs'!$P$11*AM27 -> -207.64061 | ... EI28: ='Operating Inputs'!$P$11*EI27 -> -265.73716 | EK28: =SUM(OFFSET($G28,0,EK$24*12-11,1,12)) -> -2239.7366 | EL28: =SUM(OFFSET($G28,0,EL$24*12-11,1,12)) -> -2385.7404 | EM28: =SUM(OFFSET($G28,0,EM$24*12-11,1,12)) -> -2481.7974 | EN28: =SUM(OFFSET($G28,0,EN$24*12-11,1,12)) -> -2557.0808 | EO28: =SUM(OFFSET($G28,0,EO$24*12-11,1,12)) -> -2633.7932 | EP28: =SUM(OFFSET($G28,0,EP$24*12-11,1,12)) -> -2712.807 | EQ28: =SUM(OFFSET($G28,0,EQ$24*12-11,1,12)) -> -2794.1912 | ER28: =SUM(OFFSET($G28,0,ER$24*12-11,1,12)) -> -2878.0169 | ... ET28: =SUM(OFFSET($G28,0,ET$24*12-11,1,12)) -> -3053.2882
B29: Vacancy | E29: =SUM(OFFSET(G29,0,0,1,'Executive Summary'!$I$13+1)) -> -229694.47 | G29: 0 | H29: =H21-H27 -> -3483.8773 | I29: =I21-I27 -> -3368.6849 | J29: =J21-J27 -> -3396.2934 | K29: =K21-K27 -> -3418.1287 | L29: =L21-L27 -> -3446.0812 | M29: =M21-M27 -> -3468.254 | N29: =N21-N27 -> -3496.5508 | O29: =O21-O27 -> -3519.0616 | ... EI29: =EI21-EI27 -> -4960.427 | EK29: =SUM(OFFSET($G29,0,EK$24*12-11,1,12)) -> -41937.452 | EL29: =SUM(OFFSET($G29,0,EL$24*12-11,1,12)) -> -44533.821 | EM29: =SUM(OFFSET($G29,0,EM$24*12-11,1,12)) -> -46326.885 | EN29: =SUM(OFFSET($G29,0,EN$24*12-11,1,12)) -> -47732.174 | EO29: =SUM(OFFSET($G29,0,EO$24*12-11,1,12)) -> -49164.139 | EP29: =SUM(OFFSET($G29,0,EP$24*12-11,1,12)) -> -50639.064 | EQ29: =SUM(OFFSET($G29,0,EQ$24*12-11,1,12)) -> -52158.236 | ER29: =SUM(OFFSET($G29,0,ER$24*12-11,1,12)) -> -53722.983 | ... ET29: =SUM(OFFSET($G29,0,ET$24*12-11,1,12)) -> -56994.712
B30: Bad Debt | E30: =SUM(OFFSET(G30,0,0,1,'Executive Summary'!$I$13+1)) -> -12298.148 | G30: 0 | H30: ='Renovation Plan'!$D$12*H27 -> -179.72365 | I30: ='Renovation Plan'!$D$12*I27 -> -180.46526 | J30: ='Renovation Plan'!$D$12*J27 -> -181.94429 | K30: ='Renovation Plan'!$D$12*K27 -> -183.11404 | L30: ='Renovation Plan'!$D$12*L27 -> -184.61149 | M30: ='Renovation Plan'!$D$12*M27 -> -185.79932 | N30: ='Renovation Plan'!$D$12*N27 -> -187.31522 | O30: ='Renovation Plan'!$D$12*O27 -> -188.52116 | ... S30: ='Renovation Plan'!$D$12*S27 -> -194.07463 | T30: ='Renovation Plan'!$P$12*T27 -> -194.8729 | U30: ='Renovation Plan'!$P$12*U27 -> -195.60965 | V30: ='Renovation Plan'!$P$12*V27 -> -196.06509 | W30: ='Renovation Plan'!$P$12*W27 -> -196.876 | X30: ='Renovation Plan'!$P$12*X27 -> -197.4055 | Y30: ='Renovation Plan'!$P$12*Y27 -> -198.29105 | Z30: ='Renovation Plan'!$P$12*Z27 -> -198.89509 | AA30: ='Renovation Plan'!$P$12*AA27 -> -199.85575 | ... AE30: ='Renovation Plan'!$P$12*AE27 -> -203.43793 | AF30: ='Operating Inputs'!$P$13*'Cash Flow - Monthly'!AF27 -> -203.81485 | AG30: ='Operating Inputs'!$P$13*'Cash Flow - Monthly'!AG27 -> -204.36824 | AH30: ='Operating Inputs'!$P$13*'Cash Flow - Monthly'!AH27 -> -204.91937 | AI30: ='Operating Inputs'!$P$13*'Cash Flow - Monthly'!AI27 -> -205.46823 | AJ30: ='Operating Inputs'!$P$13*'Cash Flow - Monthly'!AJ27 -> -206.0148 | AK30: ='Operating Inputs'!$P$13*'Cash Flow - Monthly'!AK27 -> -206.55906 | AL30: ='Operating Inputs'!$P$13*'Cash Flow - Monthly'!AL27 -> -207.101 | AM30: ='Operating Inputs'!$P$13*'Cash Flow - Monthly'!AM27 -> -207.64061 | ... EI30: ='Operating Inputs'!$P$13*'Cash Flow - Monthly'!EI27 -> -265.73716 | EK30: =SUM(OFFSET($G30,0,EK$24*12-11,1,12)) -> -2239.7366 | EL30: =SUM(OFFSET($G30,0,EL$24*12-11,1,12)) -> -2385.7404 | EM30: =SUM(OFFSET($G30,0,EM$24*12-11,1,12)) -> -2481.7974 | EN30: =SUM(OFFSET($G30,0,EN$24*12-11,1,12)) -> -2557.0808 | EO30: =SUM(OFFSET($G30,0,EO$24*12-11,1,12)) -> -2633.7932 | EP30: =SUM(OFFSET($G30,0,EP$24*12-11,1,12)) -> -2712.807 | EQ30: =SUM(OFFSET($G30,0,EQ$24*12-11,1,12)) -> -2794.1912 | ER30: =SUM(OFFSET($G30,0,ER$24*12-11,1,12)) -> -2878.0169 | ... ET30: =SUM(OFFSET($G30,0,ET$24*12-11,1,12)) -> -3053.2882
B31: Net Rental Income | E31: =SUM(OFFSET(G31,0,0,1,'Executive Summary'!$I$13+1)) -> 3845092 | G31: =SUM(G27:G30) -> 0 | H31: =SUM(H27:H30) -> 56064.559 | I31: =SUM(I27:I30) -> 56425.471 | J31: =SUM(J27:J30) -> 56887.915 | K31: =SUM(K27:K30) -> 57253.656 | L31: =SUM(L27:L30) -> 57721.86 | M31: =SUM(M27:M30) -> 58093.255 | N31: =SUM(N27:N30) -> 58567.226 | ... EI31: =SUM(EI27:EI30) -> 83087.152 | EK31: =SUM(OFFSET($G31,0,EK$24*12-11,1,12)) -> 700161.93 | EL31: =SUM(OFFSET($G31,0,EL$24*12-11,1,12)) -> 745941.5 | EM31: =SUM(OFFSET($G31,0,EM$24*12-11,1,12)) -> 775975.32 | EN31: =SUM(OFFSET($G31,0,EN$24*12-11,1,12)) -> 799513.92 | EO31: =SUM(OFFSET($G31,0,EO$24*12-11,1,12)) -> 823499.34 | EP31: =SUM(OFFSET($G31,0,EP$24*12-11,1,12)) -> 848204.32 | EQ31: =SUM(OFFSET($G31,0,EQ$24*12-11,1,12)) -> 873650.45 | ER31: =SUM(OFFSET($G31,0,ER$24*12-11,1,12)) -> 899859.96 | ... ET31: =SUM(OFFSET($G31,0,ET$24*12-11,1,12)) -> 954661.43
B32: Other Income
B33: Utility | E33: =SUM(OFFSET(G33,0,0,1,'Executive Summary'!$I$13+1)) -> 213873.52 | G33: 0 | H33: ='Operating Inputs'!$P$16*H45*H12*(1+'Renovation Plan'!D12) -> 3393.8007 | I33: ='Operating Inputs'!$P$16*I45*I12*(1+'Renovation Plan'!E12) -> 3399.4058 | J33: ='Operating Inputs'!$P$16*J45*J12*(1+'Renovation Plan'!F12) -> 3405.0202 | K33: ='Operating Inputs'!$P$16*K45*K12*(1+'Renovation Plan'!G12) -> 3410.6439 | L33: ='Operating Inputs'!$P$16*L45*L12*(1+'Renovation Plan'!H12) -> 3416.2769 | M33: ='Operating Inputs'!$P$16*M45*M12*(1+'Renovation Plan'!I12) -> 3421.9191 | N33: ='Operating Inputs'!$P$16*N45*N12*(1+'Renovation Plan'!J12) -> 3427.5707 | O33: ='Operating Inputs'!$P$16*O45*O12*(1+'Renovation Plan'!K12) -> 3433.2316 | ... S33: ='Operating Inputs'!$P$16*S45*S12*(1+'Renovation Plan'!O12) -> 3455.9689 | T33: ='Operating Inputs'!$P$16*T45*T12*(1+'Operating Inputs'!$P$13) -> 3461.6767 | U33: ='Operating Inputs'!$P$16*U45*U12*(1+'Operating Inputs'!$P$13) -> 3467.394 | V33: ='Operating Inputs'!$P$16*V45*V12*(1+'Operating Inputs'!$P$13) -> 3473.1206 | W33: ='Operating Inputs'!$P$16*W45*W12*(1+'Operating Inputs'!$P$13) -> 3478.8568 | X33: ='Operating Inputs'!$P$16*X45*X12*(1+'Operating Inputs'!$P$13) -> 3484.6024 | Y33: ='Operating Inputs'!$P$16*Y45*Y12*(1+'Operating Inputs'!$P$13) -> 3490.3575 | Z33: ='Operating Inputs'!$P$16*Z45*Z12*(1+'Operating Inputs'!$P$13) -> 3496.1221 | AA33: ='Operating Inputs'!$P$16*AA45*AA12*(1+'Operating Inputs'!$P$13) -> 3501.8962 | ... EI33: ='Operating Inputs'!$P$16*EI45*EI12*(1+'Operating Inputs'!$P$13) -> 4212.8068 | EK33: =SUM(OFFSET($G33,0,EK$24*12-11,1,12)) -> 41097.592 | EL33: =SUM(OFFSET($G33,0,EL$24*12-11,1,12)) -> 41919.543 | EM33: =SUM(OFFSET($G33,0,EM$24*12-11,1,12)) -> 42757.934 | EN33: =SUM(OFFSET($G33,0,EN$24*12-11,1,12)) -> 43613.093 | EO33: =SUM(OFFSET($G33,0,EO$24*12-11,1,12)) -> 44485.355 | EP33: =SUM(OFFSET($G33,0,EP$24*12-11,1,12)) -> 45375.062 | EQ33: =SUM(OFFSET($G33,0,EQ$24*12-11,1,12)) -> 46282.563 | ER33: =SUM(OFFSET($G33,0,ER$24*12-11,1,12)) -> 47208.214 | ... ET33: =SUM(OFFSET($G33,0,ET$24*12-11,1,12)) -> 49115.426
B34: Laundry/Cable | E34: =SUM(OFFSET(G34,0,0,1,'Executive Summary'!$I$13+1)) -> 27724.345 | G34: 0 | H34: ='Operating Inputs'!$P$17/12*H8*'Executive Summary'!$C$12*H12*(1+'Renovation Plan'!D12) -> 439.93713 | I34: ='Operating Inputs'!$P$17/12*I8*'Executive Summary'!$C$12*I12*(1+'Renovation Plan'!E12) -> 440.66372 | J34: ='Operating Inputs'!$P$17/12*J8*'Executive Summary'!$C$12*J12*(1+'Renovation Plan'!F12) -> 441.39151 | K34: ='Operating Inputs'!$P$17/12*K8*'Executive Summary'!$C$12*K12*(1+'Renovation Plan'!G12) -> 442.12051 | L34: ='Operating Inputs'!$P$17/12*L8*'Executive Summary'!$C$12*L12*(1+'Renovation Plan'!H12) -> 442.8507 | M34: ='Operating Inputs'!$P$17/12*M8*'Executive Summary'!$C$12*M12*(1+'Renovation Plan'!I12) -> 443.58211 | N34: ='Operating Inputs'!$P$17/12*N8*'Executive Summary'!$C$12*N12*(1+'Renovation Plan'!J12) -> 444.31472 | O34: ='Operating Inputs'!$P$17/12*O8*'Executive Summary'!$C$12*O12*(1+'Renovation Plan'!K12) -> 445.04854 | ... S34: ='Operating Inputs'!$P$17/12*S8*'Executive Summary'!$C$12*S12*(1+'Renovation Plan'!O12) -> 447.99597 | T34: ='Operating Inputs'!$P$17/12*T8*'Executive Summary'!$C$12*T12*(1+'Operating Inputs'!$P$13) -> 448.73587 | U34: ='Operating Inputs'!$P$17/12*U8*'Executive Summary'!$C$12*U12*(1+'Operating Inputs'!$P$13) -> 449.47699 | V34: ='Operating Inputs'!$P$17/12*V8*'Executive Summary'!$C$12*V12*(1+'Operating Inputs'!$P$13) -> 450.21934 | W34: ='Operating Inputs'!$P$17/12*W8*'Executive Summary'!$C$12*W12*(1+'Operating Inputs'!$P$13) -> 450.96292 | X34: ='Operating Inputs'!$P$17/12*X8*'Executive Summary'!$C$12*X12*(1+'Operating Inputs'!$P$13) -> 451.70772 | Y34: ='Operating Inputs'!$P$17/12*Y8*'Executive Summary'!$C$12*Y12*(1+'Operating Inputs'!$P$13) -> 452.45375 | Z34: ='Operating Inputs'!$P$17/12*Z8*'Executive Summary'!$C$12*Z12*(1+'Operating Inputs'!$P$13) -> 453.20101 | AA34: ='Operating Inputs'!$P$17/12*AA8*'Executive Summary'!$C$12*AA12*(1+'Operating Inputs'!$P$13) -> 453.94951 | ... EI34: ='Operating Inputs'!$P$17/12*EI8*'Executive Summary'!$C$12*EI12*(1+'Operating Inputs'!$P$13) -> 546.10459 | EK34: =SUM(OFFSET($G34,0,EK$24*12-11,1,12)) -> 5327.4656 | EL34: =SUM(OFFSET($G34,0,EL$24*12-11,1,12)) -> 5434.0149 | EM34: =SUM(OFFSET($G34,0,EM$24*12-11,1,12)) -> 5542.6952 | EN34: =SUM(OFFSET($G34,0,EN$24*12-11,1,12)) -> 5653.5491 | EO34: =SUM(OFFSET($G34,0,EO$24*12-11,1,12)) -> 5766.6201 | EP34: =SUM(OFFSET($G34,0,EP$24*12-11,1,12)) -> 5881.9525 | EQ34: =SUM(OFFSET($G34,0,EQ$24*12-11,1,12)) -> 5999.5915 | ER34: =SUM(OFFSET($G34,0,ER$24*12-11,1,12)) -> 6119.5834 | ... ET34: =SUM(OFFSET($G34,0,ET$24*12-11,1,12)) -> 6366.8145
B35: Other | E35: =SUM(OFFSET(G35,0,0,1,'Executive Summary'!$I$13+1)) -> 247545.64 | G35: 0 | H35: ='Operating Inputs'!$P$18/12*H8*'Executive Summary'!$C$12*H12*(1+'Renovation Plan'!D12) -> 3928.0101 | I35: ='Operating Inputs'!$P$18/12*I8*'Executive Summary'!$C$12*I12*(1+'Renovation Plan'!E12) -> 3934.4975 | J35: ='Operating Inputs'!$P$18/12*J8*'Executive Summary'!$C$12*J12*(1+'Renovation Plan'!F12) -> 3940.9956 | K35: ='Operating Inputs'!$P$18/12*K8*'Executive Summary'!$C$12*K12*(1+'Renovation Plan'!G12) -> 3947.5045 | L35: ='Operating Inputs'!$P$18/12*L8*'Executive Summary'!$C$12*L12*(1+'Renovation Plan'!H12) -> 3954.0241 | M35: ='Operating Inputs'!$P$18/12*M8*'Executive Summary'!$C$12*M12*(1+'Renovation Plan'!I12) -> 3960.5545 | N35: ='Operating Inputs'!$P$18/12*N8*'Executive Summary'!$C$12*N12*(1+'Renovation Plan'!J12) -> 3967.0957 | O35: ='Operating Inputs'!$P$18/12*O8*'Executive Summary'!$C$12*O12*(1+'Renovation Plan'!K12) -> 3973.6477 | ... S35: ='Operating Inputs'!$P$18/12*S8*'Executive Summary'!$C$12*S12*(1+'Renovation Plan'!O12) -> 3999.964 | T35: ='Operating Inputs'!$P$18/12*T8*'Executive Summary'!$C$12*T12*(1+'Operating Inputs'!$P$13) -> 4006.5703 | U35: ='Operating Inputs'!$P$18/12*U8*'Executive Summary'!$C$12*U12*(1+'Operating Inputs'!$P$13) -> 4013.1874 | V35: ='Operating Inputs'!$P$18/12*V8*'Executive Summary'!$C$12*V12*(1+'Operating Inputs'!$P$13) -> 4019.8155 | W35: ='Operating Inputs'!$P$18/12*W8*'Executive Summary'!$C$12*W12*(1+'Operating Inputs'!$P$13) -> 4026.4546 | X35: ='Operating Inputs'!$P$18/12*X8*'Executive Summary'!$C$12*X12*(1+'Operating Inputs'!$P$13) -> 4033.1046 | Y35: ='Operating Inputs'!$P$18/12*Y8*'Executive Summary'!$C$12*Y12*(1+'Operating Inputs'!$P$13) -> 4039.7656 | Z35: ='Operating Inputs'!$P$18/12*Z8*'Executive Summary'!$C$12*Z12*(1+'Operating Inputs'!$P$13) -> 4046.4376 | AA35: ='Operating Inputs'!$P$18/12*AA8*'Executive Summary'!$C$12*AA12*(1+'Operating Inputs'!$P$13) -> 4053.1206 | ... AN35: ='Operating Inputs'!$P$18/12*AN8*'Executive Summary'!$C$12*AN12*(1+'Operating Inputs'!$P$13) -> 4141.011 | AO35: ='Operating Inputs'!$P$18/12*AP8*'Executive Summary'!$C$12*AP12*(1+'Operating Inputs'!$P$13) -> 4154.7007 | AP35: ='Operating Inputs'!$P$18/12*AP8*'Executive Summary'!$C$12*AP12*(1+'Operating Inputs'!$P$13) -> 4154.7007 | AQ35: ='Operating Inputs'!$P$18/12*AQ8*'Executive Summary'!$C$12*AQ12*(1+'Operating Inputs'!$P$13) -> 4161.5625 | AR35: ='Operating Inputs'!$P$18/12*AR8*'Executive Summary'!$C$12*AR12*(1+'Operating Inputs'!$P$13) -> 4168.4357 | AS35: ='Operating Inputs'!$P$18/12*AS8*'Executive Summary'!$C$12*AS12*(1+'Operating Inputs'!$P$13) -> 4175.3202 | AT35: ='Operating Inputs'!$P$18/12*AT8*'Executive Summary'!$C$12*AT12*(1+'Operating Inputs'!$P$13) -> 4182.2161 | AU35: ='Operating Inputs'!$P$18/12*AU8*'Executive Summary'!$C$12*AU12*(1+'Operating Inputs'!$P$13) -> 4189.1234 | AV35: ='Operating Inputs'!$P$18/12*AV8*'Executive Summary'!$C$12*AV12*(1+'Operating Inputs'!$P$13) -> 4196.042 | AW35: ='Operating Inputs'!$P$18/12*AW8*'Executive Summary'!$C$12*AW12*(1+'Operating Inputs'!$P$13) -> 4202.9721 | ... BS35: ='Operating Inputs'!$P$18/12*BS8*'Executive Summary'!$C$12*BS12*(1+'Operating Inputs'!$P$13) -> 4358.3639 | BT35: ='Operating Inputs'!$P$18/12*BT8*'Executive Summary'!$C$12*BT12*(1+'Operating Inputs'!$P$13)+5694 -> 10059.562 | BU35: ='Operating Inputs'!$P$18/12*BU8*'Executive Summary'!$C$12*BU12*(1+'Operating Inputs'!$P$13)+5694 -> 10066.772 | BV35: ='Operating Inputs'!$P$18/12*BV8*'Executive Summary'!$C$12*BV12*(1+'Operating Inputs'!$P$13)+5694 -> 10073.994 | BW35: ='Operating Inputs'!$P$18/12*BW8*'Executive Summary'!$C$12*BW12*(1+'Operating Inputs'!$P$13)+5694 -> 10081.228 | BX35: ='Operating Inputs'!$P$18/12*BX8*'Executive Summary'!$C$12*BX12*(1+'Operating Inputs'!$P$13)+5694 -> 10088.474 | BY35: ='Operating Inputs'!$P$18/12*BY8*'Executive Summary'!$C$12*BY12*(1+'Operating Inputs'!$P$13)+5694 -> 10095.732 | BZ35: ='Operating Inputs'!$P$18/12*BZ8*'Executive Summary'!$C$12*BZ12*(1+'Operating Inputs'!$P$13)+5694 -> 10103.002 | CA35: ='Operating Inputs'!$P$18/12*CA8*'Executive Summary'!$C$12*CA12*(1+'Operating Inputs'!$P$13)+5694 -> 10110.283 | CB35: ='Operating Inputs'!$P$18/12*CB8*'Executive Summary'!$C$12*CB12*(1+'Operating Inputs'!$P$13) -> 4423.5773 | CC35: ='Operating Inputs'!$P$18/12*CC8*'Executive Summary'!$C$12*CC12*(1+'Operating Inputs'!$P$13) -> 4430.8832 | CD35: ='Operating Inputs'!$P$18/12*CD8*'Executive Summary'!$C$12*CD12*(1+'Operating Inputs'!$P$13) -> 4438.2012 | CE35: ='Operating Inputs'!$P$18/12*CE8*'Executive Summary'!$C$12*CE12*(1+'Operating Inputs'!$P$13) -> 4445.5312 | CF35: ='Operating Inputs'!$P$18/12*CF8*'Executive Summary'!$C$12*CF12*(1+'Operating Inputs'!$P$13) -> 4452.8734 | CG35: ='Operating Inputs'!$P$18/12*CG8*'Executive Summary'!$C$12*CG12*(1+'Operating Inputs'!$P$13) -> 4460.2277 | CH35: ='Operating Inputs'!$P$18/12*CH8*'Executive Summary'!$C$12*CH12*(1+'Operating Inputs'!$P$13) -> 4467.5941 | CI35: ='Operating Inputs'!$P$18/12*CI8*'Executive Summary'!$C$12*CI12*(1+'Operating Inputs'!$P$13) -> 4474.9727 | ... EI35: ='Operating Inputs'!$P$18/12*EI8*'Executive Summary'!$C$12*EI12*(1+'Operating Inputs'!$P$13) -> 4875.9338 | EK35: =SUM(OFFSET($G35,0,EK$24*12-11,1,12)) -> 47566.657 | EL35: =SUM(OFFSET($G35,0,EL$24*12-11,1,12)) -> 48517.99 | EM35: =SUM(OFFSET($G35,0,EM$24*12-11,1,12)) -> 49495.2 | EN35: =SUM(OFFSET($G35,0,EN$24*12-11,1,12)) -> 50478.117 | EO35: =SUM(OFFSET($G35,0,EO$24*12-11,1,12)) -> 51487.679 | EP35: =SUM(OFFSET($G35,0,EP$24*12-11,1,12)) -> 98069.433 | EQ35: =SUM(OFFSET($G35,0,EQ$24*12-11,1,12)) -> 53567.782 | ER35: =SUM(OFFSET($G35,0,ER$24*12-11,1,12)) -> 54639.137 | ... ET35: =SUM(OFFSET($G35,0,ET$24*12-11,1,12)) -> 56846.558
B36: Total Other Income | E36: =SUM(OFFSET(G36,0,0,1,'Executive Summary'!$I$13+1)) -> 489143.51 | G36: =SUM(G33:G35) -> 0 | H36: =SUM(H33:H35) -> 7761.7479 | I36: =SUM(I33:I35) -> 7774.567 | J36: =SUM(J33:J35) -> 7787.4074 | K36: =SUM(K33:K35) -> 7800.2689 | L36: =SUM(L33:L35) -> 7813.1517 | M36: =SUM(M33:M35) -> 7826.0557 | N36: =SUM(N33:N35) -> 7838.9811 | ... EI36: =SUM(EI33:EI35) -> 9634.8452 | EK36: =SUM(OFFSET($G36,0,EK$24*12-11,1,12)) -> 93991.714 | EL36: =SUM(OFFSET($G36,0,EL$24*12-11,1,12)) -> 95871.549 | EM36: =SUM(OFFSET($G36,0,EM$24*12-11,1,12)) -> 97795.83 | EN36: =SUM(OFFSET($G36,0,EN$24*12-11,1,12)) -> 99744.759 | EO36: =SUM(OFFSET($G36,0,EO$24*12-11,1,12)) -> 101739.65 | EP36: =SUM(OFFSET($G36,0,EP$24*12-11,1,12)) -> 149326.45 | EQ36: =SUM(OFFSET($G36,0,EQ$24*12-11,1,12)) -> 105849.94 | ER36: =SUM(OFFSET($G36,0,ER$24*12-11,1,12)) -> 107966.94 | ... ET36: =SUM(OFFSET($G36,0,ET$24*12-11,1,12)) -> 112328.8
B37: TOTAL REVENUES | E37: =SUM(OFFSET(G37,0,0,1,'Executive Summary'!$I$13+1)) -> 4334235.5 | G37: =SUM(G31,G36) -> 0 | H37: =SUM(H31,H36) -> 63826.307 | I37: =SUM(I31,I36) -> 64200.038 | J37: =SUM(J31,J36) -> 64675.322 | K37: =SUM(K31,K36) -> 65053.925 | L37: =SUM(L31,L36) -> 65535.012 | M37: =SUM(M31,M36) -> 65919.311 | N37: =SUM(N31,N36) -> 66406.207 | ... EI37: =SUM(EI31,EI36) -> 92721.997 | EK37: =SUM(OFFSET($G37,0,EK$24*12-11,1,12)) -> 794153.65 | EL37: =SUM(OFFSET($G37,0,EL$24*12-11,1,12)) -> 841813.05 | EM37: =SUM(OFFSET($G37,0,EM$24*12-11,1,12)) -> 873771.15 | EN37: =SUM(OFFSET($G37,0,EN$24*12-11,1,12)) -> 899258.68 | EO37: =SUM(OFFSET($G37,0,EO$24*12-11,1,12)) -> 925238.99 | EP37: =SUM(OFFSET($G37,0,EP$24*12-11,1,12)) -> 997530.76 | EQ37: =SUM(OFFSET($G37,0,EQ$24*12-11,1,12)) -> 979500.38 | ER37: =SUM(OFFSET($G37,0,ER$24*12-11,1,12)) -> 1007826.9 | ... ET37: =SUM(OFFSET($G37,0,ET$24*12-11,1,12)) -> 1066990.2
B39: EXPENSES
B40: Controllable
B41: Payroll | E41: =SUM(OFFSET(G41,0,0,1,'Executive Summary'!$I$13+1)) -> 462901.71 | G41: 0 | H41: ='Operating Inputs'!$P24/12*'Cash Flow - Monthly'!H$8*'Executive Summary'!$C$12 -> 7345.4449 | I41: ='Operating Inputs'!$P24/12*'Cash Flow - Monthly'!I$8*'Executive Summary'!$C$12 -> 7357.5765 | J41: ='Operating Inputs'!$P24/12*'Cash Flow - Monthly'!J$8*'Executive Summary'!$C$12 -> 7369.7282 | K41: ='Operating Inputs'!$P24/12*'Cash Flow - Monthly'!K$8*'Executive Summary'!$C$12 -> 7381.8999 | L41: ='Operating Inputs'!$P24/12*'Cash Flow - Monthly'!L$8*'Executive Summary'!$C$12 -> 7394.0917 | M41: ='Operating Inputs'!$P24/12*'Cash Flow - Monthly'!M$8*'Executive Summary'!$C$12 -> 7406.3036 | N41: ='Operating Inputs'!$P24/12*'Cash Flow - Monthly'!N$8*'Executive Summary'!$C$12 -> 7418.5357 | O41: ='Operating Inputs'!$P24/12*'Cash Flow - Monthly'!O$8*'Executive Summary'!$C$12 -> 7430.788 | ... EI41: ='Operating Inputs'!$P24/12*'Cash Flow - Monthly'!EI$8*'Executive Summary'!$C$12 -> 9118.0783 | EK41: =SUM(OFFSET($G41,0,EK$24*12-11,1,12)) -> 88950.449 | EL41: =SUM(OFFSET($G41,0,EL$24*12-11,1,12)) -> 90729.458 | EM41: =SUM(OFFSET($G41,0,EM$24*12-11,1,12)) -> 92544.047 | EN41: =SUM(OFFSET($G41,0,EN$24*12-11,1,12)) -> 94394.928 | EO41: =SUM(OFFSET($G41,0,EO$24*12-11,1,12)) -> 96282.827 | EP41: =SUM(OFFSET($G41,0,EP$24*12-11,1,12)) -> 98208.483 | EQ41: =SUM(OFFSET($G41,0,EQ$24*12-11,1,12)) -> 100172.65 | ER41: =SUM(OFFSET($G41,0,ER$24*12-11,1,12)) -> 102176.11 | ... ET41: =SUM(OFFSET($G41,0,ET$24*12-11,1,12)) -> 106304.02
B42: Operations & Maintenance | E42: =SUM(OFFSET(G42,0,0,1,'Executive Summary'!$I$13+1)) -> 315614.8 | G42: 0 | H42: ='Operating Inputs'!$P25/12*'Cash Flow - Monthly'!H$8*'Executive Summary'!$C$12 -> 5008.2579 | I42: ='Operating Inputs'!$P25/12*'Cash Flow - Monthly'!I$8*'Executive Summary'!$C$12 -> 5016.5295 | J42: ='Operating Inputs'!$P25/12*'Cash Flow - Monthly'!J$8*'Executive Summary'!$C$12 -> 5024.8147 | K42: ='Operating Inputs'!$P25/12*'Cash Flow - Monthly'!K$8*'Executive Summary'!$C$12 -> 5033.1135 | L42: ='Operating Inputs'!$P25/12*'Cash Flow - Monthly'!L$8*'Executive Summary'!$C$12 -> 5041.4261 | M42: ='Operating Inputs'!$P25/12*'Cash Flow - Monthly'!M$8*'Executive Summary'!$C$12 -> 5049.7525 | N42: ='Operating Inputs'!$P25/12*'Cash Flow - Monthly'!N$8*'Executive Summary'!$C$12 -> 5058.0925 | O42: ='Operating Inputs'!$P25/12*'Cash Flow - Monthly'!O$8*'Executive Summary'!$C$12 -> 5066.4464 | ... EI42: ='Operating Inputs'!$P25/12*'Cash Flow - Monthly'!EI$8*'Executive Summary'!$C$12 -> 6216.8715 | EK42: =SUM(OFFSET($G42,0,EK$24*12-11,1,12)) -> 60648.034 | EL42: =SUM(OFFSET($G42,0,EL$24*12-11,1,12)) -> 61860.994 | EM42: =SUM(OFFSET($G42,0,EM$24*12-11,1,12)) -> 63098.214 | EN42: =SUM(OFFSET($G42,0,EN$24*12-11,1,12)) -> 64360.178 | EO42: =SUM(OFFSET($G42,0,EO$24*12-11,1,12)) -> 65647.382 | EP42: =SUM(OFFSET($G42,0,EP$24*12-11,1,12)) -> 66960.33 | EQ42: =SUM(OFFSET($G42,0,EQ$24*12-11,1,12)) -> 68299.536 | ER42: =SUM(OFFSET($G42,0,ER$24*12-11,1,12)) -> 69665.527 | ... ET42: =SUM(OFFSET($G42,0,ET$24*12-11,1,12)) -> 72480.014
B43: Marketing | E43: =SUM(OFFSET(G43,0,0,1,'Executive Summary'!$I$13+1)) -> 73643.454 | G43: 0 | H43: ='Operating Inputs'!$P26/12*'Cash Flow - Monthly'!H$8*'Executive Summary'!$C$12 -> 1168.5935 | I43: ='Operating Inputs'!$P26/12*'Cash Flow - Monthly'!I$8*'Executive Summary'!$C$12 -> 1170.5235 | J43: ='Operating Inputs'!$P26/12*'Cash Flow - Monthly'!J$8*'Executive Summary'!$C$12 -> 1172.4568 | K43: ='Operating Inputs'!$P26/12*'Cash Flow - Monthly'!K$8*'Executive Summary'!$C$12 -> 1174.3932 | L43: ='Operating Inputs'!$P26/12*'Cash Flow - Monthly'!L$8*'Executive Summary'!$C$12 -> 1176.3328 | M43: ='Operating Inputs'!$P26/12*'Cash Flow - Monthly'!M$8*'Executive Summary'!$C$12 -> 1178.2756 | N43: ='Operating Inputs'!$P26/12*'Cash Flow - Monthly'!N$8*'Executive Summary'!$C$12 -> 1180.2216 | O43: ='Operating Inputs'!$P26/12*'Cash Flow - Monthly'!O$8*'Executive Summary'!$C$12 -> 1182.1708 | ... EI43: ='Operating Inputs'!$P26/12*'Cash Flow - Monthly'!EI$8*'Executive Summary'!$C$12 -> 1450.6034 | EK43: =SUM(OFFSET($G43,0,EK$24*12-11,1,12)) -> 14151.208 | EL43: =SUM(OFFSET($G43,0,EL$24*12-11,1,12)) -> 14434.232 | EM43: =SUM(OFFSET($G43,0,EM$24*12-11,1,12)) -> 14722.917 | EN43: =SUM(OFFSET($G43,0,EN$24*12-11,1,12)) -> 15017.375 | EO43: =SUM(OFFSET($G43,0,EO$24*12-11,1,12)) -> 15317.722 | EP43: =SUM(OFFSET($G43,0,EP$24*12-11,1,12)) -> 15624.077 | EQ43: =SUM(OFFSET($G43,0,EQ$24*12-11,1,12)) -> 15936.558 | ER43: =SUM(OFFSET($G43,0,ER$24*12-11,1,12)) -> 16255.29 | ... ET43: =SUM(OFFSET($G43,0,ET$24*12-11,1,12)) -> 16912.003
B44: General & Administrative | E44: =SUM(OFFSET(G44,0,0,1,'Executive Summary'!$I$13+1)) -> 126245.92 | G44: 0 | H44: ='Operating Inputs'!$P27/12*'Cash Flow - Monthly'!H$8*'Executive Summary'!$C$12 -> 2003.3032 | I44: ='Operating Inputs'!$P27/12*'Cash Flow - Monthly'!I$8*'Executive Summary'!$C$12 -> 2006.6118 | J44: ='Operating Inputs'!$P27/12*'Cash Flow - Monthly'!J$8*'Executive Summary'!$C$12 -> 2009.9259 | K44: ='Operating Inputs'!$P27/12*'Cash Flow - Monthly'!K$8*'Executive Summary'!$C$12 -> 2013.2454 | L44: ='Operating Inputs'!$P27/12*'Cash Flow - Monthly'!L$8*'Executive Summary'!$C$12 -> 2016.5705 | M44: ='Operating Inputs'!$P27/12*'Cash Flow - Monthly'!M$8*'Executive Summary'!$C$12 -> 2019.901 | N44: ='Operating Inputs'!$P27/12*'Cash Flow - Monthly'!N$8*'Executive Summary'!$C$12 -> 2023.237 | O44: ='Operating Inputs'!$P27/12*'Cash Flow - Monthly'!O$8*'Executive Summary'!$C$12 -> 2026.5786 | ... EI44: ='Operating Inputs'!$P27/12*'Cash Flow - Monthly'!EI$8*'Executive Summary'!$C$12 -> 2486.7486 | EK44: =SUM(OFFSET($G44,0,EK$24*12-11,1,12)) -> 24259.213 | EL44: =SUM(OFFSET($G44,0,EL$24*12-11,1,12)) -> 24744.398 | EM44: =SUM(OFFSET($G44,0,EM$24*12-11,1,12)) -> 25239.286 | EN44: =SUM(OFFSET($G44,0,EN$24*12-11,1,12)) -> 25744.071 | EO44: =SUM(OFFSET($G44,0,EO$24*12-11,1,12)) -> 26258.953 | EP44: =SUM(OFFSET($G44,0,EP$24*12-11,1,12)) -> 26784.132 | EQ44: =SUM(OFFSET($G44,0,EQ$24*12-11,1,12)) -> 27319.814 | ER44: =SUM(OFFSET($G44,0,ER$24*12-11,1,12)) -> 27866.211 | ... ET44: =SUM(OFFSET($G44,0,ET$24*12-11,1,12)) -> 28992.006
B45: Utilities: Reimbursable | E45: =SUM(OFFSET(G45,0,0,1,'Executive Summary'!$I$13+1)) -> 252491.84 | G45: 0 | H45: ='Operating Inputs'!$P28/12*'Cash Flow - Monthly'!H$8*'Executive Summary'!$C$12 -> 4006.6063 | I45: ='Operating Inputs'!$P28/12*'Cash Flow - Monthly'!I$8*'Executive Summary'!$C$12 -> 4013.2236 | J45: ='Operating Inputs'!$P28/12*'Cash Flow - Monthly'!J$8*'Executive Summary'!$C$12 -> 4019.8517 | K45: ='Operating Inputs'!$P28/12*'Cash Flow - Monthly'!K$8*'Executive Summary'!$C$12 -> 4026.4908 | L45: ='Operating Inputs'!$P28/12*'Cash Flow - Monthly'!L$8*'Executive Summary'!$C$12 -> 4033.1409 | M45: ='Operating Inputs'!$P28/12*'Cash Flow - Monthly'!M$8*'Executive Summary'!$C$12 -> 4039.802 | N45: ='Operating Inputs'!$P28/12*'Cash Flow - Monthly'!N$8*'Executive Summary'!$C$12 -> 4046.474 | O45: ='Operating Inputs'!$P28/12*'Cash Flow - Monthly'!O$8*'Executive Summary'!$C$12 -> 4053.1571 | ... EI45: ='Operating Inputs'!$P28/12*'Cash Flow - Monthly'!EI$8*'Executive Summary'!$C$12 -> 4973.4972 | EK45: =SUM(OFFSET($G45,0,EK$24*12-11,1,12)) -> 48518.427 | EL45: =SUM(OFFSET($G45,0,EL$24*12-11,1,12)) -> 49488.795 | EM45: =SUM(OFFSET($G45,0,EM$24*12-11,1,12)) -> 50478.571 | EN45: =SUM(OFFSET($G45,0,EN$24*12-11,1,12)) -> 51488.143 | EO45: =SUM(OFFSET($G45,0,EO$24*12-11,1,12)) -> 52517.906 | EP45: =SUM(OFFSET($G45,0,EP$24*12-11,1,12)) -> 53568.264 | EQ45: =SUM(OFFSET($G45,0,EQ$24*12-11,1,12)) -> 54639.629 | ER45: =SUM(OFFSET($G45,0,ER$24*12-11,1,12)) -> 55732.421 | ... ET45: =SUM(OFFSET($G45,0,ET$24*12-11,1,12)) -> 57984.011
B46: Utilities: Other | E46: =SUM(OFFSET(G46,0,0,1,'Executive Summary'!$I$13+1)) -> 18936.888 | G46: 0 | H46: ='Operating Inputs'!$P29/12*'Cash Flow - Monthly'!H$8*'Executive Summary'!$C$12 -> 300.49547 | I46: ='Operating Inputs'!$P29/12*'Cash Flow - Monthly'!I$8*'Executive Summary'!$C$12 -> 300.99177 | J46: ='Operating Inputs'!$P29/12*'Cash Flow - Monthly'!J$8*'Executive Summary'!$C$12 -> 301.48888 | K46: ='Operating Inputs'!$P29/12*'Cash Flow - Monthly'!K$8*'Executive Summary'!$C$12 -> 301.98681 | L46: ='Operating Inputs'!$P29/12*'Cash Flow - Monthly'!L$8*'Executive Summary'!$C$12 -> 302.48557 | M46: ='Operating Inputs'!$P29/12*'Cash Flow - Monthly'!M$8*'Executive Summary'!$C$12 -> 302.98515 | N46: ='Operating Inputs'!$P29/12*'Cash Flow - Monthly'!N$8*'Executive Summary'!$C$12 -> 303.48555 | O46: ='Operating Inputs'!$P29/12*'Cash Flow - Monthly'!O$8*'Executive Summary'!$C$12 -> 303.98678 | ... EI46: ='Operating Inputs'!$P29/12*'Cash Flow - Monthly'!EI$8*'Executive Summary'!$C$12 -> 373.01229 | EK46: =SUM(OFFSET($G46,0,EK$24*12-11,1,12)) -> 3638.882 | EL46: =SUM(OFFSET($G46,0,EL$24*12-11,1,12)) -> 3711.6597 | EM46: =SUM(OFFSET($G46,0,EM$24*12-11,1,12)) -> 3785.8928 | EN46: =SUM(OFFSET($G46,0,EN$24*12-11,1,12)) -> 3861.6107 | EO46: =SUM(OFFSET($G46,0,EO$24*12-11,1,12)) -> 3938.8429 | EP46: =SUM(OFFSET($G46,0,EP$24*12-11,1,12)) -> 4017.6198 | EQ46: =SUM(OFFSET($G46,0,EQ$24*12-11,1,12)) -> 4097.9722 | ER46: =SUM(OFFSET($G46,0,ER$24*12-11,1,12)) -> 4179.9316 | ... ET46: =SUM(OFFSET($G46,0,ET$24*12-11,1,12)) -> 4348.8008
B47: Total Controllable | E47: =SUM(OFFSET(G47,0,0,1,'Executive Summary'!$I$13+1)) -> 1249834.6 | G47: =SUM(G41:G46) -> 0 | H47: =SUM(H41:H46) -> 19832.701 | I47: =SUM(I41:I46) -> 19865.457 | J47: =SUM(J41:J46) -> 19898.266 | K47: =SUM(K41:K46) -> 19931.13 | L47: =SUM(L41:L46) -> 19964.048 | M47: =SUM(M41:M46) -> 19997.02 | N47: =SUM(N41:N46) -> 20030.046 | ... EI47: =SUM(EI41:EI46) -> 24618.811 | EK47: =SUM(OFFSET($G47,0,EK$24*12-11,1,12)) -> 240166.21 | EL47: =SUM(OFFSET($G47,0,EL$24*12-11,1,12)) -> 244969.54 | EM47: =SUM(OFFSET($G47,0,EM$24*12-11,1,12)) -> 249868.93 | EN47: =SUM(OFFSET($G47,0,EN$24*12-11,1,12)) -> 254866.31 | EO47: =SUM(OFFSET($G47,0,EO$24*12-11,1,12)) -> 259963.63 | EP47: =SUM(OFFSET($G47,0,EP$24*12-11,1,12)) -> 265162.9 | EQ47: =SUM(OFFSET($G47,0,EQ$24*12-11,1,12)) -> 270466.16 | ER47: =SUM(OFFSET($G47,0,ER$24*12-11,1,12)) -> 275875.49 | ... ET47: =SUM(OFFSET($G47,0,ET$24*12-11,1,12)) -> 287020.86
B48: Noncontrollable
B49: Taxes | E49: =SUM(OFFSET(G49,0,0,1,'Executive Summary'!$I$13+1)) -> 338947.66 | G49: 0 | H49: ='Executive Summary'!$I$38/12*H8 -> 5020.8203 | I49: ='Executive Summary'!$I$38/12*I8 -> 5029.1126 | J49: ='Executive Summary'!$I$38/12*J8 -> 5037.4186 | K49: ='Executive Summary'!$I$38/12*K8 -> 5045.7383 | L49: ='Executive Summary'!$I$38/12*L8 -> 5054.0717 | M49: ='Executive Summary'!$I$38/12*M8 -> 5062.4189 | N49: ='Executive Summary'!$I$38/12*N8 -> 5070.7799 | O49: ='Executive Summary'!$I$38/12*O8 -> 5079.1547 | ... S49: ='Executive Summary'!$I$38/12*S8 -> 5112.7925 | T49: ='Executive Summary'!$I$37/12*T8 -> 5572.8639 | U49: ='Executive Summary'!$I$37/12*U8 -> 5582.0679 | V49: ='Executive Summary'!$I$37/12*V8 -> 5591.2871 | W49: ='Executive Summary'!$I$37/12*W8 -> 5600.5216 | X49: ='Executive Summary'!$I$37/12*X8 -> 5609.7713 | Y49: ='Executive Summary'!$I$37/12*Y8 -> 5619.0363 | Z49: ='Executive Summary'!$I$37/12*Z8 -> 5628.3166 | AA49: ='Executive Summary'!$I$37/12*AA8 -> 5637.6122 | ... EI49: ='Executive Summary'!$I$37/12*EI8 -> 6782.0888 | EK49: =SUM(OFFSET($G49,0,EK$24*12-11,1,12)) -> 60800.159 | EL49: =SUM(OFFSET($G49,0,EL$24*12-11,1,12)) -> 67485.19 | EM49: =SUM(OFFSET($G49,0,EM$24*12-11,1,12)) -> 68834.893 | EN49: =SUM(OFFSET($G49,0,EN$24*12-11,1,12)) -> 70211.591 | EO49: =SUM(OFFSET($G49,0,EO$24*12-11,1,12)) -> 71615.823 | EP49: =SUM(OFFSET($G49,0,EP$24*12-11,1,12)) -> 73048.14 | EQ49: =SUM(OFFSET($G49,0,EQ$24*12-11,1,12)) -> 74509.102 | ER49: =SUM(OFFSET($G49,0,ER$24*12-11,1,12)) -> 75999.284 | ... ET49: =SUM(OFFSET($G49,0,ET$24*12-11,1,12)) -> 79069.655
B50: Insurance | E50: =SUM(OFFSET(G50,0,0,1,'Executive Summary'!$I$13+1)) -> 84163.947 | G50: 0 | H50: =IF('Executive Summary'!$I$55>5, 'Executive Summary'!$I$55, 'Executive Summary'!$I$49)/12*H8 -> 1335.5354 | I50: =IF('Executive Summary'!$I$55>5, 'Executive Summary'!$I$55, 'Executive Summary'!$I$49)/12*I8 -> 1337.7412 | J50: =IF('Executive Summary'!$I$55>5, 'Executive Summary'!$I$55, 'Executive Summary'!$I$49)/12*J8 -> 1339.9506 | K50: =IF('Executive Summary'!$I$55>5, 'Executive Summary'!$I$55, 'Executive Summary'!$I$49)/12*K8 -> 1342.1636 | L50: =IF('Executive Summary'!$I$55>5, 'Executive Summary'!$I$55, 'Executive Summary'!$I$49)/12*L8 -> 1344.3803 | M50: =IF('Executive Summary'!$I$55>5, 'Executive Summary'!$I$55, 'Executive Summary'!$I$49)/12*M8 -> 1346.6007 | N50: =IF('Executive Summary'!$I$55>5, 'Executive Summary'!$I$55, 'Executive Summary'!$I$49)/12*N8 -> 1348.8247 | O50: =IF('Executive Summary'!$I$55>5, 'Executive Summary'!$I$55, 'Executive Summary'!$I$49)/12*O8 -> 1351.0524 | ... EI50: =IF('Executive Summary'!$I$55>5, 'Executive Summary'!$I$55, 'Executive Summary'!$I$49)/12*EI8 -> 1657.8324 | EK50: =SUM(OFFSET($G50,0,EK$24*12-11,1,12)) -> 16172.809 | EL50: =SUM(OFFSET($G50,0,EL$24*12-11,1,12)) -> 16496.265 | EM50: =SUM(OFFSET($G50,0,EM$24*12-11,1,12)) -> 16826.19 | EN50: =SUM(OFFSET($G50,0,EN$24*12-11,1,12)) -> 17162.714 | EO50: =SUM(OFFSET($G50,0,EO$24*12-11,1,12)) -> 17505.969 | EP50: =SUM(OFFSET($G50,0,EP$24*12-11,1,12)) -> 17856.088 | EQ50: =SUM(OFFSET($G50,0,EQ$24*12-11,1,12)) -> 18213.21 | ER50: =SUM(OFFSET($G50,0,ER$24*12-11,1,12)) -> 18577.474 | ... ET50: =SUM(OFFSET($G50,0,ET$24*12-11,1,12)) -> 19328.004
B51: Property Management Fee | E51: =SUM(OFFSET(G51,0,0,1,'Executive Summary'!$I$13+1)) -> 151698.24 | G51: 0 | H51: ='Operating Inputs'!$P$34*'Cash Flow - Monthly'!H37 -> 2233.9207 | I51: ='Operating Inputs'!$P$34*'Cash Flow - Monthly'!I37 -> 2247.0013 | J51: ='Operating Inputs'!$P$34*'Cash Flow - Monthly'!J37 -> 2263.6363 | K51: ='Operating Inputs'!$P$34*'Cash Flow - Monthly'!K37 -> 2276.8874 | L51: ='Operating Inputs'!$P$34*'Cash Flow - Monthly'!L37 -> 2293.7254 | M51: ='Operating Inputs'!$P$34*'Cash Flow - Monthly'!M37 -> 2307.1759 | N51: ='Operating Inputs'!$P$34*'Cash Flow - Monthly'!N37 -> 2324.2172 | O51: ='Operating Inputs'!$P$34*'Cash Flow - Monthly'!O37 -> 2337.8673 | ... EI51: ='Operating Inputs'!$P$34*'Cash Flow - Monthly'!EI37 -> 3245.2699 | EK51: =SUM(OFFSET($G51,0,EK$24*12-11,1,12)) -> 27795.378 | EL51: =SUM(OFFSET($G51,0,EL$24*12-11,1,12)) -> 29463.457 | EM51: =SUM(OFFSET($G51,0,EM$24*12-11,1,12)) -> 30581.99 | EN51: =SUM(OFFSET($G51,0,EN$24*12-11,1,12)) -> 31474.054 | EO51: =SUM(OFFSET($G51,0,EO$24*12-11,1,12)) -> 32383.365 | EP51: =SUM(OFFSET($G51,0,EP$24*12-11,1,12)) -> 34913.577 | EQ51: =SUM(OFFSET($G51,0,EQ$24*12-11,1,12)) -> 34282.513 | ER51: =SUM(OFFSET($G51,0,ER$24*12-11,1,12)) -> 35273.941 | ... ET51: =SUM(OFFSET($G51,0,ET$24*12-11,1,12)) -> 37344.658
B52: Total Noncontrollable | E52: =SUM(OFFSET(G52,0,0,1,'Executive Summary'!$I$13+1)) -> 574809.85 | G52: =SUM(G49:G51) -> 0 | H52: =SUM(H49:H51) -> 8590.2765 | I52: =SUM(I49:I51) -> 8613.8551 | J52: =SUM(J49:J51) -> 8641.0054 | K52: =SUM(K49:K51) -> 8664.7892 | L52: =SUM(L49:L51) -> 8692.1774 | M52: =SUM(M49:M51) -> 8716.1955 | N52: =SUM(N49:N51) -> 8743.8219 | ... EI52: =SUM(EI49:EI51) -> 11685.191 | EK52: =SUM(OFFSET($G52,0,EK$24*12-11,1,12)) -> 104768.35 | EL52: =SUM(OFFSET($G52,0,EL$24*12-11,1,12)) -> 113444.91 | EM52: =SUM(OFFSET($G52,0,EM$24*12-11,1,12)) -> 116243.07 | EN52: =SUM(OFFSET($G52,0,EN$24*12-11,1,12)) -> 118848.36 | EO52: =SUM(OFFSET($G52,0,EO$24*12-11,1,12)) -> 121505.16 | EP52: =SUM(OFFSET($G52,0,EP$24*12-11,1,12)) -> 125817.8 | EQ52: =SUM(OFFSET($G52,0,EQ$24*12-11,1,12)) -> 127004.83 | ER52: =SUM(OFFSET($G52,0,ER$24*12-11,1,12)) -> 129850.7 | ... ET52: =SUM(OFFSET($G52,0,ET$24*12-11,1,12)) -> 135742.32
B53: TOTAL EXPENSES | E53: =SUM(OFFSET(G53,0,0,1,'Executive Summary'!$I$13+1)) -> 1824644.5 | G53: =SUM(G47,G52) -> 0 | H53: =SUM(H47,H52) -> 28422.978 | I53: =SUM(I47,I52) -> 28479.312 | J53: =SUM(J47,J52) -> 28539.271 | K53: =SUM(K47,K52) -> 28595.919 | L53: =SUM(L47,L52) -> 28656.225 | M53: =SUM(M47,M52) -> 28713.215 | N53: =SUM(N47,N52) -> 28773.868 | ... EI53: =SUM(EI47,EI52) -> 36304.002 | EK53: =SUM(OFFSET($G53,0,EK$24*12-11,1,12)) -> 344934.56 | EL53: =SUM(OFFSET($G53,0,EL$24*12-11,1,12)) -> 358414.45 | EM53: =SUM(OFFSET($G53,0,EM$24*12-11,1,12)) -> 366112 | EN53: =SUM(OFFSET($G53,0,EN$24*12-11,1,12)) -> 373714.67 | EO53: =SUM(OFFSET($G53,0,EO$24*12-11,1,12)) -> 381468.79 | EP53: =SUM(OFFSET($G53,0,EP$24*12-11,1,12)) -> 390980.71 | EQ53: =SUM(OFFSET($G53,0,EQ$24*12-11,1,12)) -> 397470.99 | ER53: =SUM(OFFSET($G53,0,ER$24*12-11,1,12)) -> 405726.19 | ... ET53: =SUM(OFFSET($G53,0,ET$24*12-11,1,12)) -> 422763.17
B55: NET OPERATING INCOME | E55: =SUM(OFFSET(G55,0,0,1,'Executive Summary'!$I$13+1)) -> 2509591.1 | G55: =G37-G53 -> 0 | H55: =H37-H53 -> 35403.329 | I55: =I37-I53 -> 35720.727 | J55: =J37-J53 -> 36136.051 | K55: =K37-K53 -> 36458.006 | L55: =L37-L53 -> 36878.787 | M55: =M37-M53 -> 37206.095 | N55: =N37-N53 -> 37632.339 | ... EI55: =EI37-EI53 -> 56417.995 | EK55: =SUM(OFFSET($G55,0,EK$24*12-11,1,12)) -> 449219.09 | EL55: =SUM(OFFSET($G55,0,EL$24*12-11,1,12)) -> 483398.6 | EM55: =SUM(OFFSET($G55,0,EM$24*12-11,1,12)) -> 507659.15 | EN55: =SUM(OFFSET($G55,0,EN$24*12-11,1,12)) -> 525544.01 | EO55: =SUM(OFFSET($G55,0,EO$24*12-11,1,12)) -> 543770.2 | EP55: =SUM(OFFSET($G55,0,EP$24*12-11,1,12)) -> 606550.05 | EQ55: =SUM(OFFSET($G55,0,EQ$24*12-11,1,12)) -> 582029.39 | ER55: =SUM(OFFSET($G55,0,ER$24*12-11,1,12)) -> 602100.71 | ... ET55: =SUM(OFFSET($G55,0,ET$24*12-11,1,12)) -> 644227.06
B56: Yield on Purchase Price | E56: =AVERAGE(OFFSET(G56,0,0,1,'Executive Summary'!$I$13+1))*12 -> 0.075761239 | H56: =H55/'Executive Summary'!$C$30 -> 0.0053438987 | I56: =I55/'Executive Summary'!$C$30 -> 0.0053918078 | J56: =J55/'Executive Summary'!$C$30 -> 0.0054544983 | K56: =K55/'Executive Summary'!$C$30 -> 0.0055030952 | L56: =L55/'Executive Summary'!$C$30 -> 0.0055666093 | M56: =M55/'Executive Summary'!$C$30 -> 0.0056160144 | N56: =N55/'Executive Summary'!$C$30 -> 0.005680353 | O56: =O55/'Executive Summary'!$C$30 -> 0.0057305671 | ... EI56: =EI55/'Executive Summary'!$C$30 -> 0.0085159238 | EK56: =EK55/'Executive Summary'!$C$30 -> 0.067806655 | EL56: =EL55/'Executive Summary'!$C$30 -> 0.072965827 | EM56: =EM55/'Executive Summary'!$C$30 -> 0.076627796 | EN56: =EN55/'Executive Summary'!$C$30 -> 0.079327398 | EO56: =EO55/'Executive Summary'!$C$30 -> 0.082078521 | EP56: =EP55/'Executive Summary'!$C$30 -> 0.091554725 | EQ56: =EQ55/'Executive Summary'!$C$30 -> 0.087853493 | ER56: =ER55/'Executive Summary'!$C$30 -> 0.090883126 | ... ET56: =ET55/'Executive Summary'!$C$30 -> 0.09724182
B57: Yield on Total Cost | E57: =AVERAGE(OFFSET(G57,0,0,1,'Executive Summary'!$I$13+1))*12 -> 0.071618194 | H57: =H55/'Executive Summary'!$I$23 -> 0.0050516647 | I57: =I55/'Executive Summary'!$I$23 -> 0.0050969538 | J57: =J55/'Executive Summary'!$I$23 -> 0.005156216 | K57: =K55/'Executive Summary'!$I$23 -> 0.0052021554 | L57: =L55/'Executive Summary'!$I$23 -> 0.0052621962 | M57: =M55/'Executive Summary'!$I$23 -> 0.0053088996 | N57: =N55/'Executive Summary'!$I$23 -> 0.0053697198 | O57: =O55/'Executive Summary'!$I$23 -> 0.0054171879 | ... EI57: =EI55/'Executive Summary'!$I$23 -> 0.0080502258 | EK57: =EK55/'Executive Summary'!$I$23 -> 0.064098611 | EL57: =EL55/'Executive Summary'!$I$23 -> 0.068975651 | EM57: =EM55/'Executive Summary'!$I$23 -> 0.072437363 | EN57: =EN55/'Executive Summary'!$I$23 -> 0.074989336 | EO57: =EO55/'Executive Summary'!$I$23 -> 0.077590012 | EP57: =EP55/'Executive Summary'!$I$23 -> 0.086548005 | EQ57: =EQ55/'Executive Summary'!$I$23 -> 0.083049177 | ER57: =ER55/'Executive Summary'!$I$23 -> 0.085913132 | ... ET57: =ET55/'Executive Summary'!$I$23 -> 0.091924098
B58: Value @ 7 CAP | EK58: =EK55/7.25% -> 6196125.4 | EL58: =EL55/7.25% -> 6667566.9 | EM58: =EM55/7.25% -> 7002195.2 | EN58: =EN55/7.25% -> 7248882.9 | EO58: =EO55/7.25% -> 7500278.6 | EP58: =EP55/7.25% -> 8366207.6 | EQ58: =EQ55/7.25% -> 8027991.6 | ER58: =ER55/7.25% -> 8304837.4 | ... ET58: =ET55/7.25% -> 8885890.4
B59: Exit NOI | E59: =SUM(OFFSET(G59,0,0,1,'Executive Summary'!$I$13+1)) -> 606550.05 | G59: =SUM(H55:S55)*(G$4='Executive Summary'!$I$13) -> 0 | H59: =SUM(I55:T55)*(H$4='Executive Summary'!$I$13) -> 0 | I59: =SUM(J55:U55)*(I$4='Executive Summary'!$I$13) -> 0 | J59: =SUM(K55:V55)*(J$4='Executive Summary'!$I$13) -> 0 | K59: =SUM(L55:W55)*(K$4='Executive Summary'!$I$13) -> 0 | L59: =SUM(M55:X55)*(L$4='Executive Summary'!$I$13) -> 0 | M59: =SUM(N55:Y55)*(M$4='Executive Summary'!$I$13) -> 0 | N59: =SUM(O55:Z55)*(N$4='Executive Summary'!$I$13) -> 0 | ... EI59: =SUM(EJ55:EU55)*(EI$4='Executive Summary'!$I$13) -> 0 | EK59: =SUM(OFFSET($G59,0,EK$24*12-11,1,12)) -> 0 | EL59: =SUM(OFFSET($G59,0,EL$24*12-11,1,12)) -> 0 | EM59: =SUM(OFFSET($G59,0,EM$24*12-11,1,12)) -> 0 | EN59: =SUM(OFFSET($G59,0,EN$24*12-11,1,12)) -> 0 | EO59: =SUM(OFFSET($G59,0,EO$24*12-11,1,12)) -> 606550.05 | EP59: =SUM(OFFSET($G59,0,EP$24*12-11,1,12)) -> 0 | EQ59: =SUM(OFFSET($G59,0,EQ$24*12-11,1,12)) -> 0 | ER59: =SUM(OFFSET($G59,0,ER$24*12-11,1,12)) -> 0 | ... ET59: =SUM(OFFSET($G59,0,ET$24*12-11,1,12)) -> 0
B61: Capital Expenditures
B62: Exterior Value-Add | E62: =SUM(OFFSET(G62,0,0,1,'Executive Summary'!$I$13+1)) -> 0 | G62: 0 | H62: ='Renovation Plan'!$J$21/12*H$8*(H4<='Executive Summary'!$I$13) -> 0 | I62: ='Renovation Plan'!$J$21/12*I$8*(I4<='Executive Summary'!$I$13) -> 0 | J62: ='Renovation Plan'!$J$21/12*J$8*(J4<='Executive Summary'!$I$13) -> 0 | K62: ='Renovation Plan'!$J$21/12*K$8*(K4<='Executive Summary'!$I$13) -> 0 | L62: ='Renovation Plan'!$J$21/12*L$8*(L4<='Executive Summary'!$I$13) -> 0 | M62: ='Renovation Plan'!$J$21/12*M$8*(M4<='Executive Summary'!$I$13) -> 0 | N62: ='Renovation Plan'!$J$21/12*N$8*(N4<='Executive Summary'!$I$13) -> 0 | O62: ='Renovation Plan'!$J$21/12*O$8*(O4<='Executive Summary'!$I$13) -> 0 | ... EI62: ='Renovation Plan'!$J$21/12*EI$8*(EI4<='Executive Summary'!$I$13) -> 0 | EK62: =SUM(OFFSET($G62,0,EK$24*12-11,1,12)) -> 0 | EL62: =SUM(OFFSET($G62,0,EL$24*12-11,1,12)) -> 0 | EM62: =SUM(OFFSET($G62,0,EM$24*12-11,1,12)) -> 0 | EN62: =SUM(OFFSET($G62,0,EN$24*12-11,1,12)) -> 0 | EO62: =SUM(OFFSET($G62,0,EO$24*12-11,1,12)) -> 0 | EP62: =SUM(OFFSET($G62,0,EP$24*12-11,1,12)) -> 0 | EQ62: =SUM(OFFSET($G62,0,EQ$24*12-11,1,12)) -> 0 | ER62: =SUM(OFFSET($G62,0,ER$24*12-11,1,12)) -> 0 | ... ET62: =SUM(OFFSET($G62,0,ET$24*12-11,1,12)) -> 0
B63: Asset Preservation | E63: =SUM(OFFSET(G63,0,0,1,'Executive Summary'!$I$13+1)) -> 383250 | G63: ='Renovation Plan'!I17 -> 383250 | H63: ='Renovation Plan'!$J$21/12*H$8*(H4<='Executive Summary'!$I$13) -> 0 | I63: ='Renovation Plan'!$J$21/12*I$8*(I4<='Executive Summary'!$I$13) -> 0 | J63: ='Renovation Plan'!$J$21/12*J$8*(J4<='Executive Summary'!$I$13) -> 0 | K63: ='Renovation Plan'!$J$21/12*K$8*(K4<='Executive Summary'!$I$13) -> 0 | L63: ='Renovation Plan'!$J$21/12*L$8*(L4<='Executive Summary'!$I$13) -> 0 | M63: ='Renovation Plan'!$J$21/12*M$8*(M4<='Executive Summary'!$I$13) -> 0 | N63: ='Renovation Plan'!$J$21/12*N$8*(N4<='Executive Summary'!$I$13) -> 0 | O63: ='Renovation Plan'!$J$21/12*O$8*(O4<='Executive Summary'!$I$13) -> 0 | ... EI63: ='Renovation Plan'!$J$21/12*EI$8*(EI4<='Executive Summary'!$I$13) -> 0 | EK63: =SUM(OFFSET($G63,0,EK$24*12-11,1,12)) -> 0 | EL63: =SUM(OFFSET($G63,0,EL$24*12-11,1,12)) -> 0 | EM63: =SUM(OFFSET($G63,0,EM$24*12-11,1,12)) -> 0 | EN63: =SUM(OFFSET($G63,0,EN$24*12-11,1,12)) -> 0 | EO63: =SUM(OFFSET($G63,0,EO$24*12-11,1,12)) -> 0 | EP63: =SUM(OFFSET($G63,0,EP$24*12-11,1,12)) -> 0 | EQ63: =SUM(OFFSET($G63,0,EQ$24*12-11,1,12)) -> 0 | ER63: =SUM(OFFSET($G63,0,ER$24*12-11,1,12)) -> 0 | ... ET63: =SUM(OFFSET($G63,0,ET$24*12-11,1,12)) -> 0
B64: Unit Upgrades from Cash Flow | E64: =SUM('Renovation Plan'!J17:K17) -> 0 | H64: =H9*'Renovation Plan'!$D$24*H8*(H4<='Executive Summary'!$I$13) -> 0 | I64: =I9*'Renovation Plan'!$D$24*I8*(I4<='Executive Summary'!$I$13) -> 0 | J64: =J9*'Renovation Plan'!$D$24*J8*(J4<='Executive Summary'!$I$13) -> 0 | K64: =K9*'Renovation Plan'!$D$24*K8*(K4<='Executive Summary'!$I$13) -> 0 | L64: =L9*'Renovation Plan'!$D$24*L8*(L4<='Executive Summary'!$I$13) -> 0 | M64: =M9*'Renovation Plan'!$D$24*M8*(M4<='Executive Summary'!$I$13) -> 0 | N64: =N9*'Renovation Plan'!$D$24*N8*(N4<='Executive Summary'!$I$13) -> 0 | O64: =O9*'Renovation Plan'!$D$24*O8*(O4<='Executive Summary'!$I$13) -> 0 | ... EI64: =EI9*'Renovation Plan'!$D$24*EI8*(EI4<='Executive Summary'!$I$13) -> 0 | EK64: ='Renovation Plan'!J17 -> 0 | EL64: ='Renovation Plan'!K17 -> 0 | EM64: =SUM(OFFSET($G64,0,EM$24*12-11,1,12)) -> 0 | EN64: =SUM(OFFSET($G64,0,EN$24*12-11,1,12)) -> 0 | EO64: =SUM(OFFSET($G64,0,EO$24*12-11,1,12)) -> 0 | EP64: =SUM(OFFSET($G64,0,EP$24*12-11,1,12)) -> 0 | EQ64: =SUM(OFFSET($G64,0,EQ$24*12-11,1,12)) -> 0 | ER64: =SUM(OFFSET($G64,0,ER$24*12-11,1,12)) -> 0 | ES64: =SUM(OFFSET($G64,0,ES$24*12-11,1,12)) -> 0 | ET64: =SUM(OFFSET($G64,0,ET$24*12-11,1,12)) -> 0
B65: Recurring Reserves | E65: =SUM(OFFSET(G65,0,0,1,'Executive Summary'!$I$13+1)) -> 115725.43 | H65: ='Executive Summary'!$C$54/12*'Executive Summary'!$C$12*H8*(H4<='Executive Summary'!$I$13) -> 1836.3612 | I65: ='Executive Summary'!$C$54/12*'Executive Summary'!$C$12*I8*(I4<='Executive Summary'!$I$13) -> 1839.3941 | J65: ='Executive Summary'!$C$54/12*'Executive Summary'!$C$12*J8*(J4<='Executive Summary'!$I$13) -> 1842.432 | K65: ='Executive Summary'!$C$54/12*'Executive Summary'!$C$12*K8*(K4<='Executive Summary'!$I$13) -> 1845.475 | L65: ='Executive Summary'!$C$54/12*'Executive Summary'!$C$12*L8*(L4<='Executive Summary'!$I$13) -> 1848.5229 | M65: ='Executive Summary'!$C$54/12*'Executive Summary'!$C$12*M8*(M4<='Executive Summary'!$I$13) -> 1851.5759 | N65: ='Executive Summary'!$C$54/12*'Executive Summary'!$C$12*N8*(N4<='Executive Summary'!$I$13) -> 1854.6339 | O65: ='Executive Summary'!$C$54/12*'Executive Summary'!$C$12*O8*(O4<='Executive Summary'!$I$13) -> 1857.697 | ... BO65: ='Executive Summary'!$C$54/12*'Executive Summary'!$C$12*BO8*(BO4<='Executive Summary'!$I$13) -> 2024.1481 | BP65: ='Executive Summary'!$C$55/12*'Executive Summary'!$C$12*BP8*(BP4<='Executive Summary'!$I$13) -> 0 | BQ65: ='Executive Summary'!$C$55/12*'Executive Summary'!$C$12*BQ8*(BQ4<='Executive Summary'!$I$13) -> 0 | BR65: ='Executive Summary'!$C$55/12*'Executive Summary'!$C$12*BR8*(BR4<='Executive Summary'!$I$13) -> 0 | BS65: ='Executive Summary'!$C$55/12*'Executive Summary'!$C$12*BS8*(BS4<='Executive Summary'!$I$13) -> 0 | BT65: ='Executive Summary'!$C$55/12*'Executive Summary'!$C$12*BT8*(BT4<='Executive Summary'!$I$13) -> 0 | BU65: ='Executive Summary'!$C$55/12*'Executive Summary'!$C$12*BU8*(BU4<='Executive Summary'!$I$13) -> 0 | BV65: ='Executive Summary'!$C$55/12*'Executive Summary'!$C$12*BV8*(BV4<='Executive Summary'!$I$13) -> 0 | BW65: ='Executive Summary'!$C$55/12*'Executive Summary'!$C$12*BW8*(BW4<='Executive Summary'!$I$13) -> 0 | ... EI65: ='Executive Summary'!$C$55/12*'Executive Summary'!$C$12*EI8*(EI4<='Executive Summary'!$I$13) -> 0 | EK65: =SUM(OFFSET($G65,0,EK$24*12-11,1,12)) -> 22237.612 | EL65: =SUM(OFFSET($G65,0,EL$24*12-11,1,12)) -> 22682.365 | EM65: =SUM(OFFSET($G65,0,EM$24*12-11,1,12)) -> 23136.012 | EN65: =SUM(OFFSET($G65,0,EN$24*12-11,1,12)) -> 23598.732 | EO65: =SUM(OFFSET($G65,0,EO$24*12-11,1,12)) -> 24070.707 | EP65: =SUM(OFFSET($G65,0,EP$24*12-11,1,12)) -> 0 | EQ65: =SUM(OFFSET($G65,0,EQ$24*12-11,1,12)) -> 0 | ER65: =SUM(OFFSET($G65,0,ER$24*12-11,1,12)) -> 0 | ... ET65: =SUM(OFFSET($G65,0,ET$24*12-11,1,12)) -> 0
B66: Total Capital Expenditures | E66: =SUM(OFFSET(G66,0,0,1,'Executive Summary'!$I$13+1)) -> 498975.43 | G66: =SUM(G62:G65) -> 383250 | H66: =SUM(H62:H65) -> 1836.3612 | I66: =SUM(I62:I65) -> 1839.3941 | J66: =SUM(J62:J65) -> 1842.432 | K66: =SUM(K62:K65) -> 1845.475 | L66: =SUM(L62:L65) -> 1848.5229 | M66: =SUM(M62:M65) -> 1851.5759 | N66: =SUM(N62:N65) -> 1854.6339 | ... EI66: =SUM(EI62:EI65) -> 0 | EK66: =SUM(EK62:EK65) -> 22237.612 | EL66: =SUM(EL62:EL65) -> 22682.365 | EM66: =SUM(EM62:EM65) -> 23136.012 | EN66: =SUM(EN62:EN65) -> 23598.732 | EO66: =SUM(EO62:EO65) -> 24070.707 | EP66: =SUM(EP62:EP65) -> 0 | EQ66: =SUM(EQ62:EQ65) -> 0 | ER66: =SUM(ER62:ER65) -> 0 | ... ET66: =SUM(ET62:ET65) -> 0
B68: Net Cash Flow Before Debt Service | E68: =SUM(OFFSET(G68,0,0,1,'Executive Summary'!$I$13+1)) -> 2010615.6 | G68: =(G55-G66)*(G4<='Executive Summary'!$I$13) -> -383250 | H68: =(H55-H66)*(H4<='Executive Summary'!$I$13) -> 33566.968 | I68: =(I55-I66)*(I4<='Executive Summary'!$I$13) -> 33881.332 | J68: =(J55-J66)*(J4<='Executive Summary'!$I$13) -> 34293.619 | K68: =(K55-K66)*(K4<='Executive Summary'!$I$13) -> 34612.531 | L68: =(L55-L66)*(L4<='Executive Summary'!$I$13) -> 35030.264 | M68: =(M55-M66)*(M4<='Executive Summary'!$I$13) -> 35354.519 | N68: =(N55-N66)*(N4<='Executive Summary'!$I$13) -> 35777.705 | ... EI68: =(EI55-EI66)*(EI4<='Executive Summary'!$I$13) -> 0 | EK68: =SUM(OFFSET($G68,0,EK$24*12-11,1,12)) -> 426981.48 | EL68: =SUM(OFFSET($G68,0,EL$24*12-11,1,12)) -> 460716.24 | EM68: =SUM(OFFSET($G68,0,EM$24*12-11,1,12)) -> 484523.14 | EN68: =SUM(OFFSET($G68,0,EN$24*12-11,1,12)) -> 501945.28 | EO68: =SUM(OFFSET($G68,0,EO$24*12-11,1,12)) -> 519699.5 | EP68: =SUM(OFFSET($G68,0,EP$24*12-11,1,12)) -> 0 | EQ68: =SUM(OFFSET($G68,0,EQ$24*12-11,1,12)) -> 0 | ER68: =SUM(OFFSET($G68,0,ER$24*12-11,1,12)) -> 0 | ... ET68: =SUM(OFFSET($G68,0,ET$24*12-11,1,12)) -> 0
B70: Financing Cash Flow
B71: Loan Proceeds | E71: =SUM(OFFSET(G71,0,0,1,'Executive Summary'!$I$13+1)) -> 5200000 | G71: =G100 -> 5200000 | H71: =H100 -> 0 | I71: =I100 -> 0 | J71: =J100 -> 0 | K71: =K100 -> 0 | L71: =L100 -> 0 | M71: =M100 -> 0 | N71: =N100 -> 0 | ... EI71: =EI100 -> 0 | EK71: =SUM(OFFSET($G71,0,EK$24*12-11,1,12)) -> 0 | EL71: =SUM(OFFSET($G71,0,EL$24*12-11,1,12)) -> 0 | EM71: =SUM(OFFSET($G71,0,EM$24*12-11,1,12)) -> 0 | EN71: =SUM(OFFSET($G71,0,EN$24*12-11,1,12)) -> 0 | EO71: =SUM(OFFSET($G71,0,EO$24*12-11,1,12)) -> 0 | EP71: =SUM(OFFSET($G71,0,EP$24*12-11,1,12)) -> 0 | EQ71: =SUM(OFFSET($G71,0,EQ$24*12-11,1,12)) -> 0 | ER71: =SUM(OFFSET($G71,0,ER$24*12-11,1,12)) -> 0 | ... ET71: =SUM(OFFSET($G71,0,ET$24*12-11,1,12)) -> 0
B72: Loan Closing Costs | E72: =SUM(OFFSET(G72,0,0,1,'Executive Summary'!$I$13+1)) -> -39000 | G72: =MAX(-'Executive Summary'!D44,-'Executive Summary'!D36-IF('Executive Summary'!L17=0,C139*'Executive Summary'!L18,0)) -> -39000 | H72: =-($C$139*'Executive Summary'!$L$18)*('Executive Summary'!$L$17=H4) -> 0 | I72: =-($C$139*'Executive Summary'!$L$18)*('Executive Summary'!$L$17=I4) -> 0 | J72: =-($C$139*'Executive Summary'!$L$18)*('Executive Summary'!$L$17=J4) -> 0 | K72: =-($C$139*'Executive Summary'!$L$18)*('Executive Summary'!$L$17=K4) -> 0 | L72: =-($C$139*'Executive Summary'!$L$18)*('Executive Summary'!$L$17=L4) -> 0 | M72: =-($C$139*'Executive Summary'!$L$18)*('Executive Summary'!$L$17=M4) -> 0 | N72: =-($C$139*'Executive Summary'!$L$18)*('Executive Summary'!$L$17=N4) -> 0 | O72: =-($C$139*'Executive Summary'!$L$18)*('Executive Summary'!$L$17=O4) -> 0 | ... EI72: =-($C$139*'Executive Summary'!$L$18)*('Executive Summary'!$L$17=EI4) -> 0 | EK72: =SUM(OFFSET($G72,0,EK$24*12-11,1,12)) -> 0 | EL72: =SUM(OFFSET($G72,0,EL$24*12-11,1,12)) -> 0 | EM72: =SUM(OFFSET($G72,0,EM$24*12-11,1,12)) -> 0 | EN72: =SUM(OFFSET($G72,0,EN$24*12-11,1,12)) -> 0 | EO72: =SUM(OFFSET($G72,0,EO$24*12-11,1,12)) -> 0 | EP72: =SUM(OFFSET($G72,0,EP$24*12-11,1,12)) -> 0 | EQ72: =SUM(OFFSET($G72,0,EQ$24*12-11,1,12)) -> 0 | ER72: =SUM(OFFSET($G72,0,ER$24*12-11,1,12)) -> 0 | ... ET72: =SUM(OFFSET($G72,0,ET$24*12-11,1,12)) -> 0
B73: Other Reserves | E73: =SUM(OFFSET(G73,0,0,1,'Executive Summary'!$I$13+1)) -> 0 | G73: =-'Executive Summary'!$D$43 -> -16000 | H73: ='Executive Summary'!$D$43*(H4='Executive Summary'!$I$13) -> 0 | I73: ='Executive Summary'!$D$43*(I4='Executive Summary'!$I$13) -> 0 | J73: ='Executive Summary'!$D$43*(J4='Executive Summary'!$I$13) -> 0 | K73: ='Executive Summary'!$D$43*(K4='Executive Summary'!$I$13) -> 0 | L73: ='Executive Summary'!$D$43*(L4='Executive Summary'!$I$13) -> 0 | M73: ='Executive Summary'!$D$43*(M4='Executive Summary'!$I$13) -> 0 | N73: ='Executive Summary'!$D$43*(N4='Executive Summary'!$I$13) -> 0 | O73: ='Executive Summary'!$D$43*(O4='Executive Summary'!$I$13) -> 0 | ... EI73: ='Executive Summary'!$D$43*(EI4='Executive Summary'!$I$13) -> 0 | EK73: =SUM(OFFSET($G73,0,EK$24*12-11,1,12)) -> 0 | EL73: =SUM(OFFSET($G73,0,EL$24*12-11,1,12)) -> 0 | EM73: =SUM(OFFSET($G73,0,EM$24*12-11,1,12)) -> 0 | EN73: =SUM(OFFSET($G73,0,EN$24*12-11,1,12)) -> 0 | EO73: =SUM(OFFSET($G73,0,EO$24*12-11,1,12)) -> 16000 | EP73: =SUM(OFFSET($G73,0,EP$24*12-11,1,12)) -> 0 | EQ73: =SUM(OFFSET($G73,0,EQ$24*12-11,1,12)) -> 0 | ER73: =SUM(OFFSET($G73,0,ER$24*12-11,1,12)) -> 0 | ... ET73: =SUM(OFFSET($G73,0,ET$24*12-11,1,12)) -> 0
B74: Interest Expense | E74: =SUM(OFFSET(G74,0,0,1,'Executive Summary'!$I$13+1)) -> -1252606.8 | G74: =G102 -> 0 | H74: =H102 -> -21016.667 | I74: =I102 -> -21016.667 | J74: =J102 -> -21016.667 | K74: =K102 -> -21016.667 | L74: =L102 -> -21016.667 | M74: =M102 -> -21016.667 | N74: =N102 -> -21016.667 | ... EI74: =EI102 -> 0 | EK74: =SUM(OFFSET($G74,0,EK$24*12-11,1,12)) -> -252200 | EL74: =SUM(OFFSET($G74,0,EL$24*12-11,1,12)) -> -252200 | EM74: =SUM(OFFSET($G74,0,EM$24*12-11,1,12)) -> -252200 | EN74: =SUM(OFFSET($G74,0,EN$24*12-11,1,12)) -> -250225.42 | EO74: =SUM(OFFSET($G74,0,EO$24*12-11,1,12)) -> -245781.33 | EP74: =SUM(OFFSET($G74,0,EP$24*12-11,1,12)) -> 0 | EQ74: =SUM(OFFSET($G74,0,EQ$24*12-11,1,12)) -> 0 | ER74: =SUM(OFFSET($G74,0,ER$24*12-11,1,12)) -> 0 | ... ET74: =SUM(OFFSET($G74,0,ET$24*12-11,1,12)) -> 0
B75: Loan Repayment | E75: =SUM(OFFSET(G75,0,0,1,'Executive Summary'!$I$13+1)) -> -5200000 | G75: =G101 -> 0 | H75: =H101 -> 0 | I75: =I101 -> 0 | J75: =J101 -> 0 | K75: =K101 -> 0 | L75: =L101 -> 0 | M75: =M101 -> 0 | N75: =N101 -> 0 | ... EI75: =EI101 -> 0 | EK75: =SUM(OFFSET($G75,0,EK$24*12-11,1,12)) -> 0 | EL75: =SUM(OFFSET($G75,0,EL$24*12-11,1,12)) -> 0 | EM75: =SUM(OFFSET($G75,0,EM$24*12-11,1,12)) -> 0 | EN75: =SUM(OFFSET($G75,0,EN$24*12-11,1,12)) -> -89611.55 | EO75: =SUM(OFFSET($G75,0,EO$24*12-11,1,12)) -> -5110388.5 | EP75: =SUM(OFFSET($G75,0,EP$24*12-11,1,12)) -> 0 | EQ75: =SUM(OFFSET($G75,0,EQ$24*12-11,1,12)) -> 0 | ER75: =SUM(OFFSET($G75,0,ER$24*12-11,1,12)) -> 0 | ... ET75: =SUM(OFFSET($G75,0,ET$24*12-11,1,12)) -> 0
B76: Capital/Deficit Reserve | E76: =SUM(G76:EI76) -> 0 | G76: 0 | H76: =H64 -> 0 | I76: =I64 -> 0 | J76: =J64 -> 0 | K76: =K64 -> 0 | L76: =L64 -> 0 | M76: =M64 -> 0 | N76: =N64 -> 0 | O76: =O64 -> 0 | ... U76: =U64 -> 0 | V76: =-(V109+V110) -> 0 | W76: =-(W109+W110) -> 0 | X76: =-(X109+X110) -> 0 | Y76: =-(Y109+Y110) -> 0 | Z76: =-(Z109+Z110) -> 0 | AA76: =-(AA109+AA110) -> 0 | AB76: =-(AB109+AB110) -> 0 | AC76: =-(AC109+AC110) -> 0 | ... EI76: =-(EI109+EI110) -> 0 | EK76: =SUM(OFFSET($G76,0,EK$24*12-11,1,12)) -> 0 | EL76: =SUM(OFFSET($G76,0,EL$24*12-11,1,12)) -> 0 | EM76: =SUM(OFFSET($G76,0,EM$24*12-11,1,12)) -> 0 | EN76: =SUM(OFFSET($G76,0,EN$24*12-11,1,12)) -> 0 | EO76: =SUM(OFFSET($G76,0,EO$24*12-11,1,12)) -> 0 | EP76: =SUM(OFFSET($G76,0,EP$24*12-11,1,12)) -> 0 | EQ76: =SUM(OFFSET($G76,0,EQ$24*12-11,1,12)) -> 0 | ER76: =SUM(OFFSET($G76,0,ER$24*12-11,1,12)) -> 0 | ... ET76: =SUM(OFFSET($G76,0,ET$24*12-11,1,12)) -> 0
